Workbook

Sheet 00_Summary
A1: AI Finance Forum mockup - QC summary
A2: Reviewed 28 July 2026 against the live API. 47 findings raised, 62 calculations reconciled, 31 manual tests to run.
A3: All counts below recalculate from 01_Findings. Update that sheet and this page follows.
A5: Headline
A6: Total findings | D6: Demo blockers | G6: Critical | J6: Still open
A7: =COUNTA('01_Findings'!$F$5:$F$66) | D7: =COUNTIF('01_Findings'!$G$5:$G$66,"Yes") | G7: =COUNTIF('01_Findings'!$F$5:$F$66,"Critical") | J7: =COUNTIF('01_Findings'!$N$5:$N$66,"Open")
A8: of 47 | D8: of 47 | G8: of 47 | J8: of 47
A10: By severity | G10: By agent
A11: Severity | B11: Total | C11: Blockers | D11: Open | E11: Closed | G11: Agent | H11: Total | I11: Blockers | J11: Open
A12: Critical | B12: =COUNTIF('01_Findings'!$F$5:$F$66,A12) | C12: =COUNTIFS('01_Findings'!$F$5:$F$66,A12,'01_Findings'!$G$5:$G$66,"Yes") | D12: =COUNTIFS('01_Findings'!$F$5:$F$66,A12,'01_Findings'!$N$5:$N$66,"Open") | E12: =COUNTIFS('01_Findings'!$F$5:$F$66,A12,'01_Findings'!$N$5:$N$66,"Closed") | G12: Finance | H12: =COUNTIF('01_Findings'!$C$5:$C$66,G12) | I12: =COUNTIFS('01_Findings'!$C$5:$C$66,G12,'01_Findings'!$G$5:$G$66,"Yes") | J12: =COUNTIFS('01_Findings'!$C$5:$C$66,G12,'01_Findings'!$N$5:$N$66,"Open")
A13: High | B13: =COUNTIF('01_Findings'!$F$5:$F$66,A13) | C13: =COUNTIFS('01_Findings'!$F$5:$F$66,A13,'01_Findings'!$G$5:$G$66,"Yes") | D13: =COUNTIFS('01_Findings'!$F$5:$F$66,A13,'01_Findings'!$N$5:$N$66,"Open") | E13: =COUNTIFS('01_Findings'!$F$5:$F$66,A13,'01_Findings'!$N$5:$N$66,"Closed") | G13: Collection | H13: =COUNTIF('01_Findings'!$C$5:$C$66,G13) | I13: =COUNTIFS('01_Findings'!$C$5:$C$66,G13,'01_Findings'!$G$5:$G$66,"Yes") | J13: =COUNTIFS('01_Findings'!$C$5:$C$66,G13,'01_Findings'!$N$5:$N$66,"Open")
A14: Medium | B14: =COUNTIF('01_Findings'!$F$5:$F$66,A14) | C14: =COUNTIFS('01_Findings'!$F$5:$F$66,A14,'01_Findings'!$G$5:$G$66,"Yes") | D14: =COUNTIFS('01_Findings'!$F$5:$F$66,A14,'01_Findings'!$N$5:$N$66,"Open") | E14: =COUNTIFS('01_Findings'!$F$5:$F$66,A14,'01_Findings'!$N$5:$N$66,"Closed") | G14: Leakage | H14: =COUNTIF('01_Findings'!$C$5:$C$66,G14) | I14: =COUNTIFS('01_Findings'!$C$5:$C$66,G14,'01_Findings'!$G$5:$G$66,"Yes") | J14: =COUNTIFS('01_Findings'!$C$5:$C$66,G14,'01_Findings'!$N$5:$N$66,"Open")
A15: Low | B15: =COUNTIF('01_Findings'!$F$5:$F$66,A15) | C15: =COUNTIFS('01_Findings'!$F$5:$F$66,A15,'01_Findings'!$G$5:$G$66,"Yes") | D15: =COUNTIFS('01_Findings'!$F$5:$F$66,A15,'01_Findings'!$N$5:$N$66,"Open") | E15: =COUNTIFS('01_Findings'!$F$5:$F$66,A15,'01_Findings'!$N$5:$N$66,"Closed") | G15: Treasury | H15: =COUNTIF('01_Findings'!$C$5:$C$66,G15) | I15: =COUNTIFS('01_Findings'!$C$5:$C$66,G15,'01_Findings'!$G$5:$G$66,"Yes") | J15: =COUNTIFS('01_Findings'!$C$5:$C$66,G15,'01_Findings'!$N$5:$N$66,"Open")
A16: Total | B16: =SUM(B12:B15) | C16: =SUM(C12:C15) | D16: =SUM(D12:D15) | E16: =SUM(E12:E15) | G16: All | H16: =COUNTIF('01_Findings'!$C$5:$C$66,G16) | I16: =COUNTIFS('01_Findings'!$C$5:$C$66,G16,'01_Findings'!$G$5:$G$66,"Yes") | J16: =COUNTIFS('01_Findings'!$C$5:$C$66,G16,'01_Findings'!$N$5:$N$66,"Open")
G17: Finance + Collection | H17: =COUNTIF('01_Findings'!$C$5:$C$66,G17) | I17: =COUNTIFS('01_Findings'!$C$5:$C$66,G17,'01_Findings'!$G$5:$G$66,"Yes") | J17: =COUNTIFS('01_Findings'!$C$5:$C$66,G17,'01_Findings'!$N$5:$N$66,"Open")
G18: Collection + Treasury | H18: =COUNTIF('01_Findings'!$C$5:$C$66,G18) | I18: =COUNTIFS('01_Findings'!$C$5:$C$66,G18,'01_Findings'!$G$5:$G$66,"Yes") | J18: =COUNTIFS('01_Findings'!$C$5:$C$66,G18,'01_Findings'!$N$5:$N$66,"Open")
A19: By QC area from the brief
A20: QC area | B20: Total | C20: Blockers | D20: Open
A21: a. Formula consistency | B21: =COUNTIF('01_Findings'!$D$5:$D$66,A21) | C21: =COUNTIFS('01_Findings'!$D$5:$D$66,A21,'01_Findings'!$G$5:$G$66,"Yes") | D21: =COUNTIFS('01_Findings'!$D$5:$D$66,A21,'01_Findings'!$N$5:$N$66,"Open")
A22: b. Chart accuracy | B22: =COUNTIF('01_Findings'!$D$5:$D$66,A22) | C22: =COUNTIFS('01_Findings'!$D$5:$D$66,A22,'01_Findings'!$G$5:$G$66,"Yes") | D22: =COUNTIFS('01_Findings'!$D$5:$D$66,A22,'01_Findings'!$N$5:$N$66,"Open")
A23: c. Button / menu / function | B23: =COUNTIF('01_Findings'!$D$5:$D$66,A23) | C23: =COUNTIFS('01_Findings'!$D$5:$D$66,A23,'01_Findings'!$G$5:$G$66,"Yes") | D23: =COUNTIFS('01_Findings'!$D$5:$D$66,A23,'01_Findings'!$N$5:$N$66,"Open")
A24: d. Prompt & response | B24: =COUNTIF('01_Findings'!$D$5:$D$66,A24) | C24: =COUNTIFS('01_Findings'!$D$5:$D$66,A24,'01_Findings'!$G$5:$G$66,"Yes") | D24: =COUNTIFS('01_Findings'!$D$5:$D$66,A24,'01_Findings'!$N$5:$N$66,"Open")
A25: f. Dataset | B25: =COUNTIF('01_Findings'!$D$5:$D$66,A25) | C25: =COUNTIFS('01_Findings'!$D$5:$D$66,A25,'01_Findings'!$G$5:$G$66,"Yes") | D25: =COUNTIFS('01_Findings'!$D$5:$D$66,A25,'01_Findings'!$N$5:$N$66,"Open")
A26: g. Filters | B26: =COUNTIF('01_Findings'!$D$5:$D$66,A26) | C26: =COUNTIFS('01_Findings'!$D$5:$D$66,A26,'01_Findings'!$G$5:$G$66,"Yes") | D26: =COUNTIFS('01_Findings'!$D$5:$D$66,A26,'01_Findings'!$N$5:$N$66,"Open")
A29: Progress
A30: Status | B30: Count | C30: % of all
A31: Terbuka | B31: =COUNTIF('01B_Findings_ID'!$N$5:$N$66,A31) | C31: =IFERROR(B31/COUNTA('01_Findings'!$F$5:$F$66),0)
A32: Sedang dikerjakan | B32: =COUNTIF('01B_Findings_ID'!$N$5:$N$66,A32) | C32: =IFERROR(B32/COUNTA('01_Findings'!$F$5:$F$66),0)
A33: Sudah diperbaiki - menunggu uji ulang | B33: =COUNTIF('01B_Findings_ID'!$N$5:$N$66,A33) | C33: =IFERROR(B33/COUNTA('01_Findings'!$F$5:$F$66),0)
A34: Uji ulang lulus | B34: =COUNTIF('01B_Findings_ID'!$N$5:$N$66,A34) | C34: =IFERROR(B34/COUNTA('01_Findings'!$F$5:$F$66),0)
A35: Selesai | B35: =COUNTIF('01B_Findings_ID'!$N$5:$N$66,A35) | C35: =IFERROR(B35/COUNTA('01_Findings'!$F$5:$F$66),0)
A36: Ditunda | B36: =COUNTIF('01B_Findings_ID'!$N$5:$N$66,A36) | C36: =IFERROR(B36/COUNTA('01_Findings'!$F$5:$F$66),0)
A37: Bukan cacat | B37: =COUNTIF('01B_Findings_ID'!$N$5:$N$66,A37) | C37: =IFERROR(B37/COUNTA('01_Findings'!$F$5:$F$66),0)
A38: Blockers cleared | B38: =COUNTIFS('01B_Findings_ID'!$G$5:$G$66,"Ya",'01B_Findings_ID'!$N$5:$N$66,"Selesai")+COUNTIFS('01B_Findings_ID'!$G$5:$G$66,"Ya",'01B_Findings_ID'!$N$5:$N$66,"Uji ulang lulus") | C38: =IFERROR(B38/COUNTIF('01_Findings'!$G$5:$G$66,"Yes"),0)
A39: Demo ready when this reaches 100%
A42: How to use this workbook
A43: 01_Findings every defect, with evidence, expected behaviour, likely root cause, owner, target date and status. Yellow columns are QC Tester result to fill in.
A44: 02_Manual_Test_Checklist 31 tests from outside the app. Buttons, menus, sliders, chat and stability. Run these before the event.
A45: 03_Formula_Checks every calculation that reconciled, including the ones that PASS or FAIL.
A46: 04_Dataset_Requirements the client's data volumes against what the mockup has, and where the replacement sits.
A47: 05_Filter_Requirements the 22 filters the app needs. None currently exist.
A48: 06_Demo_Readiness_Gate the go / no-go list. Nothing gets recorded until the 'Must clear' rows are done.
A50: This review was done through the read-only API. Anything behind a button click, a slider or the chat box is untested and sits in sheet 02.

Sheet 0A_Cari_Cepat
A1: Cari cepat temuan QC
A2: Ketik atau pilih nomor QC di kotak kuning. Seluruh detailnya muncul di bawah. Daftar ringkas semua temuan ada di sebelah kanan.
E4: Daftar ringkas 47 temuan
A5: Nomor QC | B5: QC-062 | C5: =IF(COUNTIF('01_Findings'!$A$5:$A$66,$B$5)=0,"Nomor tidak ada. Isi antara QC-001 sampai QC-047.","Ditemukan di 01_Findings baris "&(MATCH($B$5,'01_Findings'!$A$5:$A$66,0)+4)) | E5: No QC | F5: Tingkat | G5: Blocker | H5: Agent | I5: Judul temuan
E6: ='01B_Findings_ID'!A5 | F6: ='01B_Findings_ID'!F5 | G6: ='01B_Findings_ID'!G5 | H6: ='01B_Findings_ID'!C5 | I6: ='01B_Findings_ID'!H5
A7: Ringkasan | E7: ='01B_Findings_ID'!A6 | F7: ='01B_Findings_ID'!F6 | G7: ='01B_Findings_ID'!G6 | H7: ='01B_Findings_ID'!C6 | I7: ='01B_Findings_ID'!H6
B8: Bahasa Indonesia | C8: English | E8: ='01B_Findings_ID'!A7 | F8: ='01B_Findings_ID'!F7 | G8: ='01B_Findings_ID'!G7 | H8: ='01B_Findings_ID'!C7 | I8: ='01B_Findings_ID'!H7
A9: Tingkat keparahan | B9: =IFERROR(INDEX('01B_Findings_ID'!$F$5:$F$66,MATCH($B$5,'01B_Findings_ID'!$A$5:$A$66,0)),"tidak ditemukan") | C9: =IFERROR(INDEX('01_Findings'!$F$5:$F$66,MATCH($B$5,'01_Findings'!$A$5:$A$66,0)),"tidak ditemukan") | E9: ='01B_Findings_ID'!A8 | F9: ='01B_Findings_ID'!F8 | G9: ='01B_Findings_ID'!G8 | H9: ='01B_Findings_ID'!C8 | I9: ='01B_Findings_ID'!H8
A10: Penghambat demo | B10: =IFERROR(INDEX('01B_Findings_ID'!$G$5:$G$66,MATCH($B$5,'01B_Findings_ID'!$A$5:$A$66,0)),"tidak ditemukan") | C10: =IFERROR(INDEX('01_Findings'!$G$5:$G$66,MATCH($B$5,'01_Findings'!$A$5:$A$66,0)),"tidak ditemukan") | E10: ='01B_Findings_ID'!A9 | F10: ='01B_Findings_ID'!F9 | G10: ='01B_Findings_ID'!G9 | H10: ='01B_Findings_ID'!C9 | I10: ='01B_Findings_ID'!H9
A11: Agent | B11: =IFERROR(INDEX('01B_Findings_ID'!$C$5:$C$66,MATCH($B$5,'01B_Findings_ID'!$A$5:$A$66,0)),"tidak ditemukan") | C11: =IFERROR(INDEX('01_Findings'!$C$5:$C$66,MATCH($B$5,'01_Findings'!$A$5:$A$66,0)),"tidak ditemukan") | E11: ='01B_Findings_ID'!A10 | F11: ='01B_Findings_ID'!F10 | G11: ='01B_Findings_ID'!G10 | H11: ='01B_Findings_ID'!C10 | I11: ='01B_Findings_ID'!H10
A12: Area QC | B12: =IFERROR(INDEX('01B_Findings_ID'!$D$5:$D$66,MATCH($B$5,'01B_Findings_ID'!$A$5:$A$66,0)),"tidak ditemukan") | C12: =IFERROR(INDEX('01_Findings'!$D$5:$D$66,MATCH($B$5,'01_Findings'!$A$5:$A$66,0)),"tidak ditemukan") | E12: ='01B_Findings_ID'!A11 | F12: ='01B_Findings_ID'!F11 | G12: ='01B_Findings_ID'!G11 | H12: ='01B_Findings_ID'!C11 | I12: ='01B_Findings_ID'!H11
A13: Jenis | B13: =IFERROR(INDEX('01B_Findings_ID'!$E$5:$E$66,MATCH($B$5,'01B_Findings_ID'!$A$5:$A$66,0)),"tidak ditemukan") | C13: =IFERROR(INDEX('01_Findings'!$E$5:$E$66,MATCH($B$5,'01_Findings'!$A$5:$A$66,0)),"tidak ditemukan") | E13: ='01B_Findings_ID'!A12 | F13: ='01B_Findings_ID'!F12 | G13: ='01B_Findings_ID'!G12 | H13: ='01B_Findings_ID'!C12 | I13: ='01B_Findings_ID'!H12
A14: Penanggung jawab | B14: =IFERROR(INDEX('01B_Findings_ID'!$L$5:$L$66,MATCH($B$5,'01B_Findings_ID'!$A$5:$A$66,0)),"tidak ditemukan") | C14: =IFERROR(INDEX('01_Findings'!$L$5:$L$66,MATCH($B$5,'01_Findings'!$A$5:$A$66,0)),"tidak ditemukan") | E14: ='01B_Findings_ID'!A13 | F14: ='01B_Findings_ID'!F13 | G14: ='01B_Findings_ID'!G13 | H14: ='01B_Findings_ID'!C13 | I14: ='01B_Findings_ID'!H13
A15: Target selesai | B15: =IFERROR(INDEX('01B_Findings_ID'!$M$5:$M$66,MATCH($B$5,'01B_Findings_ID'!$A$5:$A$66,0)),"tidak ditemukan") | C15: =IFERROR(INDEX('01_Findings'!$M$5:$M$66,MATCH($B$5,'01_Findings'!$A$5:$A$66,0)),"tidak ditemukan") | E15: ='01B_Findings_ID'!A14 | F15: ='01B_Findings_ID'!F14 | G15: ='01B_Findings_ID'!G14 | H15: ='01B_Findings_ID'!C14 | I15: ='01B_Findings_ID'!H14
A16: Status | B16: =IFERROR(INDEX('01B_Findings_ID'!$N$5:$N$66,MATCH($B$5,'01B_Findings_ID'!$A$5:$A$66,0)),"tidak ditemukan") | C16: =IFERROR(INDEX('01_Findings'!$N$5:$N$66,MATCH($B$5,'01_Findings'!$A$5:$A$66,0)),"tidak ditemukan") | E16: ='01B_Findings_ID'!A15 | F16: ='01B_Findings_ID'!F15 | G16: ='01B_Findings_ID'!G15 | H16: ='01B_Findings_ID'!C15 | I16: ='01B_Findings_ID'!H15
A17: Rincian | E17: ='01B_Findings_ID'!A16 | F17: ='01B_Findings_ID'!F16 | G17: ='01B_Findings_ID'!G16 | H17: ='01B_Findings_ID'!C16 | I17: ='01B_Findings_ID'!H16
A18: Temuan | B18: =IFERROR(INDEX('01B_Findings_ID'!$H$5:$H$66,MATCH($B$5,'01B_Findings_ID'!$A$5:$A$66,0)),"tidak ditemukan") | C18: =IFERROR(INDEX('01_Findings'!$H$5:$H$66,MATCH($B$5,'01_Findings'!$A$5:$A$66,0)),"tidak ditemukan") | E18: ='01B_Findings_ID'!A17 | F18: ='01B_Findings_ID'!F17 | G18: ='01B_Findings_ID'!G17 | H18: ='01B_Findings_ID'!C17 | I18: ='01B_Findings_ID'!H17
A19: Bukti yang ditemukan | B19: =IFERROR(INDEX('01B_Findings_ID'!$I$5:$I$66,MATCH($B$5,'01B_Findings_ID'!$A$5:$A$66,0)),"tidak ditemukan") | C19: =IFERROR(INDEX('01_Findings'!$I$5:$I$66,MATCH($B$5,'01_Findings'!$A$5:$A$66,0)),"tidak ditemukan") | E19: ='01B_Findings_ID'!A18 | F19: ='01B_Findings_ID'!F18 | G19: ='01B_Findings_ID'!G18 | H19: ='01B_Findings_ID'!C18 | I19: ='01B_Findings_ID'!H18
A20: Perilaku yang seharusnya | B20: =IFERROR(INDEX('01B_Findings_ID'!$J$5:$J$66,MATCH($B$5,'01B_Findings_ID'!$A$5:$A$66,0)),"tidak ditemukan") | C20: =IFERROR(INDEX('01_Findings'!$J$5:$J$66,MATCH($B$5,'01_Findings'!$A$5:$A$66,0)),"tidak ditemukan") | E20: ='01B_Findings_ID'!A19 | F20: ='01B_Findings_ID'!F19 | G20: ='01B_Findings_ID'!G19 | H20: ='01B_Findings_ID'!C19 | I20: ='01B_Findings_ID'!H19
A21: Dugaan akar masalah | B21: =IFERROR(INDEX('01B_Findings_ID'!$K$5:$K$66,MATCH($B$5,'01B_Findings_ID'!$A$5:$A$66,0)),"tidak ditemukan") | C21: =IFERROR(INDEX('01_Findings'!$K$5:$K$66,MATCH($B$5,'01_Findings'!$A$5:$A$66,0)),"tidak ditemukan") | E21: ='01B_Findings_ID'!A20 | F21: ='01B_Findings_ID'!F20 | G21: ='01B_Findings_ID'!G20 | H21: ='01B_Findings_ID'!C20 | I21: ='01B_Findings_ID'!H20
E22: ='01B_Findings_ID'!A21 | F22: ='01B_Findings_ID'!F21 | G22: ='01B_Findings_ID'!G21 | H22: ='01B_Findings_ID'!C21 | I22: ='01B_Findings_ID'!H21
A23: Pemeriksaan formula terkait | E23: ='01B_Findings_ID'!A22 | F23: ='01B_Findings_ID'!F22 | G23: ='01B_Findings_ID'!G22 | H23: ='01B_Findings_ID'!C22 | I23: ='01B_Findings_ID'!H22
A24: Perhitungan | B24: =IFERROR(INDEX('03_Formula_Checks'!$D$5:$D$66,MATCH($B$5,'03_Formula_Checks'!$G$5:$G$66,0)),"tidak ada pemeriksaan formula untuk nomor ini") | E24: ='01B_Findings_ID'!A23 | F24: ='01B_Findings_ID'!F23 | G24: ='01B_Findings_ID'!G23 | H24: ='01B_Findings_ID'!C23 | I24: ='01B_Findings_ID'!H23
A25: Hasil di aplikasi | B25: =IFERROR(INDEX('03_Formula_Checks'!$E$5:$E$66,MATCH($B$5,'03_Formula_Checks'!$G$5:$G$66,0)),"-") | E25: ='01B_Findings_ID'!A24 | F25: ='01B_Findings_ID'!F24 | G25: ='01B_Findings_ID'!G24 | H25: ='01B_Findings_ID'!C24 | I25: ='01B_Findings_ID'!H24
A26: Verdict | B26: =IFERROR(INDEX('03_Formula_Checks'!$F$5:$F$66,MATCH($B$5,'03_Formula_Checks'!$G$5:$G$66,0)),"-") | E26: ='01B_Findings_ID'!A25 | F26: ='01B_Findings_ID'!F25 | G26: ='01B_Findings_ID'!G25 | H26: ='01B_Findings_ID'!C25 | I26: ='01B_Findings_ID'!H25
E27: ='01B_Findings_ID'!A26 | F27: ='01B_Findings_ID'!F26 | G27: ='01B_Findings_ID'!G26 | H27: ='01B_Findings_ID'!C26 | I27: ='01B_Findings_ID'!H26
E28: ='01B_Findings_ID'!A27 | F28: ='01B_Findings_ID'!F27 | G28: ='01B_Findings_ID'!G27 | H28: ='01B_Findings_ID'!C27 | I28: ='01B_Findings_ID'!H27
A29: Catatan | E29: ='01B_Findings_ID'!A28 | F29: ='01B_Findings_ID'!F28 | G29: ='01B_Findings_ID'!G28 | H29: ='01B_Findings_ID'!C28 | I29: ='01B_Findings_ID'!H28
A30: Kalau kolom B dan C berbunyi 'tidak ditemukan', berarti nomor QC-nya salah ketik. Gunakan daftar di sebelah kanan. | E30: ='01B_Findings_ID'!A29 | F30: ='01B_Findings_ID'!F29 | G30: ='01B_Findings_ID'!G29 | H30: ='01B_Findings_ID'!C29 | I30: ='01B_Findings_ID'!H29
A31: Temuan yang tidak punya pemeriksaan formula akan menampilkan 'tidak ada pemeriksaan formula untuk nomor ini'. Itu normal, tidak semua temuan berupa hitungan. | E31: ='01B_Findings_ID'!A30 | F31: ='01B_Findings_ID'!F30 | G31: ='01B_Findings_ID'!G30 | H31: ='01B_Findings_ID'!C30 | I31: ='01B_Findings_ID'!H30
E32: ='01B_Findings_ID'!A31 | F32: ='01B_Findings_ID'!F31 | G32: ='01B_Findings_ID'!G31 | H32: ='01B_Findings_ID'!C31 | I32: ='01B_Findings_ID'!H31
E33: ='01B_Findings_ID'!A32 | F33: ='01B_Findings_ID'!F32 | G33: ='01B_Findings_ID'!G32 | H33: ='01B_Findings_ID'!C32 | I33: ='01B_Findings_ID'!H32
E34: ='01B_Findings_ID'!A33 | F34: ='01B_Findings_ID'!F33 | G34: ='01B_Findings_ID'!G33 | H34: ='01B_Findings_ID'!C33 | I34: ='01B_Findings_ID'!H33
E35: ='01B_Findings_ID'!A34 | F35: ='01B_Findings_ID'!F34 | G35: ='01B_Findings_ID'!G34 | H35: ='01B_Findings_ID'!C34 | I35: ='01B_Findings_ID'!H34
E36: ='01B_Findings_ID'!A35 | F36: ='01B_Findings_ID'!F35 | G36: ='01B_Findings_ID'!G35 | H36: ='01B_Findings_ID'!C35 | I36: ='01B_Findings_ID'!H35
E37: ='01B_Findings_ID'!A36 | F37: ='01B_Findings_ID'!F36 | G37: ='01B_Findings_ID'!G36 | H37: ='01B_Findings_ID'!C36 | I37: ='01B_Findings_ID'!H36
E38: ='01B_Findings_ID'!A37 | F38: ='01B_Findings_ID'!F37 | G38: ='01B_Findings_ID'!G37 | H38: ='01B_Findings_ID'!C37 | I38: ='01B_Findings_ID'!H37
E39: ='01B_Findings_ID'!A38 | F39: ='01B_Findings_ID'!F38 | G39: ='01B_Findings_ID'!G38 | H39: ='01B_Findings_ID'!C38 | I39: ='01B_Findings_ID'!H38
E40: ='01B_Findings_ID'!A39 | F40: ='01B_Findings_ID'!F39 | G40: ='01B_Findings_ID'!G39 | H40: ='01B_Findings_ID'!C39 | I40: ='01B_Findings_ID'!H39
E41: ='01B_Findings_ID'!A40 | F41: ='01B_Findings_ID'!F40 | G41: ='01B_Findings_ID'!G40 | H41: ='01B_Findings_ID'!C40 | I41: ='01B_Findings_ID'!H40
E42: ='01B_Findings_ID'!A41 | F42: ='01B_Findings_ID'!F41 | G42: ='01B_Findings_ID'!G41 | H42: ='01B_Findings_ID'!C41 | I42: ='01B_Findings_ID'!H41
E43: ='01B_Findings_ID'!A42 | F43: ='01B_Findings_ID'!F42 | G43: ='01B_Findings_ID'!G42 | H43: ='01B_Findings_ID'!C42 | I43: ='01B_Findings_ID'!H42
... E67: ='01B_Findings_ID'!A66 | F67: ='01B_Findings_ID'!F66 | G67: ='01B_Findings_ID'!G66 | H67: ='01B_Findings_ID'!C66 | I67: ='01B_Findings_ID'!H66

Sheet 00B_Panduan_Bahasa
A1: Panduan QC Tracker - AI Finance Forum
A2: Dokumen ini menjelaskan isi workbook QC dan cara memakainya. Ditinjau 28 Juli 2026.
A4: 1. APA ITU WORKBOOK INI
A5: Workbook ini adalah hasil pemeriksaan mutu (quality control) atas mockup AI Finance Forum, plus alat pelacak
A6: perbaikannya. Isinya dua hal: daftar temuan yang harus diperbaiki, dan daftar pengujian yang masih harus
A7: dijalankan secara manual sebelum demo di depan para CFO.
A9: 2. BAGAIMANA PEMERIKSAAN INI DILAKUKAN, DAN APA BATASNYA
A10: Pemeriksaan dilakukan langsung terhadap API aplikasi yang sedang berjalan. Semua endpoint GET dibaca:
A11: dashboard keempat agent, KPI, konfigurasi grafik, 47 alert, 47 action card, dan riwayat percakapan.
A12: Batas yang penting untuk Anda ketahui: tombol, menu, slider simulator, kotak chat, serta tombol approve dan
A13: simulate pada action semuanya berjalan lewat POST atau di sisi browser. Semua itu TIDAK bisa diuji dari luar.
A14: Karena itu 31 pengujian manual disiapkan di sheet 02. Bagian tersebut masih berstatus belum diuji.
... A97: Ketiga asumsi ini ditandai kuning di workbook dataset.

Sheet 01_Findings
A1: Testing listing - findings tracker
A2: AI Finance Forum mockup. Reviewed 28 July 2026 against the live API. Update Status, Target date and Retest columns as fixes land.
A4: ID | B4: Date found | C4: Agent | D4: QC area | E4: Type | F4: Severity | G4: Demo blocker | H4: Finding | I4: Evidence observed | J4: Expected behaviour | K4: Likely root cause | L4: Fix owner | M4: Target date | N4: Status | O4: Retest date | P4: Retest result | Q4: Notes
A5: QC-001 | B5: 2026-07-28 | C5: Leakage | D5: a. Formula consistency | E5: Data | F5: Critical | G5: Yes | H5: Leakage category chart returns all zeros | I5: GET /api/html/dashboard/finance.leakage returns views.categories.data with every value 0.0 (Bank-change fraud 0, Duplicate payment 0, Overbilling 0, Lost discount 0, Split/threshold 0). The side donut 'Leakage mix' is also all zeros, the worklist Amount column is '0' for all 10 rows, and the vendor radar 'At risk' column is '0' for all 8 vendors. Meanwhile the KPI tiles show 7,845 / 3,800 / 3,050 / 4,300. | J5: Category amounts should sum to the 7,845 mn shown on the 'Flagged this cycle' KPI. | K5: The amount column is not mapped for import batch 17. Aggregate KPIs are computed from a different query than the per-category breakdown. | L5: Backend / data | M5: 2026-07-31 | N5: Fixed - awaiting retest | Q5: Fixed 30 Jul 2026 (branch bug-fix-trial, commit 53daa2c). category_breakdowns.amount_at_risk_idr_mn was probed as amount_idr_mn, so _row_get returned None and every value became 0.0 with no error. Verified on live DB batch 17: bars 3,800 / 3,050 / 900 / 95 sum to 7,845 = the Flagged this cycle card.
A6: QC-002 | B6: 2026-07-28 | C6: All | D6: a. Formula consistency | E6: Architecture | F6: Critical | G6: Yes | H6: The four agents run on four unrelated data batches | I6: import_batch_id is 19 for Finance, 17 for Leakage, 11 for Collection and 2 for Treasury. | J6: One shared ledger, so any number can be traced across agents. | K6: No single source of truth. Each agent was seeded independently. | L6: Backend / data | M6: 2026-07-31 | N6: Open
A7: QC-003 | B7: 2026-07-28 | C7: Finance + Collection | D7: a. Formula consistency | E7: Formula | F7: Critical | G7: Yes | H7: Collection revenue base is about 15 times the Finance revenue | I7: Collection raw.summary.annual_credit_sales_idr_mn = 700,000. Finance KPI revenue = 46,510. AR of 110,000 is 2.4 times the entire Finance annual revenue. | J7: DSO must be divided by the same revenue the Finance agent reports. | K7: Two unrelated seed datasets (see the batch finding above). | L7: Backend / data | M7: 2026-07-31 | N7: Open
A8: QC-004 | B8: 2026-07-28 | C8: Treasury | D8: a. Formula consistency | E8: Formula | F8: Critical | G8: Yes | H8: Deferral action moves headroom the wrong way | I8: Action 'Defer noncritical Week 5 payable' shows impact 'week6 headroom: 1012.5 +3000 -> 4012.5'. Moving a payable INTO Week 6 must reduce Week 6 headroom, not increase it. Its own spec also claims Week 5 cash rises above IDR 10,000 mn; 6,997.5 + 3,000 = 9,997.5. | J8: Week 5 headroom -1,002.5 -> +1,997.5 and Week 6 headroom 1,012.5 -> -1,987.5, so the trade-off is visible. | K8: The impact string is authored text, not computed from the forecast. Sign and week label are both wrong. | L8: Backend / agent logic | M8: 2026-07-31 | N8: Open
A9: QC-005 | B9: 2026-07-28 | C9: Treasury | D9: a. Formula consistency | E9: Formula | F9: Critical | G9: Yes | H9: Action mixes headroom with closing cash in one before-and-after | I9: Action 'Accelerate Customer A collection' shows 'cash buffer: -1002.5 -> +6997.5'. -1,002.5 is headroom, 6,997.5 is closing cash. Its own spec says recover at least IDR 1,100 mn, which would give +97.5 headroom. | J9: One unit per metric. Either headroom -1,002.5 -> +97.5, or closing cash 6,997.5 -> 8,097.5. | K9: Impact strings are free text with no unit validation. | L9: Backend / agent logic | M9: 2026-07-31 | N9: Open
A10: QC-006 | B10: 2026-07-28 | C10: All | D10: d. Prompt & response | E10: Content | F10: Critical | G10: Yes | H10: Conversation history is full of developer test messages | I10: GET /api/html/conversations returns roughly 190 saved conversations including 'test', 'asdsad', 'hello world', 'Test test test', 'selamat pagi', 'does all the right tools work?', 'gimme data', 'show me the cahrt'. | J10: A curated history containing only credible CFO questions, or the history panel hidden for the event. | K10: No separation between the development environment and the demo environment. | L10: Demo owner | M10: 2026-07-31 | N10: Open
A11: QC-007 | B11: 2026-07-28 | C11: Collection | D11: a. Formula consistency | E11: Formula | F11: High | G11: Yes | H11: High-risk KPI and the risk tier chart disagree on the same screen | I11: KPI 'High-risk exposure' = 2,500 mn with the label 'provision / high tier'. The 'Risk exposure by tier' chart shows High = 5,000 mn. | J11: Either the KPI is renamed 'High-risk provision', or it shows 5,000 to match the chart. | K11: The KPI reads the provision field while the chart reads the exposure field. Same label, two meanings. | L11: Backend / agent logic | M11: 2026-08-04 | N11: Fixed - awaiting retest | Q11: Fixed 30 Jul 2026 (commit 53daa2c). The card showed high_risk_provision (2,500) under a label reading 'exposure'. It now shows the High tier exposure (5,000), which equals the chart bar, with the provision moved to the caption.
A12: QC-008 | B12: 2026-07-28 | C12: Collection | D12: a. Formula consistency | E12: Definition | F12: High | G12: Yes | H12: 'Top 5' is defined three different ways inside one agent | I12: Options chart 'Top 5 - 46d' uses worklist rows 1 to 5 (21,300 mn recovery). Alert 'DSO gap and overdue concentration' uses top 5 by overdue amount (27,000 mn, 71.17%). Alert 'Mid-tier accounts can unlock most DSO gap' uses top 5 by expected recovery (23,225 mn). | J12: One definition, stated on screen. | K12: Each surface computes its own ranking. | L12: Backend / agent logic | M12: 2026-08-04 | N12: Open
A13: QC-009 | B13: 2026-07-28 | C13: Finance | D13: a. Formula consistency | E13: Formula | F13: High | G13: Yes | H13: Two different EBITDA margin targets are in use | I13: The KPI tile and the simulator gauge both say 'target 15%'. The alert 'Price recovery opportunity' says the budget margin is 15.7% (budget EBITDA 7,200 / budget revenue 46,000 = 15.65%). | J13: One target. If budget is the reference, use 15.7% everywhere. | K13: The gauge target is hardcoded to a round 15% while the alerts compute it from the budget. | L13: Backend / agent logic | M13: 2026-08-04 | N13: Fixed - awaiting retest | Q13: Fixed 30 Jul 2026 (commit f448e66). The target now comes from the budget row (7,200 / 46,000 = 15.65%) and is threaded through the card caption, gauge label, simulator baseline and the recalculate endpoint. NOTE: formula check #18 expects 9.2/15 = 0.6133; with one target it becomes 9.2/15.65 = 0.586, so that check needs updating.
A14: QC-010 | B14: 2026-07-28 | C14: Finance | D14: a. Formula consistency | E14: Formula | F14: High | G14: Yes | H14: Price variance is roughly ten times too small for the stated price decline | I14: Alerts state blended price fell 7.6%, from IDR 127.7k to IDR 118.0k per unit. The EBITDA waterfall shows a price step of only -390 mn on revenue of 46,510 mn. A 7.6% blended price decline implies roughly -3,800 mn. | J14: The price step and the stated percentage decline must be derived from the same calculation. | K14: The waterfall steps and the alert narrative are generated from different sources. Needs verification against the underlying model. | L14: Backend / agent logic | M14: 2026-08-04 | N14: Open
A15: QC-011 | B15: 2026-07-28 | C15: Finance | D15: a. Formula consistency | E15: Formula | F15: High | G15: Yes | H15: COGS variance is stated as two different numbers | I15: Alerts and actions use IDR 2,930 mn of COGS overrun. The EBITDA waterfall shows the Cost and FX step as -1,880 mn. | J15: One cost variance figure across the waterfall, the alerts and the action cards. | K15: The waterfall may net FX into cost while the alert reports gross cost. Not reconciled either way. | L15: Backend / agent logic | M15: 2026-08-04 | N15: Open
A16: QC-012 | B16: 2026-07-28 | C16: Finance | D16: d. Prompt & response | E16: Content | F16: High | G16: No | H16: Two near-identical numbers mean two different things | I16: Cost and FX step = -1,880 mn. Mix plus price = -1,491 + -390 = -1,881 mn, and an alert reports 'IDR 1,881mn combined profitability loss'. | J16: Separate the two on screen, or round them differently so they cannot be confused live. | K16: Coincidence in the seed data, but it will cause confusion on stage. | L16: Demo owner | M16: 2026-08-04 | N16: Open
A17: QC-013 | B17: 2026-07-28 | C17: Leakage | D17: a. Formula consistency | E17: Formula | F17: Medium | G17: No | H17: The bar labelled 'Current 95%' does not show the current position | I17: In the Leakage 'Recovery scenario' chart the third bar is labelled 'Current 95%' and equals 7,577.5. It applies 95% to duplicates and overbilling together. The real current position applies 95% to duplicates and 90% to overbilling, which gives 7,557.5. That is the figure the 'Total protected' KPI (7,558) and the side chart 'Protected vs at risk' (7,557.5) both carry. Difference = 400 x 5% = 20 mn. IMPORTANT: this is not visible to the eye. The KPI and the side chart agree with each other, so a side-by-side glance looks correct. Only the recovery chart differs, and 20 out of 7,578 is 0.26%. It surfaces in a tooltip, a data label, or when someone asks the agent for the number. | J17: The 'Current' bar uses the same assumption set as the KPI and reads 7,557.5. Alternatively rename the bar to '95% across the board' so it stops claiming to be the current position. | K17: The recovery chart hardcodes one claw-back rate across all recoverable items. The simulator baseline uses two separate rates. Neither is wrong on its own; the label 'Current' is what makes the chart incorrect. | L17: Backend / agent logic | M17: 2026-08-11 | N17: Fixed - awaiting retest | Q17: Severity lowered from High to Medium on 28 Jul 2026 after re-checking with Susan. Reason: the gap is not visible to the eye and is not a demo blocker. The defect is still real and still needs fixing. | Fixed 30 Jul 2026 (commit 53daa2c). The bar is now labelled 'Current 95/90%' and reuses the Total protected card value (7,557.5) instead of recomputing it at 95/95 (7,577.5).
A18: QC-014 | B18: 2026-07-28 | C18: Leakage | D18: a. Formula consistency | E18: Formula | F18: High | G18: Yes | H18: Flag count on the KPI does not match the tables | I18: KPI 'Flagged this cycle' says '22 flags'. The action worklist lists 10 rows and the vendor radar totals 10 flags across 8 vendors. | J18: The count on the KPI equals the number of rows a user can actually open. | K18: The KPI counts raw exceptions while the tables show a filtered top-N with no 'showing 10 of 22' label. | L18: Backend / agent logic | M18: 2026-08-04 | N18: Fixed - awaiting retest | Q18: Fixed 30 Jul 2026 (commit 53daa2c). The KPI now reads summary.items_flagged (10). The 22 came from len(anomalies), which is LIMIT 30 and includes rows that are not flagged.
A19: QC-015 | B19: 2026-07-28 | C19: Leakage | D19: a. Formula consistency | E19: Formula | F19: High | G19: Yes | H19: Split-invoice exposure sits in the chart but outside the total | I19: At risk = 7,845 = fraud 3,800 + duplicates 3,050 + overbilling 400 + other blocked 500 + lost 95. The alert 'Split invoice threshold evasion' reports IDR 1,950 mn, and 'Split / threshold' is one of the five chart categories, yet 1,950 is not in the 7,845. | J19: Either at risk becomes 9,795, or split invoices are excluded from the chart and explained. | K19: The at-risk aggregate was built before split-threshold detection was added. | L19: Backend / agent logic | M19: 2026-08-04 | N19: In progress | Q19: Partly fixed 30 Jul 2026 (commit 53daa2c). The dashboard no longer contradicts itself: rows with is_direct_loss = false are out of the category bar and mix donut, so both sum to 7,845, and the 1,950 is named in the chart note. The alert wording has NOT been checked yet.
A20: QC-016 | B20: 2026-07-28 | C20: Collection | D20: a. Formula consistency | E20: Formula | F20: High | G20: Yes | H20: Action impact does not match its own recommendation | I20: Action 'Accelerate top overdue collections' spec says collect at least IDR 20,000 mn. Impact says 'DSO: 57.36 -5.21 -> 52.14'. -5.21 days corresponds to 10,000 mn (10,000 / 1,917.8). 20,000 mn gives -10.43 days. | J20: Impact recomputed from the amount in the spec. | K20: Impact string copied from a different action. | L20: Backend / agent logic | M20: 2026-08-04 | N20: Open
A21: QC-017 | B21: 2026-07-28 | C21: Treasury | D21: a. Formula consistency | E21: Formula | F21: High | G21: Yes | H21: Combined action shows only part of its own effect | I21: Action 'Bridge Week 5 funding gap' spec says accelerate 2,000 mn plus defer 3,000 mn, which is 5,000 mn. Impact shows 'headroom: -1002.5 -> +1997.5', a movement of only 3,000 mn. | J21: -1,002.5 -> +3,997.5. | K21: Only the deferral leg is being computed. | L21: Backend / agent logic | M21: 2026-08-04 | N21: Open
A22: QC-018 | B22: 2026-07-28 | C22: Collection | D22: a. Formula consistency | E22: Labelling | F22: High | G22: No | H22: Action labels the top-2 concentration as the overall overdue share | I22: Action 'Escalate concentrated exposures' shows 'Overdue share: 43.5% -10% -> 33.5%'. The dashboard overdue share is 34.5% (37,935 / 110,000). 43.5% is the top-2 share of overdue (16,500 / 37,935). | J22: Label it 'Top-2 share of overdue'. | K22: Reused metric name for a different denominator. | L22: Backend / agent logic | M22: 2026-08-04 | N22: Open
A23: QC-019 | B23: 2026-07-28 | C23: Treasury | D23: a. Formula consistency | E23: Formula | F23: High | G23: Yes | H23: Credit line action is anchored to the wrong week | I23: Action 'Pre-arrange contingent credit capacity' uses baseline 1,012.5, which is Week 6 headroom. The breach is in Week 5 at -1,002.5. Its spec then targets a buffer above 4,000 mn. | J23: Baseline -1,002.5 (Week 5), result +1,997.5 after a 3,000 mn draw. | K23: Wrong week selected as the baseline. | L23: Backend / agent logic | M23: 2026-08-04 | N23: Open
A24: QC-020 | B24: 2026-07-28 | C24: All | D24: c. Button / menu / function | E24: Integration | F24: High | G24: Yes | H24: Agent keys are inconsistent between endpoints | I24: /api/html/agents returns finance.collection and finance.treasury. The dashboard payload returns agent 'collections' and 'treasury'. /api/actions and /api/alerts use 'collection' and 'cashflow'. | J24: One canonical key per agent across every endpoint. | K24: Naming drift between the agent registry, the dashboard service and the alert or action service. Any join on agent name will silently return an empty list for Treasury. | L24: Backend | M24: 2026-08-04 | N24: Open
A25: QC-021 | B25: 2026-07-28 | C25: All | D25: d. Prompt & response | E25: Content | F25: High | G25: Yes | H25: 47 action cards with heavy duplication | I25: Finance has at least five near-identical actions to rebalance mix toward higher-margin SKUs. Leakage has three near-identical 'Launch duplicate payment recovery' cards. Collection has four cards on the same two customers. | J25: Deduplicate to roughly three to five distinct actions per agent for the demo. | K25: Actions are generated per alert with no clustering step, and the alerts are themselves duplicated. | L25: Backend / agent logic | M25: 2026-08-04 | N25: Open
A26: QC-022 | B26: 2026-07-28 | C26: All | D26: a. Formula consistency | E26: Logic | F26: High | G26: Yes | H26: Action impacts stack with no double-count guard | I26: Approving the Finance set adds +1,500, +1,000, +390, +300 and two percentage-point moves to the same EBITDA base of 4,300, and several of them address the same driver. | J26: A portfolio view that nets overlapping actions and shows a single combined impact. | K26: Each action is scored in isolation against the baseline. | L26: Backend / agent logic | M26: 2026-08-04 | N26: Open
A27: QC-023 | B27: 2026-07-28 | C27: All | D27: d. Prompt & response | E27: Content | F27: High | G27: No | H27: 47 alerts telling roughly eight distinct stories | I27: Finance has 12 alerts, essentially all describing mix, price and cost. Cashflow has 12 restating the Week 5 breach. | J27: Cluster to one alert per underlying issue with a severity ranking. | K27: No deduplication in the alert generator. | L27: Backend / agent logic | M27: 2026-08-04 | N27: Open
A28: QC-024 | B28: 2026-07-28 | C28: Leakage | D28: b. Chart accuracy | E28: Chart | F28: High | G28: Yes | H28: The Leakage agent opens on an empty chart | I28: default_view is 'categories', which is the all-zero chart described in the first finding. | J28: Open on a populated view. | K28: Same root cause as the zero-amount issue. | L28: Backend / data | M28: 2026-08-04 | N28: Fixed - awaiting retest | Q28: Fixed 30 Jul 2026 (commit 53daa2c). Same root cause as QC-001; the default view 'categories' now renders four bars on open.
A29: QC-025 | B29: 2026-07-28 | C29: Treasury | D29: a. Formula consistency | E29: Labelling | F29: High | G29: No | H29: FX action states exposure falls to the hedge amount | I29: Action 'Increase near-term FX protection' shows 'FX exposure: 3.3m -1.3m -> 2.0m'. Hedging the unhedged 1.3M should take unhedged exposure from 1.3M to zero, or coverage from 61% to 100%. As written, 2.0M is the hedge amount, not the residual exposure. | J29: 'Unhedged exposure: USD 1.3m -> USD 0' or 'Coverage: 61% -> 100%'. | K29: Confuses gross exposure with hedged notional. | L29: Backend / agent logic | M29: 2026-08-04 | N29: Open
A30: QC-026 | B30: 2026-07-28 | C30: Collection | D30: a. Formula consistency | E30: Logic | F30: Medium | G30: No | H30: Recovery rate ignores how old the debt is | I30: Expected recovery is driven only by risk tier: High 40%, Medium 85%, Low 95%. CV Berkah Jaya at 90+ days recovers at 40% while PT Sumber Makmur at 61-90 days recovers at 85%, the same rate as a 31-60 day account. | J30: Recovery rate should be a function of both tier and ageing bucket. | K30: Single-factor recovery model. | L30: Backend / agent logic | M30: 2026-08-11 | N30: Open
A31: QC-027 | B31: 2026-07-28 | C31: Finance | D31: a. Formula consistency | E31: Formula | F31: Medium | G31: No | H31: One margin percentage rounds down where others round normally | I31: Precision gross margin displays 36.2%. 4,930 / 13,600 = 36.25%, which should display 36.3%. Industrial 23.81% -> 23.8 and Standard 16.67% -> 16.7 both round correctly. | J31: Consistent rounding, half up. | K31: Truncation rather than rounding on this path. | L31: Frontend | M31: 2026-08-11 | N31: Fixed - awaiting retest | Q31: Fixed 30 Jul 2026 (commit f448e66). Python and IEEE round half to even, so round(36.25, 1) is 36.2. Added _round_half_up and routed _fmt and _pct through it. Product GM% is now 23.8 / 36.3 / 16.7.
A32: QC-028 | B32: 2026-07-28 | C32: Collection | D32: b. Chart accuracy | E32: Chart | F32: Medium | G32: No | H32: DSO gauge shows 120% progress on a metric where lower is better | I32: DSO KPI has progress 1.2 (57 / 47). | J32: Invert the gauge, or show days over target rather than a progress percentage. | K32: Generic progress calculation applied to an inverse metric. | L32: Frontend | M32: 2026-08-11 | N32: Fixed - awaiting retest | Q32: Fixed 30 Jul 2026 (commit f448e66). Added a lower_is_better flag so enrichment inverts the ratio. DSO progress is now 0.8246 (47/57) instead of the clamped 1.2.
A33: QC-029 | B33: 2026-07-28 | C33: Treasury | D33: d. Prompt & response | E33: Formatting | F33: Medium | G33: No | H33: Inconsistent number formats in one KPI row | I33: 'Net USD exposure 3.3 M USD' sits next to 'Recommended hedge 2,000,000 USD'. The Week 5 shortfall appears as 1,002, 1,002.5 and 1,003 in different places. | J33: One format per unit across the app. | K33: No shared formatting helper. | L33: Frontend | M33: 2026-08-11 | N33: Fixed - awaiting retest | Q33: Fixed 30 Jul 2026 (commit f448e66). One USD scale across the KPI row: 3.3 M USD beside 2.0 M USD, instead of 3.3 M USD beside 2,000,000 USD which hid that 2.0 is less than 3.3.
A34: QC-030 | B34: 2026-07-28 | C34: Collection | D34: a. Formula consistency | E34: Labelling | F34: Medium | G34: No | H34: Action labels a two-customer balance as total overdue AR | I34: Action 'Tighten exposure controls' shows 'Overdue AR: 16500 -3000 -> 13500'. Total overdue AR is 37,935. 16,500 is the top two customers. | J34: 'Top-2 overdue: 16,500 -> 13,500'. | K34: Reused metric name. | L34: Backend / agent logic | M34: 2026-08-11 | N34: Open
A35: QC-031 | B35: 2026-07-28 | C35: Leakage | D35: a. Formula consistency | E35: Labelling | F35: Medium | G35: No | H35: Action uses the annualised figure while the dashboard shows the cycle figure | I35: Action 'Tighten early-payment discount capture' shows 'Discount leakage: 2470 -50% -> 1235'. The dashboard 'Lost' amount is 95 mn. The alert clarifies 95 mn per cycle annualises to 2,470 mn. | J35: State the basis on the card: 'Discount leakage (annualised)'. | K35: No period label on impact strings. | L35: Backend / agent logic | M35: 2026-08-11 | N35: Open
A36: QC-032 | B36: 2026-07-28 | C36: Leakage | D36: a. Formula consistency | E36: Labelling | F36: Medium | G36: No | H36: The same 900 mn appears under three different names | I36: Alerts call it 'IDR 900mn excess vs PO/GRN'. The simulator baseline splits it as overbill_amount 400 and other_blocked 500. An action calls it 'overbilling risk: 900mn'. | J36: One name, with the split shown as a breakdown underneath. | K36: Field naming drift. | L36: Backend / agent logic | M36: 2026-08-11 | N36: Open
A37: QC-033 | B37: 2026-07-28 | C37: Collection | D37: b. Chart accuracy | E37: Chart | F37: Medium | G37: No | H37: Two charts on the same screen order the same pair in opposite directions | I37: Main 'prize' chart plots Now then Target. The side chart 'DSO vs target' plots Target then Now. | J37: One order. | K37: Independently authored chart configs. | L37: Frontend | M37: 2026-08-11 | N37: Fixed - awaiting retest | Q37: Fixed 30 Jul 2026 (commit f448e66). Both charts now order [Now, Target]. Aligning them turned the pair into exact duplicates, so side:bottom was changed to Overdue vs expected recovery.
A38: QC-034 | B38: 2026-07-28 | C38: Treasury | D38: b. Chart accuracy | E38: Chart | F38: Medium | G38: No | H38: A zero bar next to a value bar reads as a rendering failure | I38: The 'FX impact if we do nothing' chart plots Base = 0 against Adverse = 1,777.05. | J38: Show a single value with a reference line, or label the zero bar explicitly. | K38: Chart type choice. | L38: Frontend | M38: 2026-08-11 | N38: Fixed - awaiting retest | Q38: Fixed 30 Jul 2026 (commit f448e66). The zero 'Base' bar is gone. The chart now compares Do nothing 1,777.05 against Hedge 2.0M 700.05 - both non-zero, and the first equals the FX loss card.
A39: QC-035 | B39: 2026-07-28 | C39: All | D39: b. Chart accuracy | E39: Chart | F39: Medium | G39: Yes | H39: No chart states its period | I39: None of the four dashboards labels whether a figure is monthly, year to date or full year. | J39: Every chart title carries the period, for example 'Oct 2025 to Sep 2026'. | K39: Period is not part of the payload. | L39: Frontend + backend | M39: 2026-08-11 | N39: Open
A40: QC-036 | B40: 2026-07-28 | C40: Finance | D40: b. Chart accuracy | E40: Chart | F40: Medium | G40: No | H40: The side chart duplicates the main chart exactly | I40: side.top 'Margin by product' has identical data to the 'product' view. | J40: Use the side slot for something the main view does not show. | K40: Layout placeholder never replaced. | L40: Frontend | M40: 2026-08-11 | N40: Fixed - awaiting retest | Q40: Fixed 30 Jul 2026 (commit f448e66). Finance side:top was byte-identical to view:product. It now shows the gross margin pool in IDR (4,550 / 4,930 / 2,300 = 11,780) rather than repeating the rate.
A41: QC-037 | B41: 2026-07-28 | C41: Treasury | D41: b. Chart accuracy | E41: Chart | F41: Medium | G41: Yes | H41: The cash chart cannot answer why Week 5 is low | I41: The forecast view carries closing balance only, with no inflow or outflow detail. | J41: Weekly inflows, outflows and the largest lines behind them, so the obvious follow-up question is answerable on screen. | K41: Only the balance series is stored. | L41: Backend + frontend | M41: 2026-08-11 | N41: Open
A42: QC-038 | B42: 2026-07-28 | C42: Collection | D42: b. Chart accuracy | E42: Chart | F42: Low | G42: No | H42: Worklist bucket column attributes a whole balance to the oldest bucket | I42: PT Anugerah Prima shows 10,000 in the '31-60 days' bucket while the ageing chart splits amounts across all five buckets. | J42: Label it 'Oldest bucket', or split the customer balance by bucket. | K42: Column shows max ageing, header does not say so. | L42: Frontend | M42: 2026-08-18 | N42: Open
A43: QC-039 | B43: 2026-07-28 | C43: All | D43: d. Prompt & response | E43: Content | F43: Medium | G43: Yes | H43: The word 'illustrative' is exposed in the payload | I43: The Finance simulator sets illustrative: true, a note reads 'Illustrative breakdown; profit_summary has no opex line columns in this batch', the FX chart is titled 'FX sensitivity (illustrative)', the vendor score note says 'Score is illustrative (0-100)' and the hedge table note mentions 'an illustrative 170 IDR/USD forward spread'. | J43: Remove developer notes from anything a CFO can see. Keep a single tasteful 'demo data' badge if disclosure is needed. | K43: Debug notes left in the response model. | L43: Backend | M43: 2026-08-11 | N43: Fixed - awaiting retest | Q43: Fixed 30 Jul 2026 (commit f448e66). Removed the 'illustrative' flags, the db_kpis_count / db_profit_count / db_variance_count debug counters, and reworded the debug-flavoured notes. A test now fails if any of them come back.
A44: QC-040 | B44: 2026-07-28 | C44: Treasury | D44: d. Prompt & response | E44: Content | F44: Medium | G44: Yes | H44: It is unclear whether the customer delay is already in the forecast | I44: An alert says a customer delayed IDR 8,000 mn from Week 5 to Week 7. If that delay is already inside the baseline, Week 5 would otherwise be 14,997.5 and there would be no breach at all. | J44: State plainly whether the forecast is before or after the delay. | K44: Baseline definition not documented. | L44: Backend / agent logic | M44: 2026-08-11 | N44: Open
A45: QC-041 | B45: 2026-07-28 | C45: Treasury | D45: d. Prompt & response | E45: Content | F45: Medium | G45: No | H45: Alert title names Week 5 but carries Week 6 data | I45: Alert 'Week 5 cash headroom critically thin' cites 9,012.5 closing and 1,012.5 headroom, which are Week 6 values. | J45: Title matches the week in the evidence. | K45: Template variable mismatch. | L45: Backend / agent logic | M45: 2026-08-11 | N45: Open
A46: QC-042 | B46: 2026-07-28 | C46: All | D46: d. Prompt & response | E46: Content | F46: Medium | G46: Yes | H46: Starter prompts do not show the strongest part of the story | I46: The eight starter prompts are all single-agent. None triggers routing from one agent to another, which is the differentiator. | J46: Add prompts such as 'Which agent should fix the margin problem?' and 'If Collection pulls cash forward, what happens to Week 5?' | K46: Prompt library written per agent in isolation. | L46: Demo owner | M46: 2026-08-11 | N46: Open
A47: QC-043 | B47: 2026-07-28 | C47: All | D47: g. Filters | E47: Feature | F47: High | G47: Yes | H47: The app has no filters at all | I47: No endpoint accepts a filter parameter. There is no legal entity, period, store, category, customer, vendor, currency or scenario filter anywhere. | J47: At minimum: legal entity, period, comparison basis, store, category, customer, risk tier, ageing bucket, vendor, leakage type, week and commitment type. | K47: Filtering was never in scope for the mockup. | L47: Backend + frontend | M47: 2026-08-04 | N47: Open
A48: QC-044 | B48: 2026-07-28 | C48: All | D48: f. Dataset | E48: Data | F48: High | G48: Yes | H48: Dataset is far below the volume the client asked for | I48: Collection shows 8 customers, Leakage shows 8 vendors and 10 transactions, Finance shows 3 product lines. There is no store, item, category or legal entity dimension anywhere in the payload. | J48: Minimum 3 legal entities, 20 stores, 100 items, a full category range and monthly data through Sep 2026. | K48: Mockup was seeded with hand-written illustrative rows. | L48: Backend / data | M48: 2026-08-04 | N48: Open
A49: QC-045 | B49: 2026-07-28 | C49: All | D49: c. Button / menu / function | E49: Untested | F49: High | G49: Yes | H49: Interactive behaviour could not be verified remotely | I49: Buttons, menus, tab switching, simulator sliders, action approve and simulate, chat send and export are all POST or client-side. They cannot be exercised through the read-only API surface available from outside. | J49: Run sheet 02 manually against the live app and record the result. | K49: Not a defect. A scope limit of this review. | L49: Demo owner | M49: 2026-08-04 | N49: Open
A50: QC-046 | B50: 2026-07-28 | C50: Leakage | D50: a. Formula consistency | E50: Logic | F50: Medium | G50: No | H50: Vendor risk score ignores amount and severity | I50: Every vendor scores exactly flags x 20. Osaka Precision KK has 2 flags and scores 40. A vendor with a single lost-discount flag of a few million scores 20, the same as a vendor with a single suspected fraud flag of 3,800 mn. | J50: Score weighted by exposure and severity, so the fraud case ranks first. | K50: Placeholder scoring formula, flagged as illustrative in the payload note. | L50: Backend / agent logic | M50: 2026-08-11 | N50: Fixed - awaiting retest | Q50: Fixed 30 Jul 2026 (commit f448e66). Score = 50% at-risk amount + 35% worst severity + 15% flag count, relative to the worst vendor in the batch. Live batch 17: Osaka 100, Shenzhen 64, Bahan Baku 56, Taipei 33.
A51: QC-047 | B51: 2026-07-28 | C51: Collection + Treasury | D51: a. Formula consistency | E51: Logic | F51: High | G51: Yes | H51: Treasury collection lever is not linked to the Collection book | I51: The Treasury simulator caps 'Accelerate collection' at IDR 8,000 mn. The Collection agent says the single largest customer alone frees 8,500 mn and all overdue frees 32,163 mn. | J51: The Treasury lever maximum should be derived from the Collection worklist, and pulling cash in Treasury should reduce AR in Collection. | K51: The two simulators are independent, so the cross-agent handover is narrative only, not computed. | L51: Backend / agent logic | M51: 2026-08-04 | N51: Open
A52: QC-048 | B52: 2026-07-28 | C52: All | D52: a. Formula consistency | E52: Architecture | F52: Medium | G52: No | H52: The mockup and the deployed app disagree on the numbers | I52: The standalone file 03_CFO_FinanceAI_Suite_Mockup_v9.4 and the deployed Azure app carry different figures. Week 5 cash: 6,698 vs 6,997.5. Forecast length: 14 weeks vs 13. Week 5 shortfall: -1,302 vs -1,002.5. Leakage category chart: populated vs all zeros. Recovery chart third bar: live 'Now' vs hardcoded 'Current 95%'. CLARIFIED 28 Jul: the Azure link is the build under test; the HTML file is the design reference that gets its dataset refreshed. So this is not two competing products, it is a reference that the app has drifted away from. | J52: After both are updated to the replacement dataset, the app's figures should match the reference mockup. Any remaining difference should be a deliberate, documented choice. | K52: The two tracks were updated at different times. The HTML reference is ahead of the deployed app on at least two fixes (leakage categories, recovery bar). | L52: Demo owner + Backend | M52: 2026-08-11 | N52: Open | Q52: Re-graded from Critical to Medium on 28 Jul 2026 after Susan clarified the roles: the Azure link is what gets tested, the mockup only needs its dataset refreshed. Not a demo blocker because the HTML is not shown to the audience. Still worth tracking so the app does not keep drifting from its own reference. An updated mockup carrying the replacement dataset was delivered as v10.0.
A53: QC-049 | B53: 2026-07-28 | C53: All | D53: c. Button / menu / function | E53: Feature gap | F53: Critical | G53: Yes | H53: No formula explanation panel anywhere in the app | I53: The mockup carries an info registry of about 40 entries. Every KPI, chart, table row and simulator stat has an (i) icon that opens the plain-language meaning plus the exact formula, for example 'Closing = Opening + Net cash flow; W5 = 5,789 vs 8,000 buffer'. The Azure dashboard payload has no equivalent field, and openapi.json exposes no endpoint for it. | J53: Every element on screen can explain its own number on demand, with the formula shown. | K53: The deployed app was built to a narrower scope than the reference mockup. | L53: Backend + frontend | M53: 2026-08-04 | N53: Open | Q53: Added 28 Jul 2026 from a feature comparison of mockup v10.0 against the Azure openapi.json endpoint list.
A54: QC-050 | B54: 2026-07-28 | C54: All | D54: c. Button / menu / function | E54: Feature gap | F54: Critical | G54: Yes | H54: No guided story mode | I54: The mockup has a 'Play the CFO story' control that walks the whole narrative automatically. The Azure app has no equivalent. openapi.json shows chat, dashboard, simulators, alerts and actions only. | J54: A scripted guided run, so the demo does not depend on live typing and can be repeated identically. | K54: The deployed app was built to a narrower scope than the reference mockup. | L54: Frontend | M54: 2026-08-04 | N54: Open | Q54: Added 28 Jul 2026 from a feature comparison of mockup v10.0 against the Azure openapi.json endpoint list.
A55: QC-051 | B55: 2026-07-28 | C55: All | D55: c. Button / menu / function | E55: Feature gap | F55: High | G55: Yes | H55: Simulator cannot save, load or compare a scenario | I55: The mockup has Save scenario, a Load scenario dropdown and Compare (n). The Azure app exposes only four recalculate endpoints, with no persistence and no comparison. | J55: At least save one scenario and compare it against the baseline side by side. | K55: The deployed app was built to a narrower scope than the reference mockup. | L55: Backend + frontend | M55: 2026-08-08 | N55: Open | Q55: Added 28 Jul 2026 from a feature comparison of mockup v10.0 against the Azure openapi.json endpoint list.
A56: QC-052 | B56: 2026-07-28 | C56: All | D56: c. Button / menu / function | E56: Feature gap | F56: High | G56: Yes | H56: Simulator has no presets | I56: The mockup offers four named presets per agent, for example 'Recommended: cover 1.8M @ +3%' and 'Base (95% dup / 90% overbill)'. The Azure simulator payload carries inputs and baseline only. | J56: Three to four named presets per agent, so the presenter never has to drag sliders precisely on camera. | K56: The deployed app was built to a narrower scope than the reference mockup. | L56: Backend + frontend | M56: 2026-08-08 | N56: Open | Q56: Added 28 Jul 2026 from a feature comparison of mockup v10.0 against the Azure openapi.json endpoint list.
A57: QC-053 | B57: 2026-07-28 | C57: All | D57: c. Button / menu / function | E57: Feature gap | F57: High | G57: No | H57: Simulator has no scope selector | I57: The mockup lets the user switch between All lines and FX lines, so a lever can be applied to part of the portfolio. The Azure simulator applies every lever to everything. | J57: A scope control, or a clear statement on screen that levers apply to the whole book. | K57: The deployed app was built to a narrower scope than the reference mockup. | L57: Backend + frontend | M57: 2026-08-11 | N57: Open | Q57: Added 28 Jul 2026 from a feature comparison of mockup v10.0 against the Azure openapi.json endpoint list.
A58: QC-054 | B58: 2026-07-28 | C58: All | D58: c. Button / menu / function | E58: Feature gap | F58: High | G58: Yes | H58: KPI tiles have no trend sparkline | I58: Every mockup KPI carries a five-point sparkline. The Azure KPI object has id, view, label, value, unit, delta, alert, value_num, target_num, progress and status, with no trend series. | J58: A short trend series on each KPI, so a CFO sees direction without opening a chart. | K58: The deployed app was built to a narrower scope than the reference mockup. | L58: Backend + frontend | M58: 2026-08-08 | N58: Open | Q58: Added 28 Jul 2026 from a feature comparison of mockup v10.0 against the Azure openapi.json endpoint list.
A59: QC-055 | B59: 2026-07-28 | C59: All | D59: c. Button / menu / function | E59: Feature gap | F59: High | G59: Yes | H59: Actions carry no confidence level | I59: The mockup labels each recommendation, for example 'High confidence' or 'Medium, customer must agree'. The Azure action object has id, action, agent, routes, alert_id, status, spec, impact, simulation_summary and created_at, with no confidence field. | J59: A confidence level and its basis on every action. A CFO will not approve a recommendation that will not say how sure it is. | K59: The deployed app was built to a narrower scope than the reference mockup. | L59: Backend | M59: 2026-08-08 | N59: Open | Q59: Added 28 Jul 2026 from a feature comparison of mockup v10.0 against the Azure openapi.json endpoint list.
A60: QC-056 | B60: 2026-07-28 | C60: All | D60: c. Button / menu / function | E60: Feature gap | F60: High | G60: Yes | H60: No visible cascade when an action executes | I60: The mockup animates the routing, showing each recipient picking the task up in turn. The Azure app has an approve endpoint that returns a status, with nothing to watch. | J60: A visible execution trail across the recipients. This is the single strongest agentic moment in the demo and it currently has no visual. | K60: The deployed app was built to a narrower scope than the reference mockup. | L60: Frontend | M60: 2026-08-08 | N60: Open | Q60: Added 28 Jul 2026 from a feature comparison of mockup v10.0 against the Azure openapi.json endpoint list.
A61: QC-057 | B61: 2026-07-28 | C61: All | D61: c. Button / menu / function | E61: Feature gap | F61: High | G61: Yes | H61: No status notification feed | I61: The mockup has a bell with a live feed of what the agent did and what awaits approval, plus toast pop-ups. Azure has alerts, which are findings, not activity. There is no endpoint for agent activity. | J61: A separate activity feed, distinct from alerts, showing what the agent executed and when. | K61: The deployed app was built to a narrower scope than the reference mockup. | L61: Backend + frontend | M61: 2026-08-11 | N61: Open | Q61: Added 28 Jul 2026 from a feature comparison of mockup v10.0 against the Azure openapi.json endpoint list.
A62: QC-058 | B62: 2026-07-28 | C62: All | D62: c. Button / menu / function | E62: Feature gap | F62: High | G62: Yes | H62: No Bahasa Indonesia toggle | I62: The mockup has a Bahasa ON switch. The Azure app has no language parameter on any endpoint. | J62: A language switch. The audience is Indonesian, and being able to flip to Bahasa mid-demo is a differentiator no competitor will show. | K62: The deployed app was built to a narrower scope than the reference mockup. | L62: Backend + frontend | M62: 2026-08-08 | N62: Open | Q62: Added 28 Jul 2026 from a feature comparison of mockup v10.0 against the Azure openapi.json endpoint list.
A63: QC-059 | B63: 2026-07-28 | C63: All | D63: c. Button / menu / function | E63: Feature gap | F63: High | G63: Yes | H63: No reset to baseline | I63: The mockup has a Reset control that returns every lever and view to the opening state. Azure has DELETE /api/alerts and POST /api/alerts/populate, which clear and reseed alerts, but nothing that resets the simulators. | J63: One control that returns the whole app to its opening state. Without it you cannot record several clean takes. | K63: The deployed app was built to a narrower scope than the reference mockup. | L63: Backend + frontend | M63: 2026-08-04 | N63: Open | Q63: Added 28 Jul 2026 from a feature comparison of mockup v10.0 against the Azure openapi.json endpoint list.
... A66: QC-062 | B66: 2026-07-28 | C66: All | D66: c. Button / menu / function | E66: Feature gap | F66: Medium | G66: No | H66: Chat cannot be verified to render charts and tables | I66: The mockup answers a CFO challenge with a rendered chart plus a table and a confidence badge. The Azure chat endpoint is POST only and cannot be exercised from a read-only review, so this is unknown rather than confirmed missing. | J66: Confirm by running manual test MT-019. If chat returns text only, this becomes a real gap. | K66: The deployed app was built to a narrower scope than the reference mockup. | L66: Demo owner | M66: 2026-08-04 | N66: Open | Q66: Added 28 Jul 2026 from a feature comparison of mockup v10.0 against the Azure openapi.json endpoint list.

Sheet 01B_Findings_ID
A1: Daftar temuan pengujian (Bahasa Indonesia)
A2: Nomor QC sama persis dengan sheet 01_Findings. Kolom kuning diisi oleh tim. Sheet 00_Summary menghitung dari sheet 01, jadi status wajib diperbarui di kedua sheet atau pilih satu sheet sebagai acuan.
A4: No QC | B4: Tanggal temuan | C4: Agent | D4: Area QC | E4: Jenis | F4: Tingkat | G4: Penghambat demo | H4: Temuan | I4: Bukti yang ditemukan | J4: Perilaku yang seharusnya | K4: Dugaan akar masalah | L4: Penanggung jawab | M4: Target selesai | N4: Status | O4: Tanggal uji ulang | P4: Hasil uji ulang | Q4: Catatan
A5: QC-001 | B5: 2026-07-28 | C5: Leakage | D5: a. Kesesuaian formula | E5: Data | F5: Kritis | G5: Ya | H5: Grafik kategori Leakage menampilkan nol semua | I5: Endpoint dashboard finance.leakage mengembalikan views.categories.data dengan semua nilai 0.0 (Bank-change fraud 0, Duplicate payment 0, Overbilling 0, Lost discount 0, Split/threshold 0). Donut 'Leakage mix' juga nol semua, kolom Amount pada worklist berisi '0' untuk 10 baris, dan kolom 'At risk' pada vendor radar berisi '0' untuk 8 vendor. Padahal KPI tile menampilkan 7.845 / 3.800 / 3.050 / 4.300. | J5: Jumlah per kategori harus sama dengan 7.845 mn yang tampil di KPI 'Flagged this cycle'. | K5: Kolom amount tidak ter-mapping untuk import batch 17. KPI agregat dihitung dari query yang berbeda dengan query rincian per kategori. | L5: Backend / data | M5: 2026-07-31 | N5: Sudah diperbaiki - menunggu uji ulang | Q5: Fixed 30 Jul 2026 (branch bug-fix-trial, commit 53daa2c). category_breakdowns.amount_at_risk_idr_mn was probed as amount_idr_mn, so _row_get returned None and every value became 0.0 with no error. Verified on live DB batch 17: bars 3,800 / 3,050 / 900 / 95 sum to 7,845 = the Flagged this cycle card.
A6: QC-002 | B6: 2026-07-28 | C6: Semua agent | D6: a. Kesesuaian formula | E6: Arsitektur | F6: Kritis | G6: Ya | H6: Empat agent berjalan di atas empat batch data yang tidak berhubungan | I6: import_batch_id = 19 untuk Finance, 17 untuk Leakage, 11 untuk Collection, dan 2 untuk Treasury. | J6: Satu ledger bersama, sehingga setiap angka bisa ditelusuri lintas agent. | K6: Tidak ada single source of truth. Setiap agent di-seed secara terpisah. | L6: Backend / data | M6: 2026-07-31 | N6: Terbuka
A7: QC-003 | B7: 2026-07-28 | C7: Finance + Collection | D7: a. Kesesuaian formula | E7: Formula | F7: Kritis | G7: Ya | H7: Basis pendapatan Collection sekitar 15 kali lipat pendapatan Finance | I7: Collection raw.summary.annual_credit_sales_idr_mn = 700.000. KPI revenue Finance = 46.510. Piutang 110.000 setara 2,4 kali seluruh pendapatan tahunan Finance. | J7: DSO harus dibagi dengan pendapatan yang sama dengan yang dilaporkan agent Finance. | K7: Dua dataset seed yang tidak berhubungan (lihat temuan batch di atas). | L7: Backend / data | M7: 2026-07-31 | N7: Terbuka
A8: QC-004 | B8: 2026-07-28 | C8: Treasury | D8: a. Kesesuaian formula | E8: Formula | F8: Kritis | G8: Ya | H8: Aksi penundaan pembayaran menggerakkan headroom ke arah yang salah | I8: Aksi 'Defer noncritical Week 5 payable' menampilkan dampak 'week6 headroom: 1012.5 +3000 -> 4012.5'. Memindahkan utang KE Minggu 6 seharusnya MENURUNKAN headroom Minggu 6, bukan menaikkan. Spec-nya juga mengklaim kas Minggu 5 naik di atas IDR 10.000 mn, padahal 6.997,5 + 3.000 = 9.997,5. | J8: Headroom Minggu 5: -1.002,5 -> +1.997,5 dan headroom Minggu 6: 1.012,5 -> -1.987,5, sehingga trade-off-nya terlihat. | K8: Teks dampak ditulis manual, bukan dihitung dari forecast. Tanda (+/-) dan label minggu dua-duanya salah. | L8: Backend / logika agent | M8: 2026-07-31 | N8: Terbuka
A9: QC-005 | B9: 2026-07-28 | C9: Treasury | D9: a. Kesesuaian formula | E9: Formula | F9: Kritis | G9: Ya | H9: Aksi mencampur headroom dengan saldo kas dalam satu perbandingan | I9: Aksi 'Accelerate Customer A collection' menampilkan 'cash buffer: -1002.5 -> +6997.5'. Angka -1.002,5 adalah headroom, sedangkan 6.997,5 adalah saldo kas akhir. Spec-nya sendiri menyebut penagihan minimal IDR 1.100 mn, yang hanya menghasilkan +97,5. | J9: Satu satuan untuk satu metrik. Pilih headroom -1.002,5 -> +97,5, atau saldo kas 6.997,5 -> 8.097,5. | K9: Teks dampak berupa free text tanpa validasi satuan. | L9: Backend / logika agent | M9: 2026-07-31 | N9: Terbuka
A10: QC-006 | B10: 2026-07-28 | C10: Semua agent | D10: d. Prompt dan respons | E10: Konten | F10: Kritis | G10: Ya | H10: Riwayat percakapan penuh dengan pesan uji coba developer | I10: Endpoint conversations mengembalikan sekitar 190 percakapan tersimpan, termasuk 'test', 'asdsad', 'hello world', 'Test test test', 'selamat pagi', 'does all the right tools work?', 'gimme data', dan 'show me the cahrt'. | J10: Riwayat yang sudah dikurasi, hanya berisi pertanyaan CFO yang kredibel, atau panel riwayat disembunyikan saat event. | K10: Tidak ada pemisahan antara environment development dan environment demo. | L10: Pemilik demo | M10: 2026-07-31 | N10: Terbuka
A11: QC-007 | B11: 2026-07-28 | C11: Collection | D11: a. Kesesuaian formula | E11: Formula | F11: Tinggi | G11: Ya | H11: KPI high-risk dan grafik risk tier tidak sama di layar yang sama | I11: KPI 'High-risk exposure' = 2.500 mn dengan label 'provision / high tier'. Grafik 'Risk exposure by tier' menampilkan High = 5.000 mn. | J11: Ganti nama KPI menjadi 'High-risk provision', atau tampilkan 5.000 agar sama dengan grafik. | K11: KPI membaca field pencadangan, grafik membaca field eksposur. Satu label, dua arti. | L11: Backend / logika agent | M11: 2026-08-04 | N11: Sudah diperbaiki - menunggu uji ulang | Q11: Fixed 30 Jul 2026 (commit 53daa2c). The card showed high_risk_provision (2,500) under a label reading 'exposure'. It now shows the High tier exposure (5,000), which equals the chart bar, with the provision moved to the caption.
A12: QC-008 | B12: 2026-07-28 | C12: Collection | D12: a. Kesesuaian formula | E12: Definisi | F12: Tinggi | G12: Ya | H12: Definisi 'Top 5' berbeda tiga kali di dalam satu agent | I12: Grafik options 'Top 5 - 46d' memakai baris 1-5 worklist (recovery 21.300 mn). Alert 'DSO gap and overdue concentration' memakai top 5 berdasarkan nilai overdue (27.000 mn, 71,17%). Alert 'Mid-tier accounts' memakai top 5 berdasarkan expected recovery (23.225 mn). | J12: Satu definisi saja, dan ditulis di layar. | K12: Setiap tampilan menghitung ranking-nya sendiri. | L12: Backend / logika agent | M12: 2026-08-04 | N12: Terbuka
A13: QC-009 | B13: 2026-07-28 | C13: Finance | D13: a. Kesesuaian formula | E13: Formula | F13: Tinggi | G13: Ya | H13: Ada dua target margin EBITDA yang dipakai bersamaan | I13: KPI tile dan gauge simulator sama-sama menulis 'target 15%'. Alert 'Price recovery opportunity' menyebut margin anggaran 15,7% (EBITDA anggaran 7.200 / pendapatan anggaran 46.000 = 15,65%). | J13: Satu target saja. Kalau acuannya anggaran, pakai 15,7% di semua tempat. | K13: Target gauge di-hardcode ke angka bulat 15%, sedangkan alert menghitung dari anggaran. | L13: Backend / logika agent | M13: 2026-08-04 | N13: Sudah diperbaiki - menunggu uji ulang | Q13: Fixed 30 Jul 2026 (commit f448e66). The target now comes from the budget row (7,200 / 46,000 = 15.65%) and is threaded through the card caption, gauge label, simulator baseline and the recalculate endpoint. NOTE: formula check #18 expects 9.2/15 = 0.6133; with one target it becomes 9.2/15.65 = 0.586, so that check needs updating.
A14: QC-010 | B14: 2026-07-28 | C14: Finance | D14: a. Kesesuaian formula | E14: Formula | F14: Tinggi | G14: Ya | H14: Varians harga sekitar sepuluh kali lebih kecil dari penurunan harga yang diklaim | I14: Alert menyebut harga blended turun 7,6%, dari IDR 127,7k menjadi IDR 118,0k per unit. Waterfall EBITDA hanya menampilkan langkah harga -390 mn atas pendapatan 46.510 mn. Penurunan harga 7,6% seharusnya berdampak sekitar -3.800 mn. | J14: Langkah harga di waterfall dan persentase penurunan di alert harus berasal dari perhitungan yang sama. | K14: Langkah waterfall dan narasi alert dihasilkan dari sumber berbeda. Perlu diverifikasi ke model dasarnya. | L14: Backend / logika agent | M14: 2026-08-04 | N14: Terbuka
A15: QC-011 | B15: 2026-07-28 | C15: Finance | D15: a. Kesesuaian formula | E15: Formula | F15: Tinggi | G15: Ya | H15: Varians COGS disebut dengan dua angka berbeda | I15: Alert dan action memakai COGS overrun IDR 2.930 mn. Waterfall EBITDA menampilkan langkah Cost dan FX sebesar -1.880 mn. | J15: Satu angka varians biaya di seluruh waterfall, alert, dan action card. | K15: Waterfall mungkin sudah menetkan FX ke dalam biaya, sedangkan alert melaporkan biaya bruto. Keduanya belum direkonsiliasi. | L15: Backend / logika agent | M15: 2026-08-04 | N15: Terbuka
A16: QC-012 | B16: 2026-07-28 | C16: Finance | D16: d. Prompt dan respons | E16: Konten | F16: Tinggi | G16: Tidak | H16: Dua angka yang hampir sama artinya berbeda | I16: Langkah Cost dan FX = -1.880 mn. Mix ditambah price = -1.491 + -390 = -1.881 mn, dan sebuah alert melaporkan 'IDR 1.881mn combined profitability loss'. | J16: Pisahkan keduanya di layar, atau bulatkan berbeda supaya tidak tertukar saat presentasi. | K16: Kebetulan pada data seed, tetapi berpotensi membingungkan di atas panggung. | L16: Pemilik demo | M16: 2026-08-04 | N16: Terbuka
A17: QC-013 | B17: 2026-07-28 | C17: Leakage | D17: a. Kesesuaian formula | E17: Formula | F17: Sedang | G17: Tidak | H17: Batang berlabel 'Current 95%' tidak menunjukkan posisi saat ini | I17: Pada grafik 'Recovery scenario' di agent Leakage, batang ketiga berlabel 'Current 95%' bernilai 7.577,5. Batang itu menerapkan 95% ke duplikat dan overbilling sekaligus. Posisi sebenarnya menerapkan 95% ke duplikat dan 90% ke overbilling, hasilnya 7.557,5. Angka itulah yang dipakai KPI 'Total protected' (7.558) dan grafik samping 'Protected vs at risk' (7.557,5). Selisihnya = 400 x 5% = 20 juta. PENTING: selisih ini tidak terlihat mata. KPI dan grafik samping justru sudah cocok satu sama lain, jadi kalau dilihat sekilas memang terasa benar. Yang berbeda hanya grafik recovery, dan 20 dari 7.578 hanya 0,26%. Baru kelihatan lewat tooltip, label angka pada batang, atau kalau ada yang menanyakan angkanya ke agent. | J17: Batang 'Current' memakai set asumsi yang sama dengan KPI, sehingga bernilai 7.557,5. Alternatif lain, ganti namanya menjadi '95% untuk semua' supaya tidak lagi mengaku sebagai posisi saat ini. | K17: Grafik recovery meng-hardcode satu tarif claw-back untuk semua item yang bisa ditarik. Baseline simulator memakai dua tarif berbeda. Keduanya tidak salah secara terpisah. Yang membuat grafiknya keliru adalah label 'Current'. | L17: Backend / logika agent | M17: 2026-08-11 | N17: Sudah diperbaiki - menunggu uji ulang | Q17: Severity diturunkan dari Tinggi ke Sedang pada 28 Juli 2026 setelah diperiksa ulang bersama Susan. Alasan: selisihnya tidak terlihat mata dan bukan penghambat demo. Cacatnya tetap nyata dan tetap perlu diperbaiki. | Fixed 30 Jul 2026 (commit 53daa2c). The bar is now labelled 'Current 95/90%' and reuses the Total protected card value (7,557.5) instead of recomputing it at 95/95 (7,577.5).
A18: QC-014 | B18: 2026-07-28 | C18: Leakage | D18: a. Kesesuaian formula | E18: Formula | F18: Tinggi | G18: Ya | H18: Jumlah flag di KPI tidak cocok dengan tabelnya | I18: KPI 'Flagged this cycle' menulis '22 flags'. Worklist hanya berisi 10 baris dan vendor radar berjumlah 10 flag pada 8 vendor. | J18: Angka pada KPI harus sama dengan jumlah baris yang benar-benar bisa dibuka pengguna. | K18: KPI menghitung exception mentah, sedangkan tabel menampilkan top-N tanpa keterangan 'menampilkan 10 dari 22'. | L18: Backend / logika agent | M18: 2026-08-04 | N18: Sudah diperbaiki - menunggu uji ulang | Q18: Fixed 30 Jul 2026 (commit 53daa2c). The KPI now reads summary.items_flagged (10). The 22 came from len(anomalies), which is LIMIT 30 and includes rows that are not flagged.
A19: QC-015 | B19: 2026-07-28 | C19: Leakage | D19: a. Kesesuaian formula | E19: Formula | F19: Tinggi | G19: Ya | H19: Eksposur split invoice muncul di grafik tetapi di luar total | I19: At risk = 7.845 = fraud 3.800 + duplikat 3.050 + overbilling 400 + other blocked 500 + lost 95. Alert 'Split invoice threshold evasion' melaporkan IDR 1.950 mn, dan 'Split / threshold' adalah salah satu dari lima kategori grafik, tetapi 1.950 tidak masuk ke 7.845. | J19: Pilih: at risk menjadi 9.795, atau split invoice dikeluarkan dari grafik dan dijelaskan. | K19: Agregat at-risk dibuat sebelum deteksi split-threshold ditambahkan. | L19: Backend / logika agent | M19: 2026-08-04 | N19: Sedang dikerjakan | Q19: Partly fixed 30 Jul 2026 (commit 53daa2c). The dashboard no longer contradicts itself: rows with is_direct_loss = false are out of the category bar and mix donut, so both sum to 7,845, and the 1,950 is named in the chart note. The alert wording has NOT been checked yet.
A20: QC-016 | B20: 2026-07-28 | C20: Collection | D20: a. Kesesuaian formula | E20: Formula | F20: Tinggi | G20: Ya | H20: Dampak aksi tidak cocok dengan rekomendasinya sendiri | I20: Aksi 'Accelerate top overdue collections' menyebut penagihan minimal IDR 20.000 mn. Dampaknya tertulis 'DSO: 57.36 -5.21 -> 52.14'. Angka -5,21 hari setara 10.000 mn (10.000 / 1.917,8). Untuk 20.000 mn seharusnya -10,43 hari. | J20: Dampak dihitung ulang dari nilai yang ada di spec. | K20: Teks dampak tersalin dari aksi lain. | L20: Backend / logika agent | M20: 2026-08-04 | N20: Terbuka
A21: QC-017 | B21: 2026-07-28 | C21: Treasury | D21: a. Kesesuaian formula | E21: Formula | F21: Tinggi | G21: Ya | H21: Aksi gabungan hanya menampilkan sebagian dampaknya sendiri | I21: Aksi 'Bridge Week 5 funding gap' menyebut percepatan 2.000 mn ditambah penundaan 3.000 mn, total 5.000 mn. Dampaknya tertulis 'headroom: -1002.5 -> +1997.5', hanya bergerak 3.000 mn. | J21: -1.002,5 -> +3.997,5. | K21: Hanya kaki penundaan yang dihitung. | L21: Backend / logika agent | M21: 2026-08-04 | N21: Terbuka
A22: QC-018 | B22: 2026-07-28 | C22: Collection | D22: a. Kesesuaian formula | E22: Penamaan | F22: Tinggi | G22: Tidak | H22: Aksi memberi label konsentrasi top-2 sebagai porsi overdue keseluruhan | I22: Aksi 'Escalate concentrated exposures' menampilkan 'Overdue share: 43.5% -10% -> 33.5%'. Porsi overdue di dashboard adalah 34,5% (37.935 / 110.000). Angka 43,5% adalah porsi dua pelanggan terbesar terhadap overdue (16.500 / 37.935). | J22: Beri label 'Porsi top-2 terhadap overdue'. | K22: Nama metrik dipakai ulang untuk penyebut yang berbeda. | L22: Backend / logika agent | M22: 2026-08-04 | N22: Terbuka
A23: QC-019 | B23: 2026-07-28 | C23: Treasury | D23: a. Kesesuaian formula | E23: Formula | F23: Tinggi | G23: Ya | H23: Aksi credit line berpatokan pada minggu yang salah | I23: Aksi 'Pre-arrange contingent credit capacity' memakai baseline 1.012,5, yaitu headroom Minggu 6. Pelanggaran buffer terjadi di Minggu 5 pada -1.002,5. Spec-nya lalu menargetkan buffer di atas 4.000 mn. | J23: Baseline -1.002,5 (Minggu 5), hasil +1.997,5 setelah penarikan 3.000 mn. | K23: Minggu yang dipilih sebagai baseline salah. | L23: Backend / logika agent | M23: 2026-08-04 | N23: Terbuka
A24: QC-020 | B24: 2026-07-28 | C24: Semua agent | D24: c. Tombol / menu / fungsi | E24: Integrasi | F24: Tinggi | G24: Ya | H24: Kunci nama agent tidak konsisten antar endpoint | I24: Endpoint agents mengembalikan finance.collection dan finance.treasury. Payload dashboard mengembalikan agent 'collections' dan 'treasury'. Endpoint actions dan alerts memakai 'collection' dan 'cashflow'. | J24: Satu kunci kanonik per agent di semua endpoint. | K24: Penamaan bergeser antara agent registry, dashboard service, dan alert/action service. Join berdasarkan nama agent akan mengembalikan daftar kosong untuk Treasury. | L24: Backend | M24: 2026-08-04 | N24: Terbuka
A25: QC-021 | B25: 2026-07-28 | C25: Semua agent | D25: d. Prompt dan respons | E25: Konten | F25: Tinggi | G25: Ya | H25: 47 action card dengan duplikasi berat | I25: Finance memiliki minimal lima aksi hampir identik tentang rebalance mix ke SKU bermargin tinggi. Leakage memiliki tiga aksi hampir identik 'Launch duplicate payment recovery'. Collection memiliki empat aksi pada dua pelanggan yang sama. | J25: Rapikan menjadi sekitar tiga sampai lima aksi berbeda per agent untuk demo. | K25: Aksi dibuat per alert tanpa tahap clustering, dan alert-nya sendiri sudah duplikatif. | L25: Backend / logika agent | M25: 2026-08-04 | N25: Terbuka
A26: QC-022 | B26: 2026-07-28 | C26: Semua agent | D26: a. Kesesuaian formula | E26: Logika | F26: Tinggi | G26: Ya | H26: Dampak aksi bertumpuk tanpa pengaman double counting | I26: Menyetujui seluruh set Finance menambahkan +1.500, +1.000, +390, +300, dan dua pergerakan poin persentase pada basis EBITDA yang sama yaitu 4.300, padahal beberapa di antaranya menyasar driver yang sama. | J26: Tampilan portofolio yang menetkan aksi yang tumpang tindih dan menampilkan satu dampak gabungan. | K26: Setiap aksi dinilai terpisah terhadap baseline. | L26: Backend / logika agent | M26: 2026-08-04 | N26: Terbuka
A27: QC-023 | B27: 2026-07-28 | C27: Semua agent | D27: d. Prompt dan respons | E27: Konten | F27: Tinggi | G27: Tidak | H27: 47 alert yang sebenarnya menceritakan sekitar delapan hal | I27: Finance memiliki 12 alert yang pada dasarnya semuanya membahas mix, harga, dan biaya. Cashflow memiliki 12 alert yang mengulang pelanggaran buffer Minggu 5. | J27: Kelompokkan menjadi satu alert per isu dasar, dengan peringkat severity. | K27: Tidak ada deduplikasi pada generator alert. | L27: Backend / logika agent | M27: 2026-08-04 | N27: Terbuka
A28: QC-024 | B28: 2026-07-28 | C28: Leakage | D28: b. Kesesuaian grafik | E28: Grafik | F28: Tinggi | G28: Ya | H28: Agent Leakage terbuka pada grafik kosong | I28: default_view adalah 'categories', yaitu grafik nol semua yang dijelaskan pada temuan pertama. | J28: Buka pada tampilan yang berisi data. | K28: Akar masalah sama dengan isu amount nol. | L28: Backend / data | M28: 2026-08-04 | N28: Sudah diperbaiki - menunggu uji ulang | Q28: Fixed 30 Jul 2026 (commit 53daa2c). Same root cause as QC-001; the default view 'categories' now renders four bars on open.
A29: QC-025 | B29: 2026-07-28 | C29: Treasury | D29: a. Kesesuaian formula | E29: Penamaan | F29: Tinggi | G29: Tidak | H29: Aksi FX menyatakan eksposur turun menjadi sebesar nilai hedge | I29: Aksi 'Increase near-term FX protection' menampilkan 'FX exposure: 3.3m -1.3m -> 2.0m'. Melindungi sisa 1,3 juta USD seharusnya membuat eksposur tanpa lindung nilai turun dari 1,3 juta menjadi nol, atau coverage naik dari 61% ke 100%. Seperti tertulis, 2,0 juta adalah nilai hedge, bukan sisa eksposur. | J29: 'Eksposur tanpa lindung nilai: USD 1,3 juta -> USD 0' atau 'Coverage: 61% -> 100%'. | K29: Tertukar antara eksposur bruto dan notional yang di-hedge. | L29: Backend / logika agent | M29: 2026-08-04 | N29: Terbuka
A30: QC-026 | B30: 2026-07-28 | C30: Collection | D30: a. Kesesuaian formula | E30: Logika | F30: Sedang | G30: Tidak | H30: Tingkat recovery mengabaikan umur piutang | I30: Expected recovery hanya ditentukan risk tier: High 40%, Medium 85%, Low 95%. CV Berkah Jaya pada 90+ hari mendapat 40%, sedangkan PT Sumber Makmur pada 61-90 hari mendapat 85%, sama dengan akun 31-60 hari. | J30: Tingkat recovery seharusnya merupakan fungsi dari tier DAN bucket umur piutang. | K30: Model recovery hanya satu faktor. | L30: Backend / logika agent | M30: 2026-08-11 | N30: Terbuka
A31: QC-027 | B31: 2026-07-28 | C31: Finance | D31: a. Kesesuaian formula | E31: Formula | F31: Sedang | G31: Tidak | H31: Satu persentase margin dibulatkan ke bawah, yang lain dibulatkan normal | I31: Gross margin Precision tampil 36,2%. Perhitungan 4.930 / 13.600 = 36,25%, seharusnya tampil 36,3%. Industrial 23,81% -> 23,8 dan Standard 16,67% -> 16,7 sudah benar. | J31: Pembulatan konsisten, half up. | K31: Pemotongan angka (truncation) alih-alih pembulatan pada jalur ini. | L31: Frontend | M31: 2026-08-11 | N31: Sudah diperbaiki - menunggu uji ulang | Q31: Fixed 30 Jul 2026 (commit f448e66). Python and IEEE round half to even, so round(36.25, 1) is 36.2. Added _round_half_up and routed _fmt and _pct through it. Product GM% is now 23.8 / 36.3 / 16.7.
A32: QC-028 | B32: 2026-07-28 | C32: Collection | D32: b. Kesesuaian grafik | E32: Grafik | F32: Sedang | G32: Tidak | H32: Gauge DSO menampilkan progres 120% pada metrik yang justru lebih baik bila rendah | I32: KPI DSO memiliki progress 1,2 (57 / 47). | J32: Balik arah gauge, atau tampilkan selisih hari terhadap target, bukan persentase progres. | K32: Perhitungan progres generik diterapkan pada metrik terbalik. | L32: Frontend | M32: 2026-08-11 | N32: Sudah diperbaiki - menunggu uji ulang | Q32: Fixed 30 Jul 2026 (commit f448e66). Added a lower_is_better flag so enrichment inverts the ratio. DSO progress is now 0.8246 (47/57) instead of the clamped 1.2.
A33: QC-029 | B33: 2026-07-28 | C33: Treasury | D33: d. Prompt dan respons | E33: Format | F33: Sedang | G33: Tidak | H33: Format angka tidak konsisten dalam satu baris KPI | I33: 'Net USD exposure 3.3 M USD' bersebelahan dengan 'Recommended hedge 2,000,000 USD'. Kekurangan kas Minggu 5 muncul sebagai 1.002, 1.002,5, dan 1.003 di tempat berbeda. | J33: Satu format per satuan di seluruh aplikasi. | K33: Tidak ada helper format bersama. | L33: Frontend | M33: 2026-08-11 | N33: Sudah diperbaiki - menunggu uji ulang | Q33: Fixed 30 Jul 2026 (commit f448e66). One USD scale across the KPI row: 3.3 M USD beside 2.0 M USD, instead of 3.3 M USD beside 2,000,000 USD which hid that 2.0 is less than 3.3.
A34: QC-030 | B34: 2026-07-28 | C34: Collection | D34: a. Kesesuaian formula | E34: Penamaan | F34: Sedang | G34: Tidak | H34: Aksi memberi label saldo dua pelanggan sebagai total piutang overdue | I34: Aksi 'Tighten exposure controls' menampilkan 'Overdue AR: 16500 -3000 -> 13500'. Total piutang overdue adalah 37.935. Angka 16.500 adalah dua pelanggan terbesar. | J34: 'Top-2 overdue: 16.500 -> 13.500'. | K34: Nama metrik dipakai ulang. | L34: Backend / logika agent | M34: 2026-08-11 | N34: Terbuka
A35: QC-031 | B35: 2026-07-28 | C35: Leakage | D35: a. Kesesuaian formula | E35: Penamaan | F35: Sedang | G35: Tidak | H35: Aksi memakai angka setahun sementara dashboard menampilkan angka per siklus | I35: Aksi 'Tighten early-payment discount capture' menampilkan 'Discount leakage: 2470 -50% -> 1235'. Angka 'Lost' di dashboard adalah 95 mn. Alert menjelaskan 95 mn per siklus disetahunkan menjadi 2.470 mn. | J35: Cantumkan basisnya di kartu: 'Discount leakage (disetahunkan)'. | K35: Tidak ada label periode pada teks dampak. | L35: Backend / logika agent | M35: 2026-08-11 | N35: Terbuka
A36: QC-032 | B36: 2026-07-28 | C36: Leakage | D36: a. Kesesuaian formula | E36: Penamaan | F36: Sedang | G36: Tidak | H36: Angka 900 mn yang sama muncul dengan tiga nama berbeda | I36: Alert menyebutnya 'IDR 900mn excess vs PO/GRN'. Baseline simulator memecahnya menjadi overbill_amount 400 dan other_blocked 500. Sebuah aksi menyebutnya 'overbilling risk: 900mn'. | J36: Satu nama, dengan rincian pemecahannya di bawahnya. | K36: Penamaan field bergeser. | L36: Backend / logika agent | M36: 2026-08-11 | N36: Terbuka
A37: QC-033 | B37: 2026-07-28 | C37: Collection | D37: b. Kesesuaian grafik | E37: Grafik | F37: Sedang | G37: Tidak | H37: Dua grafik di layar yang sama mengurutkan pasangan data ke arah berlawanan | I37: Grafik utama 'prize' menampilkan Now lalu Target. Grafik samping 'DSO vs target' menampilkan Target lalu Now. | J37: Satu urutan saja. | K37: Konfigurasi grafik dibuat sendiri-sendiri. | L37: Frontend | M37: 2026-08-11 | N37: Sudah diperbaiki - menunggu uji ulang | Q37: Fixed 30 Jul 2026 (commit f448e66). Both charts now order [Now, Target]. Aligning them turned the pair into exact duplicates, so side:bottom was changed to Overdue vs expected recovery.
A38: QC-034 | B38: 2026-07-28 | C38: Treasury | D38: b. Kesesuaian grafik | E38: Grafik | F38: Sedang | G38: Tidak | H38: Batang bernilai nol di sebelah batang bernilai terbaca seperti gagal render | I38: Grafik 'FX impact if we do nothing' menampilkan Base = 0 di sebelah Adverse = 1.777,05. | J38: Tampilkan satu nilai dengan garis acuan, atau beri label eksplisit pada batang nol. | K38: Pilihan jenis grafik. | L38: Frontend | M38: 2026-08-11 | N38: Sudah diperbaiki - menunggu uji ulang | Q38: Fixed 30 Jul 2026 (commit f448e66). The zero 'Base' bar is gone. The chart now compares Do nothing 1,777.05 against Hedge 2.0M 700.05 - both non-zero, and the first equals the FX loss card.
A39: QC-035 | B39: 2026-07-28 | C39: Semua agent | D39: b. Kesesuaian grafik | E39: Grafik | F39: Sedang | G39: Ya | H39: Tidak ada grafik yang mencantumkan periodenya | I39: Tidak satu pun dari empat dashboard menyebutkan apakah angkanya bulanan, year to date, atau setahun penuh. | J39: Setiap judul grafik mencantumkan periode, misalnya 'Okt 2025 sampai Sep 2026'. | K39: Periode tidak menjadi bagian dari payload. | L39: Frontend + backend | M39: 2026-08-11 | N39: Terbuka
A40: QC-036 | B40: 2026-07-28 | C40: Finance | D40: b. Kesesuaian grafik | E40: Grafik | F40: Sedang | G40: Tidak | H40: Grafik samping menduplikasi grafik utama persis | I40: side.top 'Margin by product' memiliki data identik dengan tampilan 'product'. | J40: Gunakan slot samping untuk sesuatu yang tidak ditampilkan tampilan utama. | K40: Placeholder layout belum diganti. | L40: Frontend | M40: 2026-08-11 | N40: Sudah diperbaiki - menunggu uji ulang | Q40: Fixed 30 Jul 2026 (commit f448e66). Finance side:top was byte-identical to view:product. It now shows the gross margin pool in IDR (4,550 / 4,930 / 2,300 = 11,780) rather than repeating the rate.
A41: QC-037 | B41: 2026-07-28 | C41: Treasury | D41: b. Kesesuaian grafik | E41: Grafik | F41: Sedang | G41: Ya | H41: Grafik kas tidak bisa menjawab mengapa Minggu 5 rendah | I41: Tampilan forecast hanya berisi saldo akhir, tanpa rincian arus masuk dan keluar. | J41: Tampilkan arus masuk, arus keluar, dan lini terbesar di baliknya per minggu, supaya pertanyaan lanjutan bisa dijawab langsung di layar. | K41: Hanya seri saldo yang disimpan. | L41: Backend + frontend | M41: 2026-08-11 | N41: Terbuka
A42: QC-038 | B42: 2026-07-28 | C42: Collection | D42: b. Kesesuaian grafik | E42: Grafik | F42: Rendah | G42: Tidak | H42: Kolom bucket pada worklist menempatkan seluruh saldo ke bucket tertua | I42: PT Anugerah Prima menampilkan 10.000 pada bucket '31-60 days', sementara grafik aging memecah nilai ke lima bucket. | J42: Beri label 'Bucket tertua', atau pecah saldo pelanggan per bucket. | K42: Kolom menampilkan umur maksimum, tetapi judulnya tidak menyatakan itu. | L42: Frontend | M42: 2026-08-18 | N42: Terbuka
A43: QC-039 | B43: 2026-07-28 | C43: Semua agent | D43: d. Prompt dan respons | E43: Konten | F43: Sedang | G43: Ya | H43: Kata 'illustrative' terekspos di dalam payload | I43: Simulator Finance menyetel illustrative: true, sebuah note berbunyi 'Illustrative breakdown; profit_summary has no opex line columns in this batch', grafik FX berjudul 'FX sensitivity (illustrative)', note vendor score berbunyi 'Score is illustrative (0-100)', dan note tabel hedge menyebut 'an illustrative 170 IDR/USD forward spread'. | J43: Hapus catatan developer dari apa pun yang bisa dilihat CFO. Kalau perlu disclosure, cukup satu badge 'demo data' yang rapi. | K43: Catatan debug tertinggal di response model. | L43: Backend | M43: 2026-08-11 | N43: Sudah diperbaiki - menunggu uji ulang | Q43: Fixed 30 Jul 2026 (commit f448e66). Removed the 'illustrative' flags, the db_kpis_count / db_profit_count / db_variance_count debug counters, and reworded the debug-flavoured notes. A test now fails if any of them come back.
A44: QC-040 | B44: 2026-07-28 | C44: Treasury | D44: d. Prompt dan respons | E44: Konten | F44: Sedang | G44: Ya | H44: Belum jelas apakah keterlambatan pelanggan sudah masuk ke dalam forecast | I44: Sebuah alert menyebut pelanggan menunda IDR 8.000 mn dari Minggu 5 ke Minggu 7. Kalau penundaan itu sudah ada di dalam baseline, Minggu 5 seharusnya 14.997,5 dan tidak ada pelanggaran buffer sama sekali. | J44: Nyatakan dengan jelas apakah forecast disajikan sebelum atau sesudah penundaan. | K44: Definisi baseline tidak terdokumentasi. | L44: Backend / logika agent | M44: 2026-08-11 | N44: Terbuka
A45: QC-041 | B45: 2026-07-28 | C45: Treasury | D45: d. Prompt dan respons | E45: Konten | F45: Sedang | G45: Tidak | H45: Judul alert menyebut Minggu 5 tetapi datanya Minggu 6 | I45: Alert 'Week 5 cash headroom critically thin' mengutip saldo 9.012,5 dan headroom 1.012,5, yang merupakan nilai Minggu 6. | J45: Judul harus cocok dengan minggu yang ada di buktinya. | K45: Variabel template tertukar. | L45: Backend / logika agent | M45: 2026-08-11 | N45: Terbuka
A46: QC-042 | B46: 2026-07-28 | C46: Semua agent | D46: d. Prompt dan respons | E46: Konten | F46: Sedang | G46: Ya | H46: Starter prompt tidak menampilkan bagian terkuat dari cerita | I46: Delapan starter prompt semuanya single-agent. Tidak ada satu pun yang memicu perpindahan dari satu agent ke agent lain, padahal itu pembedanya. | J46: Tambahkan prompt seperti 'Agent mana yang harus memperbaiki masalah margin?' dan 'Kalau Collection menarik kas lebih awal, apa dampaknya ke Minggu 5?' | K46: Pustaka prompt ditulis per agent secara terpisah. | L46: Pemilik demo | M46: 2026-08-11 | N46: Terbuka
A47: QC-043 | B47: 2026-07-28 | C47: Semua agent | D47: g. Filter | E47: Fitur | F47: Tinggi | G47: Ya | H47: Aplikasi sama sekali tidak punya filter | I47: Tidak ada endpoint yang menerima parameter filter. Tidak ada filter legal entity, periode, toko, kategori, pelanggan, vendor, mata uang, maupun skenario. | J47: Minimal: legal entity, periode, basis pembanding, toko, kategori, pelanggan, risk tier, bucket umur piutang, vendor, jenis kebocoran, minggu, dan jenis komitmen. | K47: Filtering memang tidak masuk lingkup mockup. | L47: Backend + frontend | M47: 2026-08-04 | N47: Terbuka
A48: QC-044 | B48: 2026-07-28 | C48: Semua agent | D48: f. Dataset | E48: Data | F48: Tinggi | G48: Ya | H48: Volume data jauh di bawah permintaan klien | I48: Collection menampilkan 8 pelanggan, Leakage menampilkan 8 vendor dan 10 transaksi, Finance menampilkan 3 lini produk. Tidak ada dimensi toko, item, kategori, maupun legal entity di mana pun dalam payload. | J48: Minimal 3 legal entity, 20 toko, 100 item, kategori yang lengkap, dan data bulanan sampai Sep 2026. | K48: Mockup di-seed dengan baris ilustratif yang ditulis manual. | L48: Backend / data | M48: 2026-08-04 | N48: Terbuka
A49: QC-045 | B49: 2026-07-28 | C49: Semua agent | D49: c. Tombol / menu / fungsi | E49: Belum diuji | F49: Tinggi | G49: Ya | H49: Perilaku interaktif tidak bisa diverifikasi dari luar | I49: Tombol, menu, perpindahan tab, slider simulator, approve dan simulate pada aksi, kirim chat, dan export semuanya berupa POST atau berjalan di sisi klien. Semua itu tidak bisa diuji lewat API read-only yang tersedia dari luar. | J49: Jalankan sheet 02 secara manual pada aplikasi live dan catat hasilnya. | K49: Bukan cacat aplikasi. Ini batas lingkup review. | L49: Pemilik demo | M49: 2026-08-04 | N49: Terbuka
A50: QC-046 | B50: 2026-07-28 | C50: Leakage | D50: a. Kesesuaian formula | E50: Logika | F50: Sedang | G50: Tidak | H50: Skor risiko vendor mengabaikan nilai dan tingkat keparahan | I50: Setiap vendor mendapat skor tepat jumlah flag dikali 20. Osaka Precision KK dengan 2 flag mendapat 40. Vendor dengan satu flag lost discount beberapa juta mendapat 20, sama dengan vendor dengan satu flag dugaan fraud senilai 3.800 mn. | J50: Skor ditimbang berdasarkan eksposur dan severity, sehingga kasus fraud berada di peringkat pertama. | K50: Formula skor masih placeholder, dan memang ditandai 'illustrative' di payload. | L50: Backend / logika agent | M50: 2026-08-11 | N50: Sudah diperbaiki - menunggu uji ulang | Q50: Fixed 30 Jul 2026 (commit f448e66). Score = 50% at-risk amount + 35% worst severity + 15% flag count, relative to the worst vendor in the batch. Live batch 17: Osaka 100, Shenzhen 64, Bahan Baku 56, Taipei 33.
A51: QC-047 | B51: 2026-07-28 | C51: Collection + Treasury | D51: a. Kesesuaian formula | E51: Logika | F51: Tinggi | G51: Ya | H51: Tuas penagihan Treasury tidak terhubung ke buku Collection | I51: Simulator Treasury membatasi 'Accelerate collection' pada IDR 8.000 mn. Agent Collection menyatakan satu pelanggan terbesar saja membebaskan 8.500 mn dan seluruh overdue membebaskan 32.163 mn. | J51: Batas maksimum tuas Treasury seharusnya diturunkan dari worklist Collection, dan menarik kas di Treasury seharusnya mengurangi piutang di Collection. | K51: Kedua simulator berdiri sendiri, sehingga perpindahan antar agent baru bersifat narasi, belum terhitung. | L51: Backend / logika agent | M51: 2026-08-04 | N51: Terbuka
A52: QC-048 | B52: 2026-07-28 | C52: Semua agent | D52: a. Kesesuaian formula | E52: Arsitektur | F52: Sedang | G52: Tidak | H52: Mockup dan aplikasi yang di-deploy menyebut angka berbeda | I52: File mandiri 03_CFO_FinanceAI_Suite_Mockup_v9.4 dan aplikasi Azure membawa angka berbeda. Kas Minggu 5: 6.698 versus 6.997,5. Panjang proyeksi: 14 minggu versus 13. Kekurangan Minggu 5: -1.302 versus -1.002,5. Grafik kategori Leakage: terisi versus nol semua. Batang ketiga grafik recovery: hidup berlabel 'Now' versus mati berlabel 'Current 95%'. DIPERJELAS 28 Juli: link Azure adalah build yang diuji, file HTML adalah acuan desain yang cukup disegarkan datasetnya. Jadi ini bukan dua produk yang bersaing, melainkan acuan yang mulai ditinggalkan oleh aplikasinya. | J52: Setelah keduanya memakai dataset pengganti, angka di aplikasi harus sama dengan mockup acuan. Sisa perbedaan apa pun harus merupakan pilihan yang disengaja dan didokumentasikan. | K52: Kedua jalur diperbarui pada waktu berbeda. Mockup HTML lebih maju dari aplikasi Azure dalam dua perbaikan: kategori Leakage dan batang recovery. | L52: Pemilik demo + Backend | M52: 2026-08-11 | N52: Selesai | Q52: Diturunkan dari Kritis ke Sedang pada 28 Juli 2026 setelah Susan menjelaskan perannya: link Azure yang diuji, mockup cukup disegarkan datasetnya. Bukan penghambat demo karena file HTML tidak ditampilkan ke audiens. Tetap dilacak supaya aplikasinya tidak makin jauh dari acuannya sendiri. Mockup versi baru dengan dataset pengganti sudah dikirim sebagai v10.0.
A53: QC-049 | B53: 2026-07-28 | C53: Semua agent | D53: c. Tombol / menu / fungsi | E53: Fitur hilang | F53: Kritis | G53: Ya | H53: Tidak ada panel penjelasan rumus di mana pun pada aplikasi >> Reasoning | I53: Mockup membawa registry penjelasan berisi sekitar 40 entri. Setiap KPI, grafik, baris tabel, dan angka simulator punya ikon (i) yang membuka arti dalam bahasa sederhana beserta rumus persisnya, misalnya 'Closing = Opening + Net cash flow; W5 = 5.789 versus buffer 8.000'. Payload dashboard Azure tidak punya field sepadan, dan openapi.json tidak memuat endpoint untuk itu. | J53: Setiap elemen di layar bisa menjelaskan angkanya sendiri saat diminta, lengkap dengan rumusnya. | K53: Aplikasi yang di-deploy dibangun dengan lingkup lebih sempit daripada mockup acuan. | L53: Backend + frontend | M53: 2026-08-04 | N53: Terbuka | Q53: Ditambahkan 28 Juli 2026 dari perbandingan fitur mockup v10.0 terhadap daftar endpoint openapi.json Azure.
A54: QC-050 | B54: 2026-07-28 | C54: Semua agent | D54: c. Tombol / menu / fungsi | E54: Fitur hilang | F54: Kritis | G54: Ya | H54: Tidak ada mode cerita terpandu | I54: Mockup punya tombol 'Play the CFO story' yang menjalankan seluruh narasi secara otomatis. Aplikasi Azure tidak punya padanannya. openapi.json hanya memuat chat, dashboard, simulator, alert, dan action. | J54: Ada alur terpandu yang sudah diskenariokan, supaya demo tidak bergantung pada pengetikan langsung dan bisa diulang persis sama. | K54: Aplikasi yang di-deploy dibangun dengan lingkup lebih sempit daripada mockup acuan. | L54: Frontend | M54: 2026-08-04 | N54: Bukan cacat | Q54: Ditambahkan 28 Juli 2026 dari perbandingan fitur mockup v10.0 terhadap daftar endpoint openapi.json Azure.
A55: QC-051 | B55: 2026-07-28 | C55: Semua agent | D55: c. Tombol / menu / fungsi | E55: Fitur hilang | F55: Tinggi | G55: Ya | H55: Simulator tidak bisa menyimpan, memuat, atau membandingkan skenario | I55: Mockup punya Save scenario, dropdown Load scenario, dan Compare (n). Aplikasi Azure hanya memiliki empat endpoint recalculate, tanpa penyimpanan dan tanpa pembanding. | J55: Minimal bisa menyimpan satu skenario dan membandingkannya berdampingan dengan baseline. | K55: Aplikasi yang di-deploy dibangun dengan lingkup lebih sempit daripada mockup acuan. | L55: Backend + frontend | M55: 2026-08-08 | N55: Terbuka | Q55: Ditambahkan 28 Juli 2026 dari perbandingan fitur mockup v10.0 terhadap daftar endpoint openapi.json Azure.
A56: QC-052 | B56: 2026-07-28 | C56: Semua agent | D56: c. Tombol / menu / fungsi | E56: Fitur hilang | F56: Tinggi | G56: Ya | H56: Simulator tidak punya preset | I56: Mockup menyediakan empat preset bernama per agent, misalnya 'Recommended: cover 1.8M @ +3%' dan 'Base (95% dup / 90% overbill)'. Payload simulator Azure hanya memuat inputs dan baseline. | J56: Tiga sampai empat preset bernama per agent, supaya presenter tidak perlu menggeser slider dengan presisi di depan kamera. | K56: Aplikasi yang di-deploy dibangun dengan lingkup lebih sempit daripada mockup acuan. | L56: Backend + frontend | M56: 2026-08-08 | N56: Terbuka | Q56: Ditambahkan 28 Juli 2026 dari perbandingan fitur mockup v10.0 terhadap daftar endpoint openapi.json Azure.
A57: QC-053 | B57: 2026-07-28 | C57: Semua agent | D57: c. Tombol / menu / fungsi | E57: Fitur hilang | F57: Tinggi | G57: Tidak | H57: Simulator tidak punya pemilih cakupan | I57: Mockup memungkinkan pengguna berganti antara All lines dan FX lines, sehingga satu tuas bisa diterapkan hanya ke sebagian portofolio. Simulator Azure menerapkan setiap tuas ke semuanya. | J57: Ada kontrol cakupan, atau pernyataan jelas di layar bahwa tuas berlaku untuk seluruh buku. | K57: Aplikasi yang di-deploy dibangun dengan lingkup lebih sempit daripada mockup acuan. | L57: Backend + frontend | M57: 2026-08-11 | N57: Terbuka | Q57: Ditambahkan 28 Juli 2026 dari perbandingan fitur mockup v10.0 terhadap daftar endpoint openapi.json Azure.
A58: QC-054 | B58: 2026-07-28 | C58: Semua agent | D58: c. Tombol / menu / fungsi | E58: Fitur hilang | F58: Tinggi | G58: Ya | H58: KPI tile tidak punya sparkline tren | I58: Setiap KPI di mockup membawa sparkline lima titik. Objek KPI Azure berisi id, view, label, value, unit, delta, alert, value_num, target_num, progress, dan status, tanpa deret tren. | J58: Ada deret tren pendek di setiap KPI, supaya CFO melihat arahnya tanpa membuka grafik. | K58: Aplikasi yang di-deploy dibangun dengan lingkup lebih sempit daripada mockup acuan. | L58: Backend + frontend | M58: 2026-08-08 | N58: Terbuka | Q58: Ditambahkan 28 Juli 2026 dari perbandingan fitur mockup v10.0 terhadap daftar endpoint openapi.json Azure.
A59: QC-055 | B59: 2026-07-28 | C59: Semua agent | D59: c. Tombol / menu / fungsi | E59: Fitur hilang | F59: Tinggi | G59: Ya | H59: Agentic Action tidak membawa tingkat keyakinan | I59: Mockup memberi label pada setiap rekomendasi, misalnya 'High confidence' atau 'Medium, customer must agree'. Objek action Azure berisi id, action, agent, routes, alert_id, status, spec, impact, simulation_summary, dan created_at, tanpa field keyakinan. | J59: Ada tingkat keyakinan beserta dasarnya di setiap aksi. CFO tidak akan menyetujui rekomendasi yang tidak mau menyebut seberapa yakin dirinya. | K59: Aplikasi yang di-deploy dibangun dengan lingkup lebih sempit daripada mockup acuan. | L59: Backend | M59: 2026-08-08 | N59: Terbuka | Q59: Ditambahkan 28 Juli 2026 dari perbandingan fitur mockup v10.0 terhadap daftar endpoint openapi.json Azure.
A60: QC-056 | B60: 2026-07-28 | C60: Semua agent | D60: c. Tombol / menu / fungsi | E60: Fitur hilang | F60: Tinggi | G60: Ya | H60: Tidak ada tampilan rantai saat aksi dieksekusi | I60: Mockup menganimasikan rutenya, memperlihatkan setiap penerima mengambil tugasnya bergantian. Aplikasi Azure hanya punya endpoint approve yang mengembalikan status, tanpa apa pun untuk dilihat. | J60: Ada jejak eksekusi yang terlihat melintasi para penerima. Ini momen agentic terkuat dalam demo, dan saat ini tidak punya visual sama sekali. | K60: Aplikasi yang di-deploy dibangun dengan lingkup lebih sempit daripada mockup acuan. | L60: Frontend | M60: 2026-08-08 | N60: Terbuka | Q60: Ditambahkan 28 Juli 2026 dari perbandingan fitur mockup v10.0 terhadap daftar endpoint openapi.json Azure.
A61: QC-057 | B61: 2026-07-28 | C61: Semua agent | D61: c. Tombol / menu / fungsi | E61: Fitur hilang | F61: Tinggi | G61: Ya | H61: Tidak ada umpan notifikasi status | I61: Mockup punya lonceng berisi umpan langsung tentang apa yang dikerjakan agent dan apa yang menunggu persetujuan, ditambah pop-up toast. Azure punya alerts, yang isinya temuan, bukan aktivitas. Tidak ada endpoint untuk aktivitas agent. | J61: Ada umpan aktivitas terpisah dari alert, menampilkan apa yang sudah dieksekusi agent dan kapan. | K61: Aplikasi yang di-deploy dibangun dengan lingkup lebih sempit daripada mockup acuan. | L61: Backend + frontend | M61: 2026-08-11 | N61: Terbuka | Q61: Ditambahkan 28 Juli 2026 dari perbandingan fitur mockup v10.0 terhadap daftar endpoint openapi.json Azure.
A62: QC-058 | B62: 2026-07-28 | C62: Semua agent | D62: c. Tombol / menu / fungsi | E62: Fitur hilang | F62: Tinggi | G62: Ya | H62: Tidak ada pengalih Bahasa Indonesia | I62: Mockup punya sakelar Bahasa ON. Aplikasi Azure tidak punya parameter bahasa pada endpoint mana pun. | J62: Ada pengalih bahasa. Audiensnya orang Indonesia, dan kemampuan berpindah ke Bahasa di tengah demo adalah pembeda yang tidak akan ditunjukkan kompetitor. | K62: Aplikasi yang di-deploy dibangun dengan lingkup lebih sempit daripada mockup acuan. | L62: Backend + frontend | M62: 2026-08-08 | N62: Terbuka | Q62: Ditambahkan 28 Juli 2026 dari perbandingan fitur mockup v10.0 terhadap daftar endpoint openapi.json Azure.
A63: QC-059 | B63: 2026-07-28 | C63: Semua agent | D63: c. Tombol / menu / fungsi | E63: Fitur hilang | F63: Tinggi | G63: Ya | H63: Tidak ada tombol kembali ke kondisi awal | I63: Mockup punya tombol Reset yang mengembalikan setiap tuas dan tampilan ke kondisi pembuka. Azure punya DELETE /api/alerts dan POST /api/alerts/populate yang menghapus dan mengisi ulang alert, tetapi tidak ada yang mengembalikan simulator. | J63: Satu tombol yang mengembalikan seluruh aplikasi ke kondisi pembuka. Tanpa itu Anda tidak bisa merekam beberapa take yang bersih. | K63: Aplikasi yang di-deploy dibangun dengan lingkup lebih sempit daripada mockup acuan. | L63: Backend + frontend | M63: 2026-08-04 | N63: Selesai | Q63: Ditambahkan 28 Juli 2026 dari perbandingan fitur mockup v10.0 terhadap daftar endpoint openapi.json Azure.
... A66: QC-062 | B66: 2026-07-28 | C66: Semua agent | D66: c. Tombol / menu / fungsi | E66: Fitur hilang | F66: Sedang | G66: Tidak | H66: Belum bisa dipastikan apakah chat bisa menampilkan grafik dan tabel | I66: Mockup menjawab CFO challenge dengan grafik yang dirender ditambah tabel dan lencana keyakinan. Endpoint chat Azure hanya POST dan tidak bisa diuji dari review read-only, jadi status ini belum diketahui, bukan dipastikan hilang. | J66: Konfirmasi lewat uji manual MT-019. Kalau chat hanya mengembalikan teks, ini menjadi kesenjangan nyata. | K66: Aplikasi yang di-deploy dibangun dengan lingkup lebih sempit daripada mockup acuan. | L66: Pemilik demo | M66: 2026-08-04 | N66: Selesai | Q66: Ditambahkan 28 Juli 2026 dari perbandingan fitur mockup v10.0 terhadap daftar endpoint openapi.json Azure.

Sheet 02_Manual_Test_Checklist
A1: Manual test checklist - things that cannot be tested from outside the app
A2: Run these against the live app and fill the yellow columns. Anything that fails becomes a new row in 01_Findings.
A4: ID | B4: Area | C4: Agent | D4: Test | E4: Steps | F4: Expected result | G4: Priority | H4: Tester | I4: Test date | J4: Result | K4: Defect ID | L4: Notes
A5: MT-001 | B5: Navigation | C5: All | D5: Agent switcher | E5: Click each of the four agents in turn: Finance, Leakage, Collection, Treasury. | F5: Each loads within 3 seconds, the KPI row changes, and no chart is blank. | G5: Critical | J5: Not run | L5: 30 Jul 2026: the blank Leakage charts that caused this Partial are fixed (QC-001 / QC-024). Ready to re-run.
A6: MT-002 | B6: Navigation | C6: All | D6: View tabs | E6: Click every view tab inside each agent (Finance: drivers, revenue, product, fx, opex. Collection: aging, worklist, prize, tiers, options. Leakage: categories, blockvs, recovery, worklist, vendors. Treasury: forecast, exposure, fx, options). | F6: All 19 views render with data. Note any that are empty or throw. | G6: Critical | J6: Not run | L6: 30 Jul 2026: the blank Leakage charts that caused this Partial are fixed (QC-001 / QC-024). Ready to re-run.
A7: MT-003 | B7: Navigation | C7: All | D7: Deep link and refresh | E7: Refresh the browser on a non-default view. | F7: The app returns to a working state rather than an error. | G7: Medium | J7: Not run
A8: MT-004 | B8: Buttons | C8: All | D8: KPI tile click | E8: Click each KPI tile. | F8: The matching view opens. KPI 'view' field suggests this is intended: margin and ebitda open drivers, revenue opens revenue, gm opens product, opex opens opex. | G8: High | J8: Not run
A9: MT-005 | B9: Buttons | C9: All | D9: Explain this KPI | E9: Use the KPI explain action. | F9: A response referencing the correct KPI name and current value. Conversation titles show this feature exists. | G9: High | J9: Not run
A10: MT-006 | B10: Simulator | C10: Finance | D10: Five sliders | E10: Move Price, Cost, Volume, FX and Opex one at a time from the default of 0. | F10: Gauge and scenario figures update on every move. Record the margin at price +5% and confirm it is arithmetically sensible against baseline revenue 46,510 and GM 11,780. | G10: Critical | J10: Not run
A11: MT-007 | B11: Simulator | C11: Finance | D11: Scope selector | E11: Switch scope between 'all' and 'fx'. | F11: The scope actually changes which levers apply. Confirm it is not cosmetic. | G11: High | J11: Not run
A12: MT-008 | B12: Simulator | C12: Finance | D12: Reset | E12: Return all sliders to 0. | F12: Every figure returns exactly to the baseline: EBITDA 4,300, margin 9.2%. | G12: Critical | J12: Not run
A13: MT-009 | B13: Simulator | C13: Collection | D13: Pull and discount | E13: Set Pull from customer to 10,000 and Discount to 1%. | F13: DSO should fall from 57.36 to about 52.14 (10,000 / 1,917.8 = 5.21 days). Confirm the discount cost is deducted somewhere. | G13: Critical | J13: Not run
A14: MT-010 | B14: Simulator | C14: Collection | D14: Maximum boundary | E14: Set Pull to the maximum of 10,000 and back to 0. | F14: No negative DSO, no error, clean return to 57.36. | G14: High | J14: Not run
A15: MT-011 | B15: Simulator | C15: Treasury | D15: Four levers | E15: Move accelerate collection, defer payment, credit line draw and hedge. | F15: Week 5 closing cash and the coverage gauge both respond. Deferring a payment should show where the money moves to, not only that Week 5 improves. | G15: Critical | J15: Not run
A16: MT-012 | B16: Simulator | C16: Treasury | D16: Defer beyond the trough | E16: Defer 3,000 from Week 5. | F16: Check whether Week 6 or Week 7 gets worse. If nothing else changes, the model is only moving one number. | G16: Critical | J16: Not run
A17: MT-013 | B17: Simulator | C17: Leakage | D17: Three levers | E17: Move Hold amount, Dup recovery % and Overbill rec %. | F17: Total protected updates. At the defaults it must read 7,557.5, not 7,577.5. Then open the 'Recovery scenario' chart and hover the 'Current 95%' bar: if its tooltip says 7,577.5 while the KPI says 7,558, QC-013 is confirmed. | G17: High | J17: Not run
A18: MT-014 | B18: Actions | C18: All | D18: Approve | E18: Approve one action. | F18: Status moves from planned. Confirm what actually changes and whether it can be undone. | G18: Critical | J18: Not run
... A35: MT-031 | B35: Stability | C35: All | D35: Full dry run | E35: Run the entire 4-minute demo end to end, twice. | F35: Same result both times, within the time budget. | G35: Critical | J35: Not run

Sheet 02B_Manual_Test_Checklist_ID
A1: Daftar uji manual - hal yang tidak bisa diuji dari luar aplikasi
A2: Jalankan pada aplikasi live lalu isi kolom kuning. Setiap kegagalan menjadi baris baru di sheet 01B_Temuan_Bahasa.
A4: No | B4: Area | C4: Agent | D4: Pengujian | E4: Step | F4: Expected Result | G4: Prioritas | H4: Penguji | I4: Tanggal uji | J4: Hasil | K4: No temuan | L4: Catatan
A5: MT-001 | B5: Navigasi | C5: Semua | D5: Pemilih agent | E5: Klik keempat agent bergantian: Finance, Leakage, Collection, Treasury. | F5: Setiap agent termuat dalam 3 detik, baris KPI berubah, dan tidak ada grafik yang kosong. | G5: Kritis | I5: 46231 | J5: Sebagian | L5: Masih ada grafik yang kosong >> terutama dipart Leakage | 30 Jul 2026: chart Leakage kosong yang menyebabkan Sebagian sudah diperbaiki (QC-001 / QC-024). Siap diuji ulang.
A6: MT-002 | B6: Navigasi | C6: Semua | D6: Tab tampilan | E6: Klik semua tab tampilan di setiap agent (Finance: drivers, revenue, product, fx, opex. Collection: aging, worklist, prize, tiers, options. Leakage: categories, blockvs, recovery, worklist, vendors. Treasury: forecast, exposure, fx, options). | F6: Ke-19 tampilan tampil berisi data. Catat mana yang kosong atau error. | G6: Kritis | I6: 46231 | J6: Sebagian | L6: Masih ada grafik yang kosong >> terutama dipart Leakage | 30 Jul 2026: chart Leakage kosong yang menyebabkan Sebagian sudah diperbaiki (QC-001 / QC-024). Siap diuji ulang.
A7: MT-003 | B7: Navigasi | C7: Semua | D7: Deep link dan refresh | E7: Refresh browser saat berada di tampilan selain default. | F7: Aplikasi kembali ke kondisi normal, bukan error. | G7: Sedang | I7: 46231 | J7: Lulus
A8: MT-004 | B8: Tombol | C8: Semua | D8: Klik KPI tile | E8: Klik setiap KPI tile. | F8: Tampilan yang sesuai terbuka. Field 'view' pada KPI menunjukkan ini memang dirancang begitu: margin dan ebitda membuka drivers, revenue membuka revenue, gm membuka product, opex membuka opex. | G8: Tinggi | J8: Belum diuji
A9: MT-005 | B9: Tombol | C9: Semua | D9: Jelaskan KPI ini | E9: Gunakan fitur explain pada KPI. | F9: Jawaban menyebut nama KPI dan nilainya dengan benar. Judul percakapan tersimpan menunjukkan fitur ini ada. | G9: Tinggi | J9: Belum diuji
A10: MT-006 | B10: Simulator | C10: Finance | D10: Lima slider | E10: Geser Price, Cost, Volume, FX, dan Opex satu per satu dari posisi awal 0. | F10: Gauge dan angka skenario berubah pada setiap pergeseran. Catat margin saat price +5% dan pastikan masuk akal terhadap baseline pendapatan 46.510 dan GM 11.780. | G10: Kritis | I10: 46231 | J10: Lulus
A11: MT-007 | B11: Simulator | C11: Finance | D11: Pemilih scope | E11: Ganti scope antara 'all' dan 'fx'. | F11: Scope benar-benar mengubah tuas mana yang berlaku. Pastikan bukan sekadar kosmetik. | G11: Tinggi | I11: 46231 | J11: Lulus
A12: MT-008 | B12: Simulator | C12: Finance | D12: Reset | E12: Kembalikan semua slider ke 0. | F12: Semua angka kembali persis ke baseline: EBITDA 4.300, margin 9,2%. | G12: Kritis | I12: 46231 | J12: Lulus
A13: MT-009 | B13: Simulator | C13: Collection | D13: Tarik dan diskon | E13: Set 'Pull from customer' ke 10.000 dan Discount ke 1%. | F13: DSO turun dari 57,36 ke sekitar 52,14 (10.000 / 1.917,8 = 5,21 hari). Pastikan biaya diskon dikurangkan di suatu tempat. | G13: Kritis | I13: 46231 | J13: Lulus
A14: MT-010 | B14: Simulator | C14: Collection | D14: Batas maksimum | E14: Set Pull ke maksimum 10.000 lalu kembali ke 0. | F14: Tidak ada DSO negatif, tidak ada error, dan kembali bersih ke 57,36. | G14: Tinggi | I14: 46231 | J14: Gagal | L14: Saya cek DSO ke 53.5
A15: MT-011 | B15: Simulator | C15: Treasury | D15: Empat tuas | E15: Geser accelerate collection, defer payment, credit line draw, dan hedge. | F15: Saldo kas Minggu 5 dan gauge coverage sama-sama merespons. Menunda pembayaran harus menunjukkan uangnya pindah ke mana, bukan hanya bahwa Minggu 5 membaik. | G15: Kritis | I15: 46231 | J15: Lulus | L15: Belum ada contoh yang sesuai
A16: MT-012 | B16: Simulator | C16: Treasury | D16: Tunda melewati titik terendah | E16: Tunda 3.000 dari Minggu 5. | F16: Periksa apakah Minggu 6 atau Minggu 7 menjadi lebih buruk. Kalau tidak ada yang berubah, modelnya hanya memindahkan satu angka. | G16: Kritis | I16: 46231 | J16: Lulus | L16: Belum ada contoh yang sesuai
A17: MT-013 | B17: Simulator | C17: Leakage | D17: Tiga tuas | E17: Geser Hold amount, Dup recovery %, dan Overbill rec %. | F17: Total protected ikut berubah. Pada posisi default harus terbaca 7.557,5, bukan 7.577,5 (lihat QC-013). | G17: Tinggi | I17: 46231 | J17: Lulus
A18: MT-014 | B18: Aksi | C18: Semua | D18: Approve | E18: Setujui satu aksi. | F18: Status berubah dari planned. Pastikan apa yang benar-benar berubah dan apakah bisa dibatalkan. | G18: Kritis | I18: 46231 | J18: Sebagian | L18: Belum bisa dibatalkan
A19: MT-015 | B19: Aksi | C19: Semua | D19: Simulate | E19: Jalankan simulate pada satu aksi. | F19: Saat ini simulation_summary bernilai null pada seluruh 47 aksi. Pastikan endpoint ini menghasilkan sesuatu atau tidak. | G19: Kritis | I19: 46231 | J19: Sebagian | L19: Agent Action belum terimpact pada Action History
A20: MT-016 | B20: Aksi | C20: Semua | D20: Routing | E20: Buka aksi dengan beberapa rute, misalnya Treasury Manager, Procurement, A/P. | F20: Rute terlihat dan bisa dijelaskan di layar. Inilah inti cerita agentic untuk audiens CFO. | G20: Kritis | J20: Belum diuji | L20: Belum dicoba
A21: MT-017 | B21: Chat | C21: Semua | D21: Starter prompt | E21: Jalankan kedelapan starter prompt. | F21: Jawaban mengutip angka yang persis sama dengan dashboard. Catat setiap angka yang berbeda. | G21: Kritis | I21: 46231 | J21: Lulus
A22: MT-018 | B22: Chat | C22: Semua | D22: Perpindahan antar agent | E22: Tanyakan 'siapa yang harus saya libatkan untuk memperbaiki margin' dan 'kalau Collection menarik kas lebih awal, apa dampaknya ke Minggu 5'. | F22: Agent menyebut agent lain lalu menyerahkan tugasnya. Inilah bagian paling penting dari demo. | G22: Kritis | I22: 46231 | J22: Gagal | L22: Muncul error "Object of type Decimal is not JSON serializable"
A23: MT-019 | B23: Chat | C23: Semua | D23: Minta grafik | E23: Tanyakan 'tampilkan EBITDA bridge' dan 'tampilkan umur piutang dalam pie chart'. | F23: Grafik muncul di dalam chat dengan angka yang sama dengan dashboard. | G23: Tinggi | I23: 46231 | J23: Lulus
A24: MT-020 | B24: Chat | C24: Semua | D24: Pertanyaan menantang | E24: Tanyakan 'Anda menyuruh saya menagih pelanggan terbesar saya 10.000 mn, apa dampaknya ke hubungan bisnis'. | F24: Jawaban yang matang, bukan pengulangan worklist. Pertanyaan ini sudah ada di riwayat tersimpan. | G24: Tinggi | I24: 46231 | J24: Lulus
A25: MT-021 | B25: Chat | C25: Semua | D25: Uji halusinasi | E25: Tanyakan angka yang tidak ada, misalnya 'berapa EBITDA kita di Q1 2024'. | F25: Agent menyatakan tidak memiliki datanya, bukan mengarang angka. | G25: Kritis | I25: 46231 | J25: Lulus
A26: MT-022 | B26: Chat | C26: Semua | D26: Bahasa | E26: Ajukan satu pertanyaan dalam Bahasa Indonesia. | F26: Pastikan perilakunya sebelum event supaya tidak ada kejutan bila peserta mencoba. | G26: Sedang | I26: 46231 | J26: Lulus
A27: MT-023 | B27: Chat | C27: Semua | D27: Kecepatan respons | E27: Ukur waktu lima jawaban. | F27: Di bawah sekitar 8 detik. Kalau lebih lambat, siapkan kalimat pengisi di voice over. | G27: Tinggi | I27: 46231 | J27: Terhambat | L27: Masih lambat
A28: MT-024 | B28: Chat | C28: Semua | D28: Panel riwayat | E28: Buka riwayat percakapan. | F28: Pastikan apakah sekitar 190 percakapan uji coba terlihat oleh audiens. Lihat QC-006. | G28: Kritis | I28: 46231 | J28: Lulus
A29: MT-025 | B29: Data | C29: Semua | D29: Export | E29: Coba tombol export atau download apa pun. | F29: File terbuka dan isinya sama dengan yang di layar. | G29: Sedang | J29: Belum diuji | L29: Belum ada feature export dan download
A30: MT-026 | B30: Tampilan | C30: Semua | D30: Uji proyektor | E30: Buka aplikasi pada 1920x1080 dan pada resolusi asli event. | F30: Tidak ada label terpotong, tidak ada legenda bertumpuk, dan terbaca dari belakang ruangan. | G30: Kritis | I30: 46231 | J30: Lulus
A31: MT-027 | B31: Tampilan | C31: Semua | D31: Ruangan terang atau gelap | E31: Lihat pada layar event dengan pencahayaan ruangan sesungguhnya. | F31: Warna grafik tetap bisa dibedakan. | G31: Tinggi | I31: 46231 | J31: Lulus
A32: MT-028 | B32: Tampilan | C32: Semua | D32: Zoom browser | E32: Uji pada 80%, 100%, dan 125%. | F32: Tata letak tetap rapi. | G32: Sedang | I32: 46231 | J32: Lulus
A33: MT-029 | B33: Stabilitas | C33: Semua | D33: Cold start | E33: Diamkan aplikasi 30 menit, lalu buka kembali. | F33: Tidak ada jeda cold start di depan audiens. Azure Container Apps bisa turun ke nol instance. | G33: Kritis | I33: 46231 | J33: Lulus
A34: MT-030 | B34: Stabilitas | C34: Semua | D34: Klik cepat | E34: Klik seluruh tampilan dengan cepat sebanyak dua putaran. | F34: Tidak ada spinner macet dan tidak ada error permintaan ganda. | G34: Tinggi | I34: 46231 | J34: Sebagian | L34: Masih butuh loading
A35: MT-031 | B35: Stabilitas | C35: Semua | D35: Gladi bersih penuh | E35: Jalankan seluruh demo 4 menit dari awal sampai akhir, dua kali. | F35: Hasil sama pada kedua percobaan, dan masuk dalam batas waktu. | G35: Kritis | J35: Belum diuji | L35: Masih menunggu scenario dulu

Sheet 03_Formula_Checks
A1: Formula reconciliation
A2: PASS means the arithmetic on the live app is correct and you can defend it on stage. FAIL means it is wrong and has a QC ID.
A4: # | B4: Agent | C4: What was checked | D4: Calculation performed | E4: Result on the app | F4: Verdict | G4: QC ID | H4: Retest 30 Jul 2026 | I4: What changed
A5: 1 | B5: Finance | C5: Revenue equals the sum of the three product lines | D5: 19,110 + 13,600 + 13,800 = 46,510 | E5: 46,510 | F5: PASS
A6: 2 | B6: Finance | C6: Gross margin equals the sum of the product line margins | D6: 4,550 + 4,930 + 2,300 = 11,780 | E6: 11,780 | F6: PASS
A7: 3 | B7: Finance | C7: Gross margin percentage | D7: 11,780 / 46,510 = 25.33% | E7: 25.3% | F7: PASS
A8: 4 | B8: Finance | C8: EBITDA equals gross margin less opex | D8: 11,780 - 7,480 = 4,300 | E8: 4,300 | F8: PASS
A9: 5 | B9: Finance | C9: EBITDA margin | D9: 4,300 / 46,510 = 9.245% | E9: 9.2% | F9: PASS
A10: 6 | B10: Finance | C10: Opex intensity | D10: 7,480 / 46,510 = 16.08% | E10: 16.1% | F10: PASS
A11: 7 | B11: Finance | C11: EBITDA waterfall closes | D11: 7,200 + 1,341 - 1,491 - 390 - 1,880 - 480 = 4,300 | E11: 4,300 | F11: PASS
A12: 8 | B12: Finance | C12: Opex table actual column sums | D12: 1,650 + 3,300 + 760 + 850 + 920 = 7,480 | E12: 7,480 | F12: PASS
A13: 9 | B13: Finance | C13: Opex table budget column sums | D13: 1,400 + 3,200 + 700 + 800 + 900 = 7,000 | E13: 7,000 | F13: PASS
A14: 10 | B14: Finance | C14: Opex variance ties to the waterfall step | D14: 7,480 - 7,000 = 480, waterfall opex step = -480 | E14: Matches | F14: PASS
A15: 11 | B15: Finance | C15: Product gross margin percentages | D15: 4,550/19,110 = 23.81%, 4,930/13,600 = 36.25%, 2,300/13,800 = 16.67% | E15: 23.8, 36.2, 16.7 | F15: FAIL | G15: QC-027 | H15: PASS | I15: Was 36.2 (banker's rounding). Now 23.8 / 36.3 / 16.7 - QC-027.
A16: 12 | B16: Finance | C16: Opex ratio in the alert | D16: 7,000/46,000 = 15.22% budget, 7,480/46,510 = 16.08% actual | E16: 15.2% to 16.1% | F16: PASS
A17: 13 | B17: Finance | C17: Revenue growth in the alert | D17: 510 / 46,000 = 1.11%. Opex growth 480 / 7,000 = 6.86% | E17: 1.1% vs 6.9% | F17: PASS
A18: 14 | B18: Finance | C18: Budget gross margin implied by the alert | D18: 25.3% + 5.5pt = 30.8%. Budget GM 14,200 / 46,000 = 30.87% | E18: Consistent | F18: PASS
A19: 15 | B19: Finance | C19: Budget EBITDA margin | D19: 7,200 / 46,000 = 15.65% | E19: Alert says 15.7%, gauge says 15% | F19: FAIL | G19: QC-009 | H19: PASS | I19: One target everywhere: 15.7% from the budget row - QC-009.
A20: 16 | B20: Finance | C20: Unit price decline is internally consistent | D20: 127.7k - 118.0k = 9.7k, and 9.7 / 127.7 = 7.6% | E20: Consistent | F20: PASS
A21: 17 | B21: Finance | C21: Price variance is consistent with the price decline | D21: A 7.6% decline on 46,510 revenue implies roughly -3,800 mn, not -390 mn | E21: -390 | F21: FAIL | G21: QC-010
A22: 18 | B22: Finance | C22: Margin KPI progress | D22: 9.2 / 15 = 0.6133 | E22: 0.6133 | F22: PASS | H22: REVIEW | I22: Expected value is now stale. With a single target the progress is 9.2 / 15.65 = 0.586, not 9.2 / 15 = 0.6133. The formula (value / target) is unchanged; only the constant moved.
A23: 19 | B23: Collection | C23: Ageing buckets sum to total AR | D23: 72,065 + 23,935 + 10,300 + 2,700 + 1,000 = 110,000 | E23: 110,000 | F23: PASS
A24: 20 | B24: Collection | C24: Overdue equals AR less current | D24: 110,000 - 72,065 = 37,935 | E24: 37,935 | F24: PASS
A25: 21 | B25: Collection | C25: Overdue share | D25: 37,935 / 110,000 = 34.49% | E25: 34% | F25: PASS
A26: 22 | B26: Collection | C26: Daily credit sales | D26: 700,000 / 365 = 1,917.81 | E26: 1,917.81 | F26: PASS
A27: 23 | B27: Collection | C27: DSO | D27: 110,000 / 1,917.81 = 57.36 days | E27: 57.36 | F27: PASS
A28: 24 | B28: Collection | C28: Cash freed at target | D28: (57.357 - 47) x 1,917.81 = 19,863 | E28: 19,863 | F28: PASS
A29: 25 | B29: Collection | C29: Risk tiers sum to total AR | D29: 65,500 + 39,500 + 5,000 = 110,000 | E29: 110,000 | F29: PASS
A30: 26 | B30: Collection | C30: Worklist expected recovery per row | D30: Every row equals overdue x tier rate: High 40%, Medium 85%, Low 95% | E30: All 8 rows correct | F30: PASS
A31: 27 | B31: Collection | C31: Option 1 DSO | D31: (110,000 - 8,500) / 1,917.81 = 52.9 days | E31: 53d | F31: PASS
A32: 28 | B32: Collection | C32: Option 2 DSO | D32: (110,000 - 21,300) / 1,917.81 = 46.2 days | E32: 46d | F32: PASS
A33: 29 | B33: Collection | C33: Option 3 amount | D33: Worklist recoveries 29,375 plus residual overdue 2,935 at 95% = 32,163.25 | E33: 32,163.25 | F33: PASS
A34: 30 | B34: Collection | C34: Option 3 DSO | D34: (110,000 - 32,163.25) / 1,917.81 = 40.6 days | E34: 41d | F34: PASS
A35: 31 | B35: Collection | C35: Top-5 concentration in the alert | D35: Top 5 by amount 27,000 / 37,935 = 71.17% | E35: 71.17% | F35: PASS
A36: 32 | B36: Collection | C36: Top-5 is used consistently | D36: Three different top-5 sets appear: 21,300, 27,000 and 23,225 | E36: Inconsistent | F36: FAIL | G36: QC-008
A37: 33 | B37: Collection | C37: Medium and high tier share | D37: (39,500 + 5,000) / 110,000 = 40.45% | E37: 40.45% | F37: PASS
A38: 34 | B38: Collection | C38: Top-2 overdue share | D38: 16,500 / 37,935 = 43.50% | E38: 43.5% | F38: PASS
A39: 35 | B39: Collection | C39: High-risk KPI matches the tier chart | D39: KPI 2,500 vs chart High 5,000 | E39: Mismatch | F39: FAIL | G39: QC-007 | H39: PASS | I39: Card now shows the High tier exposure 5,000 = chart bar - QC-007.
A40: 36 | B40: Collection | C40: Action DSO impact matches its own amount | D40: 20,000 / 1,917.81 = 10.43 days, card claims 5.21 days | E40: Mismatch | F40: FAIL | G40: QC-016
A41: 37 | B41: Leakage | C41: At risk equals the category sum | D41: 3,800 + 3,050 + 400 + 500 + 95 = 7,845 | E41: 7,845 | F41: PASS | H41: PASS | I41: Still PASS. The chart now shows overbilling as one 900 category; 400 recoverable + 500 blocked is that same 900 split by payment status. Both decompositions total 7,845.
A42: 38 | B42: Leakage | C42: Blocked, recoverable and lost sum to at risk | D42: 4,300 + 3,450 + 95 = 7,845 | E42: 7,845 | F42: PASS
A43: 39 | B43: Leakage | C43: Blocked equals fraud plus other blocked | D43: 3,800 + 500 = 4,300 | E43: 4,300 | F43: PASS
A44: 40 | B44: Leakage | C44: Recoverable equals duplicates plus overbilling | D44: 3,050 + 400 = 3,450 | E44: 3,450 | F44: PASS
A45: 41 | B45: Leakage | C45: Recovery scenario bars | D45: 4,300 + 3,450 x 60% = 6,370. x 80% = 7,060. x 95% = 7,577.5 | E45: All three correct | F45: PASS | H45: PASS | I45: Verified live: 6,370 / 7,060 / 7,557.5.
A46: 42 | B46: Leakage | C46: Total protected at the simulator defaults | D46: 3,800 + 500 + 3,050x95% + 400x90% = 7,557.5 | E46: 7,557.5 | F46: PASS
A47: 43 | B47: Leakage | C47: The bar labelled 'Current' matches the current position | D47: Chart 'Current 95%' = 4,300 + 3,450 x 95% = 7,577.5. Actual current = 4,300 + 3,050 x 95% + 400 x 90% = 7,557.5 | E47: 7,577.5 vs 7,557.5, gap 20 | F47: FAIL | G47: QC-013 | H47: PASS | I47: Bar reuses the card value, so the 20 mn gap cannot recur - QC-013.
A48: 44 | B48: Leakage | C48: Flag count matches the tables | D48: KPI says 22, tables show 10 | E48: Mismatch | F48: FAIL | G48: QC-014 | H48: PASS | I48: KPI reads summary.items_flagged; both surfaces say 10 - QC-014.
A49: 45 | B49: Leakage | C49: Split invoices are inside the at-risk total | D49: 1,950 reported in an alert but absent from 7,845 | E49: Excluded | F49: FAIL | G49: QC-015 | H49: PARTLY | I49: Dashboard side resolved: control weaknesses are out of the category charts and the 1,950 is named in the note. Alert wording still to be checked - QC-015.
A50: 46 | B50: Leakage | C50: Vendor score formula | D50: Every vendor scores flags x 20, ignoring amount and severity | E50: Weak model | F50: FAIL | G50: QC-046 | H50: PASS | I50: Score now weights amount and severity - QC-046.
A51: 47 | B51: Leakage | C51: Duplicate share of paid leakage | D51: 3,050 / (3,050 + 400) = 88.4% | E51: 88% | F51: PASS
A52: 48 | B52: Treasury | C52: Week 5 headroom | D52: 6,997.5 - 8,000 = -1,002.5 | E52: -1,002 | F52: PASS
A53: 49 | B53: Treasury | C53: Week 6 headroom | D53: 9,012.5 - 8,000 = 1,012.5 | E53: 1,012.5 | F53: PASS
A54: 50 | B54: Treasury | C54: Week 7 headroom | D54: 21,112.5 - 8,000 = 13,112.5 | E54: 13,112.5 | F54: PASS
A55: 51 | B55: Treasury | C55: Adverse rate implied by the FX loss | D55: 1,777.05 mn / 3.3m USD = 538.5 IDR per USD move. 17,950 + 538.5 = 18,488.5 | E55: 18,488.5 | F55: PASS
A56: 52 | B56: Treasury | C56: Loss avoided by the recommended hedge | D56: 2,000,000 x 538.5 = 1,077 mn | E56: 1,077 | F56: PASS
A57: 53 | B57: Treasury | C57: Forward premium | D57: 2,000,000 x 170 = 340 mn | E57: 340 | F57: PASS
A58: 54 | B58: Treasury | C58: Half hedge option | D58: 1,077 / 2 = 538 avoided, 340 / 2 = 170 premium | E58: 538 and 170 | F58: PASS
A59: 55 | B59: Treasury | C59: Spot purchase cash out | D59: 2,000,000 x 17,950 = 35,900 mn | E59: 35,900 | F59: PASS
A60: 56 | B60: Treasury | C60: Hedge coverage | D60: 2,000,000 / 3,300,000 = 60.6% | E60: 61% | F60: PASS
A61: 57 | B61: Treasury | C61: Option B is the recommended one on the numbers | D61: Option C avoids the same 1,077 with zero premium. Only liquidity justifies B, and the table does say so. | E61: Defensible but will be challenged | F61: PASS
A62: 58 | B62: Treasury | C62: Deferral action arithmetic | D62: Two cards compute -1,002.5 + 3,000 = 1,997.5 correctly. Two others do not. | E62: Mixed | F62: FAIL | G62: QC-004
A63: 59 | B63: Treasury | C63: Combined action arithmetic | D63: 2,000 + 3,000 = 5,000 should give +3,997.5, card shows +1,997.5 | E63: Mismatch | F63: FAIL | G63: QC-017
A64: 60 | B64: Cross-agent | C64: Collection revenue base against Finance revenue | D64: 700,000 annual credit sales vs 46,510 Finance revenue | E64: 15x apart | F64: FAIL | G64: QC-003
A65: 61 | B65: Cross-agent | C65: Treasury collection lever against the Collection book | D65: Treasury caps accelerate collection at 8,000 while Collection says one customer alone frees 8,500 | E65: Not linked | F65: FAIL | G65: QC-047
A66: 62 | B66: Cross-agent | C66: Cost variance across surfaces | D66: Waterfall -1,880 vs alerts and actions 2,930 | E66: Two figures | F66: FAIL | G66: QC-011

Sheet 04_Dataset_Requirements
A1: Dataset requirement versus what the mockup contains
A2: The replacement dataset is delivered as a separate workbook: Dataset_AI_Finance_Forum_v1.xlsx
A4: Requirement | B4: Client asked for | C4: In the current mockup | D4: In the replacement dataset | E4: Status | F4: Where to find it
A5: Legal entity | B5: Minimum 3 | C5: None. No entity dimension exists anywhere in the payload. | D5: 3: Indonesia (IDR), Singapore (SGD), Malaysia (MYR) | E5: Met | F5: 10_DIM_Legal_Entity
A6: Store | B6: Minimum 20 | C6: None | D6: 24 stores across 4 formats, 4 channels and 18 cities | E6: Met | F6: 11_DIM_Store
A7: Item | B7: Minimum 100 | C7: None. Finance shows 3 product lines only. | D7: 120 items, ABC classified, imported and local flagged | E7: Met | F7: 13_DIM_Item
A8: Category | B8: A full variety | C8: None | D8: 12 categories across 5 category groups | E8: Met | F8: 12_DIM_Category
A9: Period | B9: Full year through Sep 2026 | C9: Single undated snapshot. No chart states its period. | D9: 21 months, Jan 2025 to Sep 2026, monthly | E9: Met and extended | F9: 20_FACT_Sales
A10: Customers | B10: Not specified | C10: 8 in the worklist | D10: 40 customers with terms, credit limits, risk tiers and payment behaviour | E10: Met | F10: 14_DIM_Customer
A11: Vendors | B11: Not specified | C11: 8 in the vendor radar | D11: 30 vendors across 9 countries and 5 currencies | E11: Met | F11: 15_DIM_Vendor
A12: Transactions | B12: Not specified | C12: 10 leakage rows, 8 AR rows | D12: 25,588 sales lines, 2,016 AR invoices, 630 AP invoices, 288 cash lines | E12: Met | F12: 20 / 30 / 31 / 40
A13: Budget | B13: Implied by variance reporting | C13: A single budget EBITDA of 7,200 with no detail | D13: Budget revenue and COGS by month, entity and category | E13: Met | F13: 21_FACT_Budget
A14: Opex detail | B14: Implied | C14: Flagged in the payload as 'illustrative, profit_summary has no opex line columns in this batch' | D14: 5 opex lines by month and entity, actual and budget | E14: Met | F14: 22_FACT_Opex
A15: Cash forecast | B15: Implied | C15: 13 closing balances with no drivers | D15: 288 individual cash lines rolling up to 13 weekly balances | E15: Met | F15: 40 / 41
... A17: Prior year comparison | B17: Not asked for | C17: Not possible | D17: 2025 included so year-on-year is available | E17: Added | F17: 20_FACT_Sales
A20: Recommended cut-over
A21: 1. Load the replacement dataset as one import batch and repoint all four agents at it. Retire batches 2, 11, 17 and 19.
A22: 2. Rebuild the four agent KPI packs from sheet 50_Agent_KPIs. Every row there states its own derivation.
A23: 3. Run sheet 90_Reconciliation in the dataset workbook after loading. All 14 checks must pass before the demo.
A24: 4. Confirm the four yellow assumptions with the client: minimum cash buffer 8,000 mn, target DSO 47 days, spot rate 17,950 and the 3% adverse move.
A25: 5. Keep the story shape you already have. The replacement numbers land close to the current ones on purpose: revenue about 46,500 mn a month, gross margin about 25%, opex about 16% of revenue, EBITDA about 9%, DSO about 62 days against a 47-day target, and one clear cash trough. Your storyline does not need rewriting.

Sheet 05_Filter_Requirements
A1: Additional filters required
A2: The current API exposes no filter parameters at all. Every filter below is already supported by the replacement dataset.
A4: # | B4: Filter | C4: Applies to | D4: Source column | E4: Values available | F4: Priority | G4: Why a CFO needs it | H4: Status
A5: 1 | B5: Legal entity | C5: All four agents | D5: legal_entity_id | E5: Indonesia, Singapore, Malaysia | F5: Must have | G5: A group CFO reviews by entity first. Without it the demo is one blended number nobody owns. | H5: Not built
A6: 2 | B6: Period and date range | C6: All four agents | D6: month, year, quarter | E6: Jan 2025 to Sep 2026 | F6: Must have | G6: No chart on the current build states its period. The first CFO question will be whether that is the month or the year. | H6: Not built
A7: 3 | B7: Comparison basis | C7: Finance | D7: actual, budget, prior year | E7: Budget for every month, 2025 as prior year | F7: Must have | G7: Variance means nothing without naming what it is measured against. | H7: Not built
A8: 4 | B8: Store or branch | C8: Finance, Collection | D8: store_id | E8: 24 stores | F8: Must have | G8: Regional managers are held to store numbers. | H8: Not built
A9: 5 | B9: Region and country | C9: Finance, Collection | D9: region, country | E9: 18 cities across 3 countries | F9: Should have | G9: Supports the entity roll-up story. | H9: Not built
A10: 6 | B10: Category and category group | C10: Finance, Leakage | D10: category_id, category_group | E10: 12 categories in 5 groups | F10: Must have | G10: Mix is the headline margin story. It cannot be told without category. | H10: Not built
A11: 7 | B11: Item or SKU | C11: Finance | D11: item_id, abc_class | E11: 120 items, ABC classified | F11: Should have | G11: Lets the agent drill from mix down to the actual SKU. | H11: Not built
A12: 8 | B12: Channel | C12: Finance | D12: channel | E12: Retail, Wholesale, B2B Contract, E-commerce | F12: Should have | G12: Discounting behaves very differently by channel. | H12: Not built
A13: 9 | B13: Imported versus local | C13: Finance, Treasury | D13: import_flag | E13: 55% imported, 45% local | F13: Must have | G13: This is the bridge between the margin story and the FX story. | H13: Not built
A14: 10 | B14: Customer | C14: Collection | D14: customer_id | E14: 40 customers | F14: Must have | G14: The worklist is useless without it. | H14: Not built
A15: 11 | B15: Risk tier | C15: Collection | D15: risk_tier | E15: Low, Medium, High | F15: Must have | G15: Drives both the recovery rate and the credit hold decision. | H15: Not built
A16: 12 | B16: Ageing bucket | C16: Collection | D16: aging_bucket | E16: Current, 1-30, 31-60, 61-90, 90+ | F16: Must have | G16: The standard AR review lens. | H16: Not built
... A26: 22 | B26: Scenario reset | C26: All four agents | D26: baseline versus simulated | E26: Application state | F26: Should have | G26: Lets you reset cleanly between takes while recording the demo video. | H26: Not built

Sheet 06_Demo_Readiness_Gate
A1: Go / no-go gate before the CFO event
A2: Work top to bottom. Do not start recording the demo video until every 'Must clear' row is green.
A4: # | B4: Gate | C4: Why it matters for a CFO audience | D4: Depends on | E4: Level | F4: Owner | G4: Due | H4: Status
A5: 1 | B5: Leakage charts show real amounts | C5: The Leakage agent currently opens on a chart of five zeros. A CFO will read that as a broken product in the first ten seconds. | D5: QC-001, QC-024 | E5: Must clear | F5: Backend | G5: 2026-07-31 | H5: Not started
A6: 2 | B6: All four agents run on one dataset | C6: The moment someone asks how DSO relates to revenue, the 15x gap is exposed and the whole model loses credibility. | D6: QC-002, QC-003, QC-044 | E6: Must clear | F6: Backend | G6: 2026-08-04 | H6: Not started
A7: 3 | B7: Action impact strings are computed, not typed | C7: Five action cards currently show arithmetic that contradicts their own text. One screenshot of that ends the deal. | D7: QC-004, QC-005, QC-016, QC-017, QC-019 | E7: Must clear | F7: Backend | G7: 2026-08-04 | H7: Not started
A8: 4 | B8: Conversation history cleaned or hidden | C8: Roughly 190 saved conversations include 'asdsad', 'hello world' and 'test test test'. | D8: QC-006 | E8: Must clear | F8: Demo owner | G8: 2026-07-30 | H8: Not started
A9: 5 | B9: The word 'illustrative' removed from anything visible | C9: Telling a room of CFOs the numbers are illustrative undercuts everything you just showed them. | D9: QC-039 | E9: Must clear | F9: Backend | G9: 2026-07-31 | H9: Not started
A10: 6 | B10: One number per concept | C10: High-risk exposure, top 5, cost variance and the EBITDA target each currently have two or three values. | D10: QC-007, QC-008, QC-009, QC-011, QC-014 | E10: Must clear | F10: Backend | G10: 2026-08-04 | H10: Not started
A11: 7 | B11: Every chart states its period | C11: The first question from the floor will be whether the figure is monthly or annual. | D11: QC-035 | E11: Must clear | F11: Frontend | G11: 2026-08-04 | H11: Not started
A12: 8 | B12: Alerts and actions deduplicated | C12: 47 alerts and 47 actions telling eight stories reads as a model that loops. | D12: QC-021, QC-023 | E12: Must clear | F12: Backend | G12: 2026-08-06 | H12: Not started
A13: 9 | B13: Cross-agent handover actually computes | C13: The agentic handover is the differentiator. Right now it is narrative only. | D13: QC-047, QC-022 | E13: Must clear | F13: Backend | G13: 2026-08-08 | H13: Not started
A14: 10 | B14: Filters live for entity, period and category | C14: Without these the demo cannot answer a follow-up question. | D14: QC-043 | E14: Should clear | F14: Full stack | G14: 2026-08-11 | H14: Not started
A15: 11 | B15: Manual checklist fully run, twice | C15: Sheet 02. Nothing in this review covered buttons, menus, sliders or chat responses. | D15: QC-045 | E15: Must clear | F15: Demo owner | G15: 2026-08-11 | H15: Not started
A16: 12 | B16: Cold start eliminated | C16: Azure Container Apps can scale to zero. A 30-second load in front of the room is fatal. | D16: MT-029 | E16: Must clear | F16: Infrastructure | G16: 2026-08-11 | H16: Not started
... A18: 14 | B18: Full dry run at event resolution | C18: Projector legibility and the 4-minute time budget. | D18: MT-026, MT-031 | E18: Must clear | F18: Demo owner | G18: 2026-08-13 | H18: Not started

Sheet 06B_Demo_Readiness_Gate_ID
A1: Gate Checking go / no-go sebelum event CFO
A2: Kerjakan dari atas ke bawah. Jangan mulai merekam video demo sebelum semua baris 'Wajib tuntas' berstatus Selesai.
A4: No | B4: Gate | C4: Mengapa penting bagi audiens CFO | D4: Bergantung pada | E4: Tingkat | F4: Penanggung jawab | G4: Tenggat | H4: Status
A5: 1 | B5: Grafik Leakage menampilkan angka sungguhan | C5: Agent Leakage saat ini terbuka pada grafik berisi lima angka nol. CFO akan membacanya sebagai produk rusak dalam sepuluh detik pertama. | D5: QC-001, QC-024 | E5: Wajib tuntas | F5: Backend | G5: 2026-07-31 | H5: Belum mulai
A6: 2 | B6: Keempat agent memakai satu dataset | C6: Begitu ada yang bertanya bagaimana DSO berhubungan dengan pendapatan, selisih 15 kali lipat itu terbuka dan seluruh model kehilangan kredibilitas. | D6: QC-002, QC-003, QC-044 | E6: Wajib tuntas | F6: Backend | G6: 2026-08-04 | H6: Belum mulai
A7: 3 | B7: Teks dampak aksi dihitung, bukan diketik | C7: Lima action card saat ini menampilkan perhitungan yang bertentangan dengan teksnya sendiri. Satu tangkapan layar saja bisa menggagalkan peluang. | D7: QC-004, QC-005, QC-016, QC-017, QC-019 | E7: Wajib tuntas | F7: Backend | G7: 2026-08-04 | H7: Belum mulai
A8: 4 | B8: Riwayat percakapan dibersihkan atau disembunyikan | C8: Sekitar 190 percakapan tersimpan berisi 'asdsad', 'hello world', dan 'test test test'. | D8: QC-006 | E8: Wajib tuntas | F8: Pemilik demo | G8: 2026-07-30 | H8: Belum mulai
A9: 5 | B9: Kata 'illustrative' dihapus dari yang terlihat | C9: Memberi tahu ruangan berisi CFO bahwa angkanya hanya ilustrasi akan meruntuhkan semua yang baru saja ditunjukkan. Cukup dibuktikan dengan tingkat confidence saja | D9: QC-039 | E9: Wajib tuntas | F9: Backend | G9: 2026-07-31 | H9: Belum mulai
A10: 6 | B10: Satu angka untuk satu pengertian | C10: High-risk exposure, top 5, varians biaya, dan target EBITDA masing-masing saat ini punya dua sampai tiga nilai berbeda. | D10: QC-007, QC-008, QC-009, QC-011, QC-013, QC-014 | E10: Wajib tuntas | F10: Backend | G10: 2026-08-04 | H10: Belum mulai
A11: 7 | B11: Setiap grafik mencantumkan periodenya | C11: Pertanyaan pertama dari lantai akan berupa apakah angka itu bulanan atau tahunan. | D11: QC-035 | E11: Wajib tuntas | F11: Frontend | G11: 2026-08-04 | H11: Belum mulai
A12: 8 | B12: Alert dan aksi dirapikan dari duplikasi | C12: 47 alert dan 47 aksi yang hanya menceritakan delapan hal terbaca sebagai model yang berputar-putar. | D12: QC-021, QC-023 | E12: Wajib tuntas | F12: Backend | G12: 2026-08-06 | H12: Belum mulai
A13: 9 | B13: Perpindahan antar agent benar-benar terhitung | C13: Perpindahan agentic adalah pembeda utama. Saat ini masih sebatas narasi. | D13: QC-047, QC-022 | E13: Wajib tuntas | F13: Backend | G13: 2026-08-08 | H13: Belum mulai
A14: 10 | B14: Filter entity, periode, dan kategori aktif | C14: Tanpa ketiganya, demo tidak bisa menjawab pertanyaan lanjutan. | D14: QC-043 | E14: Sebaiknya tuntas | F14: Full stack | G14: 2026-08-11 | H14: Belum mulai
A15: 11 | B15: Daftar uji manual dijalankan penuh, dua kali | C15: Sheet 02B. Tidak ada satu pun bagian tombol, menu, slider, dan chat yang tercakup dalam review ini. | D15: QC-045 | E15: Wajib tuntas | F15: Pemilik demo | G15: 2026-08-11 | H15: Sedang dikerjakan
A16: 12 | B16: Cold start dihilangkan | C16: Azure Container Apps bisa turun ke nol instance. Jeda 30 detik di depan ruangan berakibat fatal. | D16: MT-029 | E16: Wajib tuntas | F16: Infrastruktur | G16: 2026-08-11 | H16: Belum mulai
... A18: 14 | B18: Gladi bersih pada resolusi event | C18: Storylinde dengan batas waktu 4 menit. | D18: MT-026, MT-031 | E18: Wajib tuntas | F18: Pemilik demo | G18: 2026-08-13 | H18: Belum mulai

Sheet Technical Priorities ID
A1: PRIORITAS TEKNIS — AI FINANCE FORUM
A2: Prioritas teknis berdasarkan 62 temuan QC dan hasil uji manual per 29 Juli 2026
A4: Story-in-Brief: Fokus pertama adalah memulihkan kredibilitas angka—grafik Leakage, satu dataset lintas agent, dan dampak action yang dihitung dari model. Quick wins yang harus langsung ditutup adalah membersihkan history developer serta teks illustrative. Setelah fondasi angka stabil, selesaikan gap fitur panggung dan tes manual kritis; filter, deduplikasi, dan handoff lintas agent dikerjakan sebagai gelombang berikutnya. Jangan lakukan gladi bersih final sebelum semua prioritas Tinggi selesai dan diuji ulang.
A8: TOTAL TEMUAN | C8: PRIORITAS TINGGI | E8: KESULITAN SUSAH | G8: DEMO BLOCKER | I8: TES MASIH BERISIKO
A9: =COUNTA(A40:A101) | C9: =COUNTIF(I40:I101,"Tinggi") | E9: =COUNTIF(J40:J101,"Susah") | G9: =COUNTIF(E40:E101,"Yes") | I9: =COUNTA(A107:A119)
A12: URUTAN KERJA YANG DIREKOMENDASIKAN
A13: Urut | B13: Workstream | C13: Prioritas | D13: Kesulitan | E13: Dasar & tindakan berikutnya | F13: QC / Test terkait | G13: Owner | H13: Target
A14: 1 | B14: Pulihkan angka dan grafik Leakage | C14: Tinggi | D14: Susah | E14: Perbaiki mapping amount dan satukan query KPI–rincian; tampilan awal saat ini terbaca rusak. | F14: QC-001, QC-024 | G14: Backend / data | H14: 46234
A15: 2 | B15: Satukan dataset keempat agent | C15: Tinggi | D15: Susah | E15: Jadikan satu import batch/ledger sebagai sumber angka lintas Finance, Collection, Leakage, dan Treasury. | F15: QC-002, QC-003, QC-044 | G15: Backend / data | H15: 46238
A16: 3 | B16: Hitung dampak action dari model | C16: Tinggi | D16: Susah | E16: Ganti impact string manual dengan kalkulasi forecast, unit validation, dan guard double-count. | F16: QC-004, 005, 016, 017, 019, 022 | G16: Backend / agent logic | H16: 46238
A17: 4 | B17: Bersihkan history percakapan demo | C17: Tinggi | D17: Mudah | E17: Hapus data developer atau sembunyikan panel history pada environment demo. | F17: QC-006 | G17: Pemilik demo | H17: 46233
A18: 5 | B18: Hapus teks illustrative/debug | C18: Tinggi | D18: Mudah | E18: Bersihkan debug note dari response model yang terlihat audiens. | F18: QC-039 | G18: Backend | H18: 46234
A19: 6 | B19: Samakan definisi dan angka KPI | C19: Tinggi | D19: Sedang | E19: Tetapkan satu definisi untuk exposure, Top 5, target EBITDA, COGS, dan flag count. | F19: QC-007–011, 014–015 | G19: Backend / agent logic | H19: 46238
A20: 7 | B20: Tuntaskan gap fitur panggung utama | C20: Tinggi | D20: Susah | E20: Prioritaskan formula explanation, guided story, reset baseline, dan Bahasa Indonesia sebelum fitur kosmetik. | F20: QC-049, 050, 058, 059 | G20: Backend + frontend | H20: 46238
A21: 8 | B21: Selesaikan tes manual kritis | C21: Tinggi | D21: Sedang | E21: Perbaiki MT gagal/parsial, lalu jalankan seluruh checklist dua kali pada build final. | F21: QC-045; MT-001,002,010,014,015,018 | G21: Pemilik demo + Tech | H21: 46245
A22: 9 | B22: Aktifkan perpindahan antar-agent | C22: Sedang | D22: Susah | E22: Hubungkan Collection–Treasury dan benahi serialisasi Decimal pada handoff chat. | F22: QC-047; MT-018 | G22: Backend / agent logic | H22: 46242
A23: 10 | B23: Rapikan alert dan action duplikat | C23: Sedang | D23: Susah | E23: Tambahkan clustering/deduplication dan tampilkan delapan cerita unik, bukan 47 pengulangan. | F23: QC-021, QC-023 | G23: Backend / agent logic | H23: 46240
A24: 11 | B24: Tambahkan periode dan driver grafik | C24: Sedang | D24: Sedang | E24: Masukkan period ke payload/label dan tambahkan driver untuk menjelaskan cash trough. | F24: QC-035, QC-037 | G24: Frontend + backend | H24: 46245
A25: 12 | B25: Aktifkan filter entity/periode/kategori | C25: Sedang | D25: Susah | E25: Implementasikan dimensi filter end-to-end setelah shared dataset stabil. | F25: QC-043 | G25: Full stack | H25: 46245
... A27: 14 | B27: Gladi bersih resolusi event | C27: Sedang | D27: Mudah | E27: Jalankan storyline empat menit dua kali setelah semua item Tinggi selesai. | F27: MT-031 | G27: Pemilik demo | H27: 46247
A30: RINGKASAN PORTOFOLIO TEMUAN
A31: Prioritas | B31: Jumlah | D31: Kesulitan | E31: Jumlah | G31: ATURAN KLASIFIKASI
A32: Tinggi | B32: =COUNTIF($I$40:$I$101,A32) | D32: Mudah | E32: =COUNTIF($J$40:$J$101,D32) | G32: Tinggi = blocker Critical/High yang terbuka. Sedang = blocker Medium atau High non-blocker. Rendah = sisanya. Kesulitan diestimasi dari cakupan data/arsitektur, dependency lintas komponen, dan jenis perubahan.
A33: Sedang | B33: =COUNTIF($I$40:$I$101,A33) | D33: Sedang | E33: =COUNTIF($J$40:$J$101,D33)
A34: Rendah | B34: =COUNTIF($I$40:$I$101,A34) | D34: Susah | E34: =COUNTIF($J$40:$J$101,D34)
A37: BACKLOG LENGKAP — 62 TEMUAN, DIURUTKAN BERDASARKAN PRIORITAS
A39: ID | B39: Agent | C39: Finding | D39: Severity | E39: Blocker | F39: Status | G39: Owner | H39: Target | I39: Prioritas | J39: Kesulitan | K39: Fix status 30 Jul 2026
A40: QC-004 | B40: Treasury | C40: Deferral action moves headroom the wrong way | D40: Critical | E40: Yes | F40: Open | G40: Backend / agent logic | H40: 46234 | I40: Tinggi | J40: Mudah
A41: QC-006 | B41: All | C41: Conversation history is full of developer test messages | D41: Critical | E41: Yes | F41: Open | G41: Demo owner | H41: 46234 | I41: Tinggi | J41: Mudah
A42: QC-007 | B42: Collection | C42: High-risk KPI and the risk tier chart disagree on the same screen | D42: High | E42: Yes | F42: Sudah diperbaiki - menunggu uji ulang | G42: Backend / agent logic | H42: 46238 | I42: Tinggi | J42: Mudah | K42: Fixed 30 Jul 2026 (commit 53daa2c). The card showed high_risk_provision (2,500) under a label reading 'exposure'. It now shows the High tier exposure (5,000), which equals the chart bar, with the provision moved to the caption.
A43: QC-014 | B43: Leakage | C43: Flag count on the KPI does not match the tables | D43: High | E43: Yes | F43: Sudah diperbaiki - menunggu uji ulang | G43: Backend / agent logic | H43: 46238 | I43: Tinggi | J43: Mudah | K43: Fixed 30 Jul 2026 (commit 53daa2c). The KPI now reads summary.items_flagged (10). The 22 came from len(anomalies), which is LIMIT 30 and includes rows that are not flagged.
A44: QC-021 | B44: All | C44: 47 action cards with heavy duplication | D44: High | E44: Yes | F44: Open | G44: Backend / agent logic | H44: 46238 | I44: Tinggi | J44: Mudah
A45: QC-005 | B45: Treasury | C45: Action mixes headroom with closing cash in one before-and-after | D45: Critical | E45: Yes | F45: Open | G45: Backend / agent logic | H45: 46234 | I45: Tinggi | J45: Sedang
A46: QC-008 | B46: Collection | C46: Top 5' is defined three different ways inside one agent | D46: High | E46: Yes | F46: Open | G46: Backend / agent logic | H46: 46238 | I46: Tinggi | J46: Sedang
A47: QC-009 | B47: Finance | C47: Two different EBITDA margin targets are in use | D47: High | E47: Yes | F47: Sudah diperbaiki - menunggu uji ulang | G47: Backend / agent logic | H47: 46238 | I47: Tinggi | J47: Sedang | K47: Fixed 30 Jul 2026 (commit f448e66). The target now comes from the budget row (7,200 / 46,000 = 15.65%) and is threaded through the card caption, gauge label, simulator baseline and the recalculate endpoint. NOTE: formula check #18 expects 9.2/15 = 0.6133; with one target it becomes 9.2/15.65 = 0.586, so that check needs updating.
A48: QC-010 | B48: Finance | C48: Price variance is roughly ten times too small for the stated price decline | D48: High | E48: Yes | F48: Open | G48: Backend / agent logic | H48: 46238 | I48: Tinggi | J48: Sedang
A49: QC-011 | B49: Finance | C49: COGS variance is stated as two different numbers | D49: High | E49: Yes | F49: Open | G49: Backend / agent logic | H49: 46238 | I49: Tinggi | J49: Sedang
A50: QC-015 | B50: Leakage | C50: Split-invoice exposure sits in the chart but outside the total | D50: High | E50: Yes | F50: Sedang dikerjakan | G50: Backend / agent logic | H50: 46238 | I50: Tinggi | J50: Sedang | K50: Partly fixed 30 Jul 2026 (commit 53daa2c). The dashboard no longer contradicts itself: rows with is_direct_loss = false are out of the category bar and mix donut, so both sum to 7,845, and the 1,950 is named in the chart note. The alert wording has NOT been checked yet.
A51: QC-016 | B51: Collection | C51: Action impact does not match its own recommendation | D51: High | E51: Yes | F51: Open | G51: Backend / agent logic | H51: 46238 | I51: Tinggi | J51: Sedang
A52: QC-017 | B52: Treasury | C52: Combined action shows only part of its own effect | D52: High | E52: Yes | F52: Open | G52: Backend / agent logic | H52: 46238 | I52: Tinggi | J52: Sedang
A53: QC-019 | B53: Treasury | C53: Credit line action is anchored to the wrong week | D53: High | E53: Yes | F53: Open | G53: Backend / agent logic | H53: 46238 | I53: Tinggi | J53: Sedang
A54: QC-022 | B54: All | C54: Action impacts stack with no double-count guard | D54: High | E54: Yes | F54: Open | G54: Backend / agent logic | H54: 46238 | I54: Tinggi | J54: Sedang
A55: QC-045 | B55: All | C55: Interactive behaviour could not be verified remotely | D55: High | E55: Yes | F55: Open | G55: Demo owner | H55: 46238 | I55: Tinggi | J55: Sedang
A56: QC-001 | B56: Leakage | C56: Leakage category chart returns all zeros | D56: Critical | E56: Yes | F56: Sudah diperbaiki - menunggu uji ulang | G56: Backend / data | H56: 46234 | I56: Tinggi | J56: Susah | K56: Fixed 30 Jul 2026 (branch bug-fix-trial, commit 53daa2c). category_breakdowns.amount_at_risk_idr_mn was probed as amount_idr_mn, so _row_get returned None and every value became 0.0 with no error. Verified on live DB batch 17: bars 3,800 / 3,050 / 900 / 95 sum to 7,845 = the Flagged this cycle card.
A57: QC-002 | B57: All | C57: The four agents run on four unrelated data batches | D57: Critical | E57: Yes | F57: Open | G57: Backend / data | H57: 46234 | I57: Tinggi | J57: Susah
A58: QC-003 | B58: Finance + Collection | C58: Collection revenue base is about 15 times the Finance revenue | D58: Critical | E58: Yes | F58: Open | G58: Backend / data | H58: 46234 | I58: Tinggi | J58: Susah
A59: QC-020 | B59: All | C59: Agent keys are inconsistent between endpoints | D59: High | E59: Yes | F59: Open | G59: Backend | H59: 46238 | I59: Tinggi | J59: Susah
A60: QC-024 | B60: Leakage | C60: The Leakage agent opens on an empty chart | D60: High | E60: Yes | F60: Sudah diperbaiki - menunggu uji ulang | G60: Backend / data | H60: 46238 | I60: Tinggi | J60: Susah | K60: Fixed 30 Jul 2026 (commit 53daa2c). Same root cause as QC-001; the default view 'categories' now renders four bars on open.
A61: QC-043 | B61: All | C61: The app has no filters at all | D61: High | E61: Yes | F61: Open | G61: Backend + frontend | H61: 46238 | I61: Tinggi | J61: Susah
A62: QC-044 | B62: All | C62: Dataset is far below the volume the client asked for | D62: High | E62: Yes | F62: Open | G62: Backend / data | H62: 46238 | I62: Tinggi | J62: Susah
A63: QC-047 | B63: Collection + Treasury | C63: Treasury collection lever is not linked to the Collection book | D63: High | E63: Yes | F63: Open | G63: Backend / agent logic | H63: 46238 | I63: Tinggi | J63: Susah
A64: QC-049 | B64: All | C64: No formula explanation panel anywhere in the app | D64: Critical | E64: Yes | F64: Open | G64: Backend + frontend | H64: 46238 | I64: Tinggi | J64: Susah
A65: QC-050 | B65: All | C65: No guided story mode | D65: Critical | E65: Yes | F65: Open | G65: Frontend | H65: 46238 | I65: Tinggi | J65: Susah
A66: QC-051 | B66: All | C66: Simulator cannot save, load or compare a scenario | D66: High | E66: Yes | F66: Open | G66: Backend + frontend | H66: 46242 | I66: Tinggi | J66: Susah
A67: QC-052 | B67: All | C67: Simulator has no presets | D67: High | E67: Yes | F67: Open | G67: Backend + frontend | H67: 46242 | I67: Tinggi | J67: Susah
A68: QC-054 | B68: All | C68: KPI tiles have no trend sparkline | D68: High | E68: Yes | F68: Open | G68: Backend + frontend | H68: 46242 | I68: Tinggi | J68: Susah
A69: QC-055 | B69: All | C69: Actions carry no confidence level | D69: High | E69: Yes | F69: Open | G69: Backend | H69: 46242 | I69: Tinggi | J69: Susah
A70: QC-056 | B70: All | C70: No visible cascade when an action executes | D70: High | E70: Yes | F70: Open | G70: Frontend | H70: 46242 | I70: Tinggi | J70: Susah
A71: QC-057 | B71: All | C71: No status notification feed | D71: High | E71: Yes | F71: Open | G71: Backend + frontend | H71: 46245 | I71: Tinggi | J71: Susah
A72: QC-058 | B72: All | C72: No Bahasa Indonesia toggle | D72: High | E72: Yes | F72: Open | G72: Backend + frontend | H72: 46242 | I72: Tinggi | J72: Susah
... A76: QC-025 | B76: Treasury | C76: FX action states exposure falls to the hedge amount | D76: High | E76: No | F76: Open | G76: Backend / agent logic | H76: 46238 | I76: Sedang | J76: Mudah
A77: QC-039 | B77: All | C77: The word 'illustrative' is exposed in the payload | D77: Medium | E77: Yes | F77: Sudah diperbaiki - menunggu uji ulang | G77: Backend | H77: 46245 | I77: Sedang | J77: Mudah | K77: Fixed 30 Jul 2026 (commit f448e66). Removed the 'illustrative' flags, the db_kpis_count / db_profit_count / db_variance_count debug counters, and reworded the debug-flavoured notes. A test now fails if any of them come back.
A78: QC-040 | B78: Treasury | C78: It is unclear whether the customer delay is already in the forecast | D78: Medium | E78: Yes | F78: Open | G78: Backend / agent logic | H78: 46245 | I78: Sedang | J78: Mudah
A79: QC-023 | B79: All | C79: 47 alerts telling roughly eight distinct stories | D79: High | E79: No | F79: Open | G79: Backend / agent logic | H79: 46238 | I79: Sedang | J79: Sedang
A80: QC-042 | B80: All | C80: Starter prompts do not show the strongest part of the story | D80: Medium | E80: Yes | F80: Open | G80: Demo owner | H80: 46245 | I80: Sedang | J80: Sedang
A81: QC-035 | B81: All | C81: No chart states its period | D81: Medium | E81: Yes | F81: Open | G81: Frontend + backend | H81: 46245 | I81: Sedang | J81: Susah
A82: QC-037 | B82: Treasury | C82: The cash chart cannot answer why Week 5 is low | D82: Medium | E82: Yes | F82: Open | G82: Backend + frontend | H82: 46245 | I82: Sedang | J82: Susah
A83: QC-053 | B83: All | C83: Simulator has no scope selector | D83: High | E83: No | F83: Open | G83: Backend + frontend | H83: 46245 | I83: Sedang | J83: Susah
A84: QC-013 | B84: Leakage | C84: The bar labelled 'Current 95%' does not show the current position | D84: Medium | E84: No | F84: Sudah diperbaiki - menunggu uji ulang | G84: Backend / agent logic | H84: 46245 | I84: Rendah | J84: Mudah | K84: Fixed 30 Jul 2026 (commit 53daa2c). The bar is now labelled 'Current 95/90%' and reuses the Total protected card value (7,557.5) instead of recomputing it at 95/95 (7,577.5).
A85: QC-027 | B85: Finance | C85: One margin percentage rounds down where others round normally | D85: Medium | E85: No | F85: Sudah diperbaiki - menunggu uji ulang | G85: Frontend | H85: 46245 | I85: Rendah | J85: Mudah | K85: Fixed 30 Jul 2026 (commit f448e66). Python and IEEE round half to even, so round(36.25, 1) is 36.2. Added _round_half_up and routed _fmt and _pct through it. Product GM% is now 23.8 / 36.3 / 16.7.
A86: QC-029 | B86: Treasury | C86: Inconsistent number formats in one KPI row | D86: Medium | E86: No | F86: Sudah diperbaiki - menunggu uji ulang | G86: Frontend | H86: 46245 | I86: Rendah | J86: Mudah | K86: Fixed 30 Jul 2026 (commit f448e66). One USD scale across the KPI row: 3.3 M USD beside 2.0 M USD, instead of 3.3 M USD beside 2,000,000 USD which hid that 2.0 is less than 3.3.
A87: QC-030 | B87: Collection | C87: Action labels a two-customer balance as total overdue AR | D87: Medium | E87: No | F87: Open | G87: Backend / agent logic | H87: 46245 | I87: Rendah | J87: Mudah
A88: QC-031 | B88: Leakage | C88: Action uses the annualised figure while the dashboard shows the cycle figure | D88: Medium | E88: No | F88: Open | G88: Backend / agent logic | H88: 46245 | I88: Rendah | J88: Mudah
A89: QC-032 | B89: Leakage | C89: The same 900 mn appears under three different names | D89: Medium | E89: No | F89: Open | G89: Backend / agent logic | H89: 46245 | I89: Rendah | J89: Mudah
A90: QC-041 | B90: Treasury | C90: Alert title names Week 5 but carries Week 6 data | D90: Medium | E90: No | F90: Open | G90: Backend / agent logic | H90: 46245 | I90: Rendah | J90: Mudah
A91: QC-026 | B91: Collection | C91: Recovery rate ignores how old the debt is | D91: Medium | E91: No | F91: Open | G91: Backend / agent logic | H91: 46245 | I91: Rendah | J91: Sedang
A92: QC-028 | B92: Collection | C92: DSO gauge shows 120% progress on a metric where lower is better | D92: Medium | E92: No | F92: Sudah diperbaiki - menunggu uji ulang | G92: Frontend | H92: 46245 | I92: Rendah | J92: Sedang | K92: Fixed 30 Jul 2026 (commit f448e66). Added a lower_is_better flag so enrichment inverts the ratio. DSO progress is now 0.8246 (47/57) instead of the clamped 1.2.
A93: QC-034 | B93: Treasury | C93: A zero bar next to a value bar reads as a rendering failure | D93: Medium | E93: No | F93: Sudah diperbaiki - menunggu uji ulang | G93: Frontend | H93: 46245 | I93: Rendah | J93: Sedang | K93: Fixed 30 Jul 2026 (commit f448e66). The zero 'Base' bar is gone. The chart now compares Do nothing 1,777.05 against Hedge 2.0M 700.05 - both non-zero, and the first equals the FX loss card.
A94: QC-036 | B94: Finance | C94: The side chart duplicates the main chart exactly | D94: Medium | E94: No | F94: Sudah diperbaiki - menunggu uji ulang | G94: Frontend | H94: 46245 | I94: Rendah | J94: Sedang | K94: Fixed 30 Jul 2026 (commit f448e66). Finance side:top was byte-identical to view:product. It now shows the gross margin pool in IDR (4,550 / 4,930 / 2,300 = 11,780) rather than repeating the rate.
A95: QC-038 | B95: Collection | C95: Worklist bucket column attributes a whole balance to the oldest bucket | D95: Low | E95: No | F95: Open | G95: Frontend | H95: 46252 | I95: Rendah | J95: Sedang
A96: QC-046 | B96: Leakage | C96: Vendor risk score ignores amount and severity | D96: Medium | E96: No | F96: Sudah diperbaiki - menunggu uji ulang | G96: Backend / agent logic | H96: 46245 | I96: Rendah | J96: Sedang | K96: Fixed 30 Jul 2026 (commit f448e66). Score = 50% at-risk amount + 35% worst severity + 15% flag count, relative to the worst vendor in the batch. Live batch 17: Osaka 100, Shenzhen 64, Bahan Baku 56, Taipei 33.
A97: QC-033 | B97: Collection | C97: Two charts on the same screen order the same pair in opposite directions | D97: Medium | E97: No | F97: Sudah diperbaiki - menunggu uji ulang | G97: Frontend | H97: 46245 | I97: Rendah | J97: Susah | K97: Fixed 30 Jul 2026 (commit f448e66). Both charts now order [Now, Target]. Aligning them turned the pair into exact duplicates, so side:bottom was changed to Overdue vs expected recovery.
A98: QC-048 | B98: All | C98: The mockup and the deployed app disagree on the numbers | D98: Medium | E98: No | F98: Open | G98: Demo owner + Backend | H98: 46245 | I98: Rendah | J98: Susah
A99: QC-060 | B99: All | C99: No exact-parameter calculation flow | D99: Medium | E99: No | F99: Open | G99: Backend + frontend | H99: 46245 | I99: Rendah | J99: Susah
A100: QC-061 | B100: All | C100: Next best action cards are not on the dashboard | D100: Medium | E100: No | F100: Open | G100: Frontend | H100: 46245 | I100: Rendah | J100: Susah
A101: QC-062 | B101: All | C101: Chat cannot be verified to render charts and tables | D101: Medium | E101: No | F101: Open | G101: Demo owner | H101: 46238 | I101: Rendah | J101: Susah
A104: UJI MANUAL YANG BELUM LULUS / BELUM SELESAI
A106: ID | B106: Area | C106: Agent | D106: Pengujian | E106: Prioritas test | F106: Hasil | G106: Defect ID | H106: Catatan | I106: Prioritas | J106: Kesulitan
A107: MT-001 | B107: Navigasi | C107: Semua | D107: Pemilih agent | E107: Kritis | F107: Sebagian | H107: Masih ada grafik yang kosong >> terutama dipart Leakage | I107: Tinggi | J107: Mudah
A108: MT-002 | B108: Navigasi | C108: Semua | D108: Tab tampilan | E108: Kritis | F108: Sebagian | H108: Masih ada grafik yang kosong >> terutama dipart Leakage | I108: Tinggi | J108: Mudah
A109: MT-004 | B109: Tombol | C109: Semua | D109: Klik KPI tile | E109: Tinggi | F109: Belum diuji | I109: Sedang | J109: Mudah
A110: MT-005 | B110: Tombol | C110: Semua | D110: Jelaskan KPI ini | E110: Tinggi | F110: Belum diuji | I110: Sedang | J110: Mudah
A111: MT-010 | B111: Simulator | C111: Collection | D111: Batas maksimum | E111: Tinggi | F111: Gagal | H111: Saya cek DSO ke 53.5 | I111: Tinggi | J111: Mudah
A112: MT-014 | B112: Aksi | C112: Semua | D112: Approve | E112: Kritis | F112: Sebagian | H112: Belum bisa dibatalkan | I112: Tinggi | J112: Sedang
A113: MT-015 | B113: Aksi | C113: Semua | D113: Simulate | E113: Kritis | F113: Sebagian | H113: Agent Action belum terimpact pada Action History | I113: Tinggi | J113: Sedang
A114: MT-016 | B114: Aksi | C114: Semua | D114: Routing | E114: Kritis | F114: Belum diuji | H114: Belum dicoba | I114: Tinggi | J114: Sedang
A115: MT-018 | B115: Chat | C115: Semua | D115: Perpindahan antar agent | E115: Kritis | F115: Gagal | H115: Muncul error "Object of type Decimal is not JSON serializable" | I115: Tinggi | J115: Sedang
A116: MT-023 | B116: Chat | C116: Semua | D116: Kecepatan respons | E116: Tinggi | F116: Terhambat | H116: Masih lambat | I116: Tinggi | J116: Sedang
A117: MT-025 | B117: Data | C117: Semua | D117: Export | E117: Sedang | F117: Belum diuji | H117: Belum ada feature export dan download | I117: Sedang | J117: Mudah
A118: MT-030 | B118: Stabilitas | C118: Semua | D118: Klik cepat | E118: Tinggi | F118: Sebagian | H118: Masih butuh loading | I118: Sedang | J118: Sedang
...

Sheet Technical Priorities EN
A1: TECHNICAL PRIORITIES — AI FINANCE FORUM
A2: Technical prioritization based on 62 QC findings and manual-test results as of 29 July 2026
A4: Story-in-Brief: First restore confidence in the numbers���the Leakage charts, one shared dataset across agents, and action impacts calculated from the model. Immediate quick wins are removing developer conversation history and all illustrative/debug wording. Once the numerical foundation is stable, close the stage-critical feature gaps and critical manual tests; filters, deduplication, and cross-agent handoffs follow in the next wave. Do not run the final rehearsal until every High-priority item is complete and retested.
A8: TOTAL FINDINGS | C8: HIGH PRIORITY | E8: DIFFICULT | G8: DEMO BLOCKERS | I8: TESTS STILL AT RISK
A9: =COUNTA(A40:A101) | C9: =COUNTIF(I40:I101,"High") | E9: =COUNTIF(J40:J101,"Difficult") | G9: =COUNTIF(E40:E101,"Yes") | I9: =COUNTA(A107:A119)
A12: RECOMMENDED DELIVERY SEQUENCE
A13: Order | B13: Workstream | C13: Priority | D13: Difficulty | E13: Rationale & next action | F13: Related QC / Test | G13: Owner | H13: Target
A14: 1 | B14: Restore Leakage numbers and charts | C14: High | D14: Difficult | E14: Fix amount mapping and unify KPI/detail queries; the current landing view appears broken. | F14: QC-001, QC-024 | G14: Backend / data | H14: 46234
A15: 2 | B15: Unify the dataset across all four agents | C15: High | D15: Difficult | E15: Use one import batch/ledger as the source of truth across Finance, Collection, Leakage, and Treasury. | F15: QC-002, QC-003, QC-044 | G15: Backend / data | H15: 46238
A16: 3 | B16: Calculate action impacts from the model | C16: High | D16: Difficult | E16: Replace manual impact strings with forecast calculations, unit validation, and double-count protection. | F16: QC-004, 005, 016, 017, 019, 022 | G16: Backend / agent logic | H16: 46238
A17: 4 | B17: Clean the demo conversation history | C17: High | D17: Easy | E17: Delete developer data or hide the history panel in the demo environment. | F17: QC-006 | G17: Demo owner | H17: 46233
A18: 5 | B18: Remove illustrative/debug wording | C18: High | D18: Easy | E18: Remove visible debug notes from the response model. | F18: QC-039 | G18: Backend | H18: 46234
A19: 6 | B19: Standardize KPI definitions and values | C19: High | D19: Moderate | E19: Adopt one definition for exposure, Top 5, EBITDA target, COGS, and flag count. | F19: QC-007–011, 014–015 | G19: Backend / agent logic | H19: 46238
A20: 7 | B20: Close stage-critical feature gaps | C20: High | D20: Difficult | E20: Prioritize formula explanations, guided story, baseline reset, and Bahasa Indonesia before cosmetic features. | F20: QC-049, 050, 058, 059 | G20: Backend + frontend | H20: 46238
A21: 8 | B21: Complete critical manual tests | C21: High | D21: Moderate | E21: Fix failed/partial tests, then run the entire checklist twice on the final build. | F21: QC-045; MT-001,002,010,014,015,018 | G21: Demo owner + Tech | H21: 46245
A22: 9 | B22: Enable cross-agent handoffs | C22: Medium | D22: Difficult | E22: Connect Collection–Treasury and fix Decimal serialization in chat handoffs. | F22: QC-047; MT-018 | G22: Backend / agent logic | H22: 46242
A23: 10 | B23: Deduplicate alerts and actions | C23: Medium | D23: Difficult | E23: Add clustering/deduplication and show eight unique stories instead of 47 repetitions. | F23: QC-021, QC-023 | G23: Backend / agent logic | H23: 46240
A24: 11 | B24: Add chart periods and drivers | C24: Medium | D24: Moderate | E24: Include period in payloads/labels and add drivers that explain the cash trough. | F24: QC-035, QC-037 | G24: Frontend + backend | H24: 46245
A25: 12 | B25: Enable entity/period/category filters | C25: Medium | D25: Difficult | E25: Implement filtering end-to-end after the shared dataset is stable. | F25: QC-043 | G25: Full stack | H25: 46245
... A27: 14 | B27: Rehearse at the event resolution | C27: Medium | D27: Easy | E27: Run the four-minute story twice after every High-priority item is complete. | F27: MT-031 | G27: Demo owner | H27: 46247
A30: FINDINGS PORTFOLIO SUMMARY
A31: Priority | B31: Count | D31: Difficulty | E31: Count | G31: CLASSIFICATION RULES
A32: High | B32: =COUNTIF($I$40:$I$101,A32) | D32: Easy | E32: =COUNTIF($J$40:$J$101,D32) | G32: High = open Critical/High demo blocker. Medium = Medium blocker or High non-blocker. Low = all others. Difficulty is estimated from data/architecture scope, cross-component dependencies, and change type.
A33: Medium | B33: =COUNTIF($I$40:$I$101,A33) | D33: Moderate | E33: =COUNTIF($J$40:$J$101,D33)
A34: Low | B34: =COUNTIF($I$40:$I$101,A34) | D34: Difficult | E34: =COUNTIF($J$40:$J$101,D34)
A37: COMPLETE BACKLOG — 62 FINDINGS SORTED BY PRIORITY
A39: ID | B39: Agent | C39: Finding | D39: Severity | E39: Blocker | F39: Status | G39: Owner | H39: Target | I39: Priority | J39: Difficulty | K39: Fix status 30 Jul 2026
A40: QC-004 | B40: Treasury | C40: Deferral action moves headroom the wrong way | D40: Critical | E40: Yes | F40: Open | G40: Backend / agent logic | H40: 46234 | I40: High | J40: Easy
A41: QC-006 | B41: All | C41: Conversation history is full of developer test messages | D41: Critical | E41: Yes | F41: Open | G41: Demo owner | H41: 46234 | I41: High | J41: Easy
A42: QC-007 | B42: Collection | C42: High-risk KPI and the risk tier chart disagree on the same screen | D42: High | E42: Yes | F42: Fixed - awaiting retest | G42: Backend / agent logic | H42: 46238 | I42: High | J42: Easy | K42: Fixed 30 Jul 2026 (commit 53daa2c). The card showed high_risk_provision (2,500) under a label reading 'exposure'. It now shows the High tier exposure (5,000), which equals the chart bar, with the provision moved to the caption.
A43: QC-014 | B43: Leakage | C43: Flag count on the KPI does not match the tables | D43: High | E43: Yes | F43: Fixed - awaiting retest | G43: Backend / agent logic | H43: 46238 | I43: High | J43: Easy | K43: Fixed 30 Jul 2026 (commit 53daa2c). The KPI now reads summary.items_flagged (10). The 22 came from len(anomalies), which is LIMIT 30 and includes rows that are not flagged.
A44: QC-021 | B44: All | C44: 47 action cards with heavy duplication | D44: High | E44: Yes | F44: Open | G44: Backend / agent logic | H44: 46238 | I44: High | J44: Easy
A45: QC-005 | B45: Treasury | C45: Action mixes headroom with closing cash in one before-and-after | D45: Critical | E45: Yes | F45: Open | G45: Backend / agent logic | H45: 46234 | I45: High | J45: Medium
A46: QC-008 | B46: Collection | C46: Top 5' is defined three different ways inside one agent | D46: High | E46: Yes | F46: Open | G46: Backend / agent logic | H46: 46238 | I46: High | J46: Medium
A47: QC-009 | B47: Finance | C47: Two different EBITDA margin targets are in use | D47: High | E47: Yes | F47: Fixed - awaiting retest | G47: Backend / agent logic | H47: 46238 | I47: High | J47: Medium | K47: Fixed 30 Jul 2026 (commit f448e66). The target now comes from the budget row (7,200 / 46,000 = 15.65%) and is threaded through the card caption, gauge label, simulator baseline and the recalculate endpoint. NOTE: formula check #18 expects 9.2/15 = 0.6133; with one target it becomes 9.2/15.65 = 0.586, so that check needs updating.
A48: QC-010 | B48: Finance | C48: Price variance is roughly ten times too small for the stated price decline | D48: High | E48: Yes | F48: Open | G48: Backend / agent logic | H48: 46238 | I48: High | J48: Medium
A49: QC-011 | B49: Finance | C49: COGS variance is stated as two different numbers | D49: High | E49: Yes | F49: Open | G49: Backend / agent logic | H49: 46238 | I49: High | J49: Medium
A50: QC-015 | B50: Leakage | C50: Split-invoice exposure sits in the chart but outside the total | D50: High | E50: Yes | F50: In progress | G50: Backend / agent logic | H50: 46238 | I50: High | J50: Medium | K50: Partly fixed 30 Jul 2026 (commit 53daa2c). The dashboard no longer contradicts itself: rows with is_direct_loss = false are out of the category bar and mix donut, so both sum to 7,845, and the 1,950 is named in the chart note. The alert wording has NOT been checked yet.
A51: QC-016 | B51: Collection | C51: Action impact does not match its own recommendation | D51: High | E51: Yes | F51: Open | G51: Backend / agent logic | H51: 46238 | I51: High | J51: Medium
A52: QC-017 | B52: Treasury | C52: Combined action shows only part of its own effect | D52: High | E52: Yes | F52: Open | G52: Backend / agent logic | H52: 46238 | I52: High | J52: Medium
A53: QC-019 | B53: Treasury | C53: Credit line action is anchored to the wrong week | D53: High | E53: Yes | F53: Open | G53: Backend / agent logic | H53: 46238 | I53: High | J53: Medium
A54: QC-022 | B54: All | C54: Action impacts stack with no double-count guard | D54: High | E54: Yes | F54: Open | G54: Backend / agent logic | H54: 46238 | I54: High | J54: Medium
A55: QC-045 | B55: All | C55: Interactive behaviour could not be verified remotely | D55: High | E55: Yes | F55: Open | G55: Demo owner | H55: 46238 | I55: High | J55: Medium
A56: QC-001 | B56: Leakage | C56: Leakage category chart returns all zeros | D56: Critical | E56: Yes | F56: Fixed - awaiting retest | G56: Backend / data | H56: 46234 | I56: High | J56: Difficult | K56: Fixed 30 Jul 2026 (branch bug-fix-trial, commit 53daa2c). category_breakdowns.amount_at_risk_idr_mn was probed as amount_idr_mn, so _row_get returned None and every value became 0.0 with no error. Verified on live DB batch 17: bars 3,800 / 3,050 / 900 / 95 sum to 7,845 = the Flagged this cycle card.
A57: QC-002 | B57: All | C57: The four agents run on four unrelated data batches | D57: Critical | E57: Yes | F57: Open | G57: Backend / data | H57: 46234 | I57: High | J57: Difficult
A58: QC-003 | B58: Finance + Collection | C58: Collection revenue base is about 15 times the Finance revenue | D58: Critical | E58: Yes | F58: Open | G58: Backend / data | H58: 46234 | I58: High | J58: Difficult
A59: QC-020 | B59: All | C59: Agent keys are inconsistent between endpoints | D59: High | E59: Yes | F59: Open | G59: Backend | H59: 46238 | I59: High | J59: Difficult
A60: QC-024 | B60: Leakage | C60: The Leakage agent opens on an empty chart | D60: High | E60: Yes | F60: Fixed - awaiting retest | G60: Backend / data | H60: 46238 | I60: High | J60: Difficult | K60: Fixed 30 Jul 2026 (commit 53daa2c). Same root cause as QC-001; the default view 'categories' now renders four bars on open.
A61: QC-043 | B61: All | C61: The app has no filters at all | D61: High | E61: Yes | F61: Open | G61: Backend + frontend | H61: 46238 | I61: High | J61: Difficult
A62: QC-044 | B62: All | C62: Dataset is far below the volume the client asked for | D62: High | E62: Yes | F62: Open | G62: Backend / data | H62: 46238 | I62: High | J62: Difficult
A63: QC-047 | B63: Collection + Treasury | C63: Treasury collection lever is not linked to the Collection book | D63: High | E63: Yes | F63: Open | G63: Backend / agent logic | H63: 46238 | I63: High | J63: Difficult
A64: QC-049 | B64: All | C64: No formula explanation panel anywhere in the app | D64: Critical | E64: Yes | F64: Open | G64: Backend + frontend | H64: 46238 | I64: High | J64: Difficult
A65: QC-050 | B65: All | C65: No guided story mode | D65: Critical | E65: Yes | F65: Open | G65: Frontend | H65: 46238 | I65: High | J65: Difficult
A66: QC-051 | B66: All | C66: Simulator cannot save, load or compare a scenario | D66: High | E66: Yes | F66: Open | G66: Backend + frontend | H66: 46242 | I66: High | J66: Difficult
A67: QC-052 | B67: All | C67: Simulator has no presets | D67: High | E67: Yes | F67: Open | G67: Backend + frontend | H67: 46242 | I67: High | J67: Difficult
A68: QC-054 | B68: All | C68: KPI tiles have no trend sparkline | D68: High | E68: Yes | F68: Open | G68: Backend + frontend | H68: 46242 | I68: High | J68: Difficult
A69: QC-055 | B69: All | C69: Actions carry no confidence level | D69: High | E69: Yes | F69: Open | G69: Backend | H69: 46242 | I69: High | J69: Difficult
A70: QC-056 | B70: All | C70: No visible cascade when an action executes | D70: High | E70: Yes | F70: Open | G70: Frontend | H70: 46242 | I70: High | J70: Difficult
A71: QC-057 | B71: All | C71: No status notification feed | D71: High | E71: Yes | F71: Open | G71: Backend + frontend | H71: 46245 | I71: High | J71: Difficult
A72: QC-058 | B72: All | C72: No Bahasa Indonesia toggle | D72: High | E72: Yes | F72: Open | G72: Backend + frontend | H72: 46242 | I72: High | J72: Difficult
... A76: QC-025 | B76: Treasury | C76: FX action states exposure falls to the hedge amount | D76: High | E76: No | F76: Open | G76: Backend / agent logic | H76: 46238 | I76: Medium | J76: Easy
A77: QC-039 | B77: All | C77: The word 'illustrative' is exposed in the payload | D77: Medium | E77: Yes | F77: Fixed - awaiting retest | G77: Backend | H77: 46245 | I77: Medium | J77: Easy | K77: Fixed 30 Jul 2026 (commit f448e66). Removed the 'illustrative' flags, the db_kpis_count / db_profit_count / db_variance_count debug counters, and reworded the debug-flavoured notes. A test now fails if any of them come back.
A78: QC-040 | B78: Treasury | C78: It is unclear whether the customer delay is already in the forecast | D78: Medium | E78: Yes | F78: Open | G78: Backend / agent logic | H78: 46245 | I78: Medium | J78: Easy
A79: QC-023 | B79: All | C79: 47 alerts telling roughly eight distinct stories | D79: High | E79: No | F79: Open | G79: Backend / agent logic | H79: 46238 | I79: Medium | J79: Medium
A80: QC-042 | B80: All | C80: Starter prompts do not show the strongest part of the story | D80: Medium | E80: Yes | F80: Open | G80: Demo owner | H80: 46245 | I80: Medium | J80: Medium
A81: QC-035 | B81: All | C81: No chart states its period | D81: Medium | E81: Yes | F81: Open | G81: Frontend + backend | H81: 46245 | I81: Medium | J81: Difficult
A82: QC-037 | B82: Treasury | C82: The cash chart cannot answer why Week 5 is low | D82: Medium | E82: Yes | F82: Open | G82: Backend + frontend | H82: 46245 | I82: Medium | J82: Difficult
A83: QC-053 | B83: All | C83: Simulator has no scope selector | D83: High | E83: No | F83: Open | G83: Backend + frontend | H83: 46245 | I83: Medium | J83: Difficult
A84: QC-013 | B84: Leakage | C84: The bar labelled 'Current 95%' does not show the current position | D84: Medium | E84: No | F84: Fixed - awaiting retest | G84: Backend / agent logic | H84: 46245 | I84: Low | J84: Easy | K84: Fixed 30 Jul 2026 (commit 53daa2c). The bar is now labelled 'Current 95/90%' and reuses the Total protected card value (7,557.5) instead of recomputing it at 95/95 (7,577.5).
A85: QC-027 | B85: Finance | C85: One margin percentage rounds down where others round normally | D85: Medium | E85: No | F85: Fixed - awaiting retest | G85: Frontend | H85: 46245 | I85: Low | J85: Easy | K85: Fixed 30 Jul 2026 (commit f448e66). Python and IEEE round half to even, so round(36.25, 1) is 36.2. Added _round_half_up and routed _fmt and _pct through it. Product GM% is now 23.8 / 36.3 / 16.7.
A86: QC-029 | B86: Treasury | C86: Inconsistent number formats in one KPI row | D86: Medium | E86: No | F86: Fixed - awaiting retest | G86: Frontend | H86: 46245 | I86: Low | J86: Easy | K86: Fixed 30 Jul 2026 (commit f448e66). One USD scale across the KPI row: 3.3 M USD beside 2.0 M USD, instead of 3.3 M USD beside 2,000,000 USD which hid that 2.0 is less than 3.3.
A87: QC-030 | B87: Collection | C87: Action labels a two-customer balance as total overdue AR | D87: Medium | E87: No | F87: Open | G87: Backend / agent logic | H87: 46245 | I87: Low | J87: Easy
A88: QC-031 | B88: Leakage | C88: Action uses the annualised figure while the dashboard shows the cycle figure | D88: Medium | E88: No | F88: Open | G88: Backend / agent logic | H88: 46245 | I88: Low | J88: Easy
A89: QC-032 | B89: Leakage | C89: The same 900 mn appears under three different names | D89: Medium | E89: No | F89: Open | G89: Backend / agent logic | H89: 46245 | I89: Low | J89: Easy
A90: QC-041 | B90: Treasury | C90: Alert title names Week 5 but carries Week 6 data | D90: Medium | E90: No | F90: Open | G90: Backend / agent logic | H90: 46245 | I90: Low | J90: Easy
A91: QC-026 | B91: Collection | C91: Recovery rate ignores how old the debt is | D91: Medium | E91: No | F91: Open | G91: Backend / agent logic | H91: 46245 | I91: Low | J91: Medium
A92: QC-028 | B92: Collection | C92: DSO gauge shows 120% progress on a metric where lower is better | D92: Medium | E92: No | F92: Fixed - awaiting retest | G92: Frontend | H92: 46245 | I92: Low | J92: Medium | K92: Fixed 30 Jul 2026 (commit f448e66). Added a lower_is_better flag so enrichment inverts the ratio. DSO progress is now 0.8246 (47/57) instead of the clamped 1.2.
A93: QC-034 | B93: Treasury | C93: A zero bar next to a value bar reads as a rendering failure | D93: Medium | E93: No | F93: Fixed - awaiting retest | G93: Frontend | H93: 46245 | I93: Low | J93: Medium | K93: Fixed 30 Jul 2026 (commit f448e66). The zero 'Base' bar is gone. The chart now compares Do nothing 1,777.05 against Hedge 2.0M 700.05 - both non-zero, and the first equals the FX loss card.
A94: QC-036 | B94: Finance | C94: The side chart duplicates the main chart exactly | D94: Medium | E94: No | F94: Fixed - awaiting retest | G94: Frontend | H94: 46245 | I94: Low | J94: Medium | K94: Fixed 30 Jul 2026 (commit f448e66). Finance side:top was byte-identical to view:product. It now shows the gross margin pool in IDR (4,550 / 4,930 / 2,300 = 11,780) rather than repeating the rate.
A95: QC-038 | B95: Collection | C95: Worklist bucket column attributes a whole balance to the oldest bucket | D95: Low | E95: No | F95: Open | G95: Frontend | H95: 46252 | I95: Low | J95: Medium
A96: QC-046 | B96: Leakage | C96: Vendor risk score ignores amount and severity | D96: Medium | E96: No | F96: Fixed - awaiting retest | G96: Backend / agent logic | H96: 46245 | I96: Low | J96: Medium | K96: Fixed 30 Jul 2026 (commit f448e66). Score = 50% at-risk amount + 35% worst severity + 15% flag count, relative to the worst vendor in the batch. Live batch 17: Osaka 100, Shenzhen 64, Bahan Baku 56, Taipei 33.
A97: QC-033 | B97: Collection | C97: Two charts on the same screen order the same pair in opposite directions | D97: Medium | E97: No | F97: Fixed - awaiting retest | G97: Frontend | H97: 46245 | I97: Low | J97: Difficult | K97: Fixed 30 Jul 2026 (commit f448e66). Both charts now order [Now, Target]. Aligning them turned the pair into exact duplicates, so side:bottom was changed to Overdue vs expected recovery.
A98: QC-048 | B98: All | C98: The mockup and the deployed app disagree on the numbers | D98: Medium | E98: No | F98: Open | G98: Demo owner + Backend | H98: 46245 | I98: Low | J98: Difficult
A99: QC-060 | B99: All | C99: No exact-parameter calculation flow | D99: Medium | E99: No | F99: Open | G99: Backend + frontend | H99: 46245 | I99: Low | J99: Difficult
A100: QC-061 | B100: All | C100: Next best action cards are not on the dashboard | D100: Medium | E100: No | F100: Open | G100: Frontend | H100: 46245 | I100: Low | J100: Difficult
A101: QC-062 | B101: All | C101: Chat cannot be verified to render charts and tables | D101: Medium | E101: No | F101: Open | G101: Demo owner | H101: 46238 | I101: Low | J101: Difficult
A104: MANUAL TESTS NOT YET PASSED / COMPLETED
A106: ID | B106: Area | C106: Agent | D106: Test | E106: Test priority | F106: Result | G106: Defect ID | H106: Notes | I106: Priority | J106: Difficulty
A107: MT-001 | B107: Navigation | C107: All | D107: Agent switcher | E107: Critical | F107: Partial | H107: Some charts are still blank, especially in Leakage. | I107: High | J107: Easy
A108: MT-002 | B108: Navigation | C108: All | D108: View tabs | E108: Critical | F108: Partial | H108: Some charts are still blank, especially in Leakage. | I108: High | J108: Easy
A109: MT-004 | B109: Buttons | C109: All | D109: KPI tile click | E109: High | F109: Not run | I109: Medium | J109: Easy
A110: MT-005 | B110: Buttons | C110: All | D110: Explain this KPI | E110: High | F110: Not run | I110: Medium | J110: Easy
A111: MT-010 | B111: Simulator | C111: Collection | D111: Maximum boundary | E111: High | F111: Failed | H111: Observed DSO at 53.5. | I111: High | J111: Easy
A112: MT-014 | B112: Actions | C112: All | D112: Approve | E112: Critical | F112: Partial | H112: The action cannot yet be cancelled. | I112: High | J112: Medium
A113: MT-015 | B113: Actions | C113: All | D113: Simulate | E113: Critical | F113: Partial | H113: Agent Action has not yet affected Action History. | I113: High | J113: Medium
A114: MT-016 | B114: Actions | C114: All | D114: Routing | E114: Critical | F114: Not run | H114: Not attempted yet. | I114: High | J114: Medium
A115: MT-018 | B115: Chat | C115: All | D115: Cross-agent handoff | E115: Critical | F115: Failed | H115: Muncul error "Object of type Decimal is not JSON serializable" | I115: High | J115: Medium
A116: MT-023 | B116: Chat | C116: All | D116: Response speed | E116: High | F116: Blocked | H116: Response is still slow. | I116: High | J116: Medium
A117: MT-025 | B117: Data | C117: All | D117: Export | E117: Medium | F117: Not run | H117: Export and download features are not available yet. | I117: Medium | J117: Easy
A118: MT-030 | B118: Stability | C118: All | D118: Rapid clicking | E118: High | F118: Partial | H118: Loading delays remain. | I118: Medium | J118: Medium
...
