Workbook

Sheet 00 Read Me First
B1: FINANCIAL PERFORMANCE ANALYSIS AGENT - DEMO DATA ENGINE
B2: A working profit model behind the storyline. Same illustrative company as your other agents, so the whole suite tells one Future Finance AI story.
B4: WHAT THIS WORKBOOK IS
B5: It answers the CFO's hardest monthly question: revenue held up, so why did profit fall, and what do we do.
B6: The 'STORYLINE FINPERF 01' sheet is the demo script. The numbered sheets are the model behind it.
B8: SHEET MAP
B9: 01 Assumptions - inputs (BLUE): target margin, imported-cost share, elasticity note.
B10: 02 P&L Actual vs Budget - sales and margin by product, down to EBITDA.
B11: 03 Variance Bridge - splits the EBITDA change into volume, mix, price, cost, and opex.
B12: 04 KPIs & Ratios - the headline numbers and per-product margins.
B13: 05 What-if Simulator - change levers, watch EBITDA move, compare to target.
B14: 06 Recommendation - the three moves, the impact, the decision card.
... B43: BLUE = input you can change. GREEN = pulled from another sheet. BLACK = calculated. YELLOW = key number.

Sheet Summary Future Finance AI
A3: AGENT AI
A4: AGENT 01 | B4: Agent 1, Financial Performance. Why did profit fall. It explains it in one chart and tests the fix
A5: AGENT 02 | B5: Agent 2, Cash Flow. Will I have enough cash. It finds a shortfall four weeks early and fixes it.
A6: AGENT 03 | B6: Agent 3, Collections. Why is my cash stuck. It finds the overdue cash and who to chase first
A7: AGENT 04 | B7: Agent 4, Leakage and Fraud. Is money leaking out. It blocks a fraud and finds duplicate payments
A9: AGENT AI DRIVER
A10: OPENING | B10: Most finance teams are busy, but they are always one step behind. They find cash problems too late. They chase the wrong customers first. Money leaks out in small ways. And when profit falls, it takes days to find out why. Now imagine a small AI finance team that works for you all day and night. It watches your numbers. It explains why things happen. It tests a fix before you act. Then it acts. But it never does anything without your approval. That is what I will show you today. We built four of these agents inside your Dynamics 365 Finance system. They share the same data, and they work together. To keep it real, we use one example company. An Indonesian manufacturer that imports raw materials in US dollars. Everything you see uses the same company, so the four agents tell one connected story. And all the numbers today are illustrative, just to show how it works.
A11: AGENT 01 | B11: First question. My revenue is on plan, so why did my profit fall. 1. Look. Revenue is on target. But profit, the EBITDA, dropped from about 16 percent to about 9 percent. 2. Most tools stop at the number. This agent explains why, in one chart. 3. Selling more helped. But two things hurt. Input cost went up, mostly from the weaker rupiah on imported materials. And the product mix shifted to lower-margin products. So this is a margin problem, not a sales problem. 4. Then it lets you test a fix. If we raise price 4 percent, profit improves, but not enough. So the agent recommends three moves together. Raise price where the market allows. Sell more of the high-margin products. And hedge the currency, which it hands to the cash flow agent.
A12: AGENT 02 | B12: Second question. Will I have enough cash. 1. This agent builds a 14-week cash forecast from your live data. Look here. It found a problem in Week 5, four weeks early. Cash drops below your safety buffer. 2. Why. Two reasons. A large US dollar payment for imported materials lands that week. And your biggest customer pays late. 3. The agent does not just warn you. It recommends a fix. Move one flexible payment to a later week. Pull one customer payment earlier. That closes the gap. 4. It also handles the currency risk. It suggests locking the US dollar rate with a forward, so a weaker rupiah does not hurt you. 5. And here is the key part. It asks for your approval before doing anything. Transition: Good. Cash is safe. But some of your cash is stuck. Let us see where.
A13: AGENT 03 | B13: Third question. Why is my cash stuck, and who is risky. 1. This agent looks at everyone who owes you money. It found IDR 38 billion overdue. 2. Then it does something useful. It ranks who to chase first. The top five customers hold about 70 percent of the overdue cash. So your team stops guessing, and starts with the ones that matter. 3. It also scores each customer for risk. This one customer is high risk. It has a dispute, and it is sliding toward default. The agent says hold new shipments, and set aside a provision. 4. And here is the prize for you. If we cut the collection time from 57 days to 47 days, we free about IDR 20 billion in cash. Transition: So we found stuck cash. Now, is money leaking out the back door.
A14: AGENT 04 | B14: Fourth question. Is money leaving by mistake, or by fraud. 1. This agent scans every vendor payment. This cycle it scanned 1,850 invoices, and flagged only 10. A short, focused list. 2. Look at the top one. A vendor bank account changed two days before a payment of IDR 3.8 billion. That is a classic fraud pattern. The agent blocked it before the money left, and asked the team to verify by phone. 3. It also found IDR 3 billion in duplicate payments already made, ready to claw back. And smaller leaks, like missed early-payment discounts. 4. In total, IDR 7.8 billion of risk caught this cycle. Most of it before it left the building. Transition: Cash is safe, unstuck, and protected. Last question, the one that keeps a CFO awake.
A15: CONNECTIONS | B15: Now here is the real power. These are not four separate tools. They share one set of data, and they hand work to each other. The performance agent found a currency problem, and handed it to the treasury agent. The treasury agent already knew your customer was paying late, because the collections agent flagged it. The leakage agent feeds cost savings back into performance. Together, they are one finance brain. It watches, it explains, and it acts.
A16: CLOSING | B16: Three things make this different from a generic AI tool. First, you are always in control. Every agent asks for approval before it acts, and it logs everything for audit. It is not a black box. Second, it is built inside your Dynamics 365 Finance system, using Microsoft Copilot Studio. It reads and writes your real data. No copy and paste, no separate app. Third, it is tuned to your world. Local tax rules, local accounting standards, your currency. So instead of a finance team that reacts in days, you get a finance team that responds in minutes, and never sleeps. And you decide every action. Thank you. What questions can I answer.
A17: NEED TO BE HIGHLIGHTED | B17: ● If they ask: "Is it safe. Can it act on its own." >> No agent acts without your approval. Every action is logged for audit. You set what it can and cannot do. ● If they ask: "Are these real numbers." >> These are illustrative, to show how it works. In a pilot, we connect your real data. ● If they ask: "How accurate is the AI." >> The heavy math, like the cash forecast and the profit bridge, is normal finance logic, not a guess. The AI helps read data, explain it, and set priorities. And a human approves every action. ● If they ask: "What does it cost. What license do we need." >> That depends on Microsoft's licensing at the time. I will confirm the exact terms for you. (Do not quote a price.) ● If they ask: "How long does it take to build." >> We start with one agent as a pilot on your data, then add more. I can propose a plan. ● If they ask: "Does it work on our version of D365." >> I will confirm the features available on your exact release.

Sheet STORYLINE FINPERF
B1: FINANCIAL PERFORMANCE ANALYSIS AGENT
B2: Demo storyline for a CFO / Finance audience. Company: PT Future Manufacturing Tbk (illustrative). Same company as the other agents, so they tell one connected story.
B4: THE BUSINESS PROBLEM
B5: Setup | C5: PT Future Manufacturing's revenue came in on plan for August, but EBITDA margin dropped from about 16% to about 9%. The finance team can see the fall, but it takes them days in spreadsheets to explain why. The CFO wants the cause and the fix, fast.
B7: THE AGENT LOOP (7 STEPS)
B8: 1. TRIGGER | C8: Runs at month-end close, on demand, or when a KPI breaches a limit (for example EBITDA margin falls more than 2 points below budget).
B9: 2. PERCEIVE | C9: Reads the general ledger, sales by product, the budget, and standard vs actual costs from D365 Finance.
B10: 3. REASON | C10: Builds Actual vs Budget, then splits the margin change into volume, mix, price, and cost. Computes the KPIs and ranks the drivers by size.
B11: 4. RECOMMEND | C11: Explains the cause in one chart, then proposes actions on price, mix, and cost, each with a number, plus what-if scenarios.
B12: 5. APPROVE | C12: Human in the loop. The CFO and Commercial lead approve the price and mix actions. Dual control.
B13: 6. EXECUTE | C13: Updates price lists or quotes in D365, creates tasks, hands the FX piece to the Treasury agent, and logs everything for audit.
B14: 7. LEARN | C14: Tracks which actions recovered margin and tunes the assumptions, including how volume reacts to price.
B16: WOW MOMENTS (tie each to a sheet)
B17: Explained the why in one chart | C17: Revenue on plan, but EBITDA margin fell about 6 points. The bridge shows exactly why. Point to sheet 03.
B18: Named the culprits | C18: Input cost inflation on imported materials and a shift to low-margin products, not weak demand. Point to sheet 03.
B19: Tested the fix live | C19: A 4% price pass-through recovers part of the margin, and the FX piece goes to the Treasury agent. Point to sheet 05.
B20: Governance, not a black box | C20: Human approval plus a full audit trail. Point to the decision card on sheet 06.
C23: Part 1. The story, step by step (what is happening) - The AI sends the CFO an alert. Profit fell. It asks if he wants to know why. - The CFO pushes back hard. He asks if this is the final close or a guess, and tells the AI to prove its claims and break them down by product. - The AI shows the answer with charts. It explains the profit drop with a bridge, then shows margin by product. - The CFO keeps challenging. He asks which currency rate was used and how much material is bought in dollars. - The AI gives three fixes, each with a confidence level, and runs a simulation. - The CFO deep dives. He asks for the bad case, including losing some sales volume. - The CFO approves a final action. It flows to the Treasury agent, updates the price list in D365, tells the Collections agent, and logs everything. Each step still needs a human to approve. That is the whole loop. Watch, explain, simulate, then act with the human in control.
C25: Part 2. The core finance terms (the numbers in the charts) - Revenue (pendapatan). Total sales. In the mockup, budget was 46,000 and actual was 46,510 IDR million (so about IDR 46 billion). "On plan" matched the budget. - COGS, cost of goods sold (harga pokok penjualan, HPP). The direct cost to make the products sold. Budget 31,800, actual 34,730. - Gross margin (laba kotor / marjin kotor). Revenue minus COGS. Budget 14,200, actual 11,780. Gross margin % is that divided by revenue: 30.9% fell to 25.3%. - EBITDA. Profit before interest, tax, depreciation, and amortization (laba sebelum bunga, pajak, dan penyusutan). A simple picture of operating cash profit. Budget 7,200, actual 4,300. - EBITDA margin (marjin EBITDA). EBITDA divided by revenue. It fell from 15.7% to 9.2%, against a 15% target. This is the headline the CFO reacts to. [High confidence on all these definitions] - Budget vs Actual, and variance (anggaran vs aktual, selisih). - Opex, operating expenses (biaya operasional). Costs to run the business that are not COGS, like payroll and freight. Budget 7,000, actual 7,480.
C27: Part 3. The bridge and its four drivers (the hardest part) The bridge (jembatan varians) splits the profit drop into causes that add up exactly. From 7,200 down to 4,300. - Volume effect (efek volume): +1,341. You sold more total units. That helped. - Mix effect (efek mix produk): −1,491. You sold a different blend. More cheap-margin product, less rich-margin product. Even at the same prices, the average margin drops. This hurt. - Price effect (efek harga): −390. You sold at slightly lower prices than planned. - Cost effect (efek biaya): −1,880. Unit costs went up, mostly from the weaker rupiah on imported materials. The biggest single cause. Messages : "Selling more helped us. But a shift to low-margin products and higher input costs hurt us more." Why mix is separate from cost, since the CFO challenged this: mix holds price and cost fixed and only changes the product blend. Cost holds the blend fixed and only changes the unit cost. They are calculated on different things, so there is no double counting. [High confidence] Product margins in the mockup: Industrial 23.8%, Precision 36.3% (the best), Standard 16.7% (the worst). The best line lost 15% of its volume and the worst line grew. That is the mix problem in one sentence. Blended margin (marjin gabungan) means one average margin across all products. The CFO said do not give me a blended margin, because an average can hide that one product is bleeding.
C29: Part 4. The currency and hedging terms - FX, foreign exchange (nilai tukar / valas). Here it is USD/IDR, how many rupiah for one US dollar, about 17,950 in the mockup. - Imported material share of COGS (porsi bahan impor). About 55% of product cost is bought in dollars. So when the rupiah weakens, cost rises. - Hedge, forward-cover (lindung nilai / kontrak forward). A deal with the bank to lock a future exchange rate now. It removes the risk that the rupiah gets worse. The mockup hands a "forward-cover USD 2.0M" to the Treasury agent. [High confidence on the concept] - Price pass-through (meneruskan kenaikan biaya ke harga jual). Raising your selling price to cover a cost increase.
C31: Part 5. The simulation terms - Simulation, what-if, scenario (simulasi, skenario). Testing "what happens to profit if we change one thing." - The scenarios shown: price +4% gives 12.7%, price +4% with FX +3% gives 11.6%, price +4% with a hedge holds 12.7%. None reach the 15% target alone. - Deep dive downside: price +4% but losing 3% of volume gives 11.1%. Price +6% gives 13.7% if volume holds. - Price elasticity (elastisitas harga). How much volume you lose when you raise price. This is the weak spot. The model does not know it, so the CFO tests it with the volume lever. [Low confidence on any elasticity number] This needs verification with the client's real data. - Confidence levels. The AI marks each claim High, Medium, or Low, the same way I do with you. It shows the AI is honest about what it knows.
C33: Part 6. The action and cascade terms - Human-in-the-loop, dual control (persetujuan manusia, kontrol ganda). Nothing happens automatically. A person must approve. Two owners approve sensitive actions. - Sales price agreement, or price list, in D365 (perjanjian harga jual di D365). Where selling prices are stored in the ERP. The AI drafts the change and waits for the Controller. - ERP (sistem inti perusahaan). Here it is Dynamics 365 Finance and Operations, the system of record. - Audit trail (jejak audit). A full log of who did what, when, and why. Important for trust and compliance. - The cascade means one CFO decision flows to other agents (Treasury, Collections) and to the ERP, each with its own approval.

Sheet 00 Mock Up
A1: #VALUE! | C1: Part 1. The alert : - What happens: The AI messages the CFO first, without being asked. Profit fell, and it offers to explain. - Terms: Proactive alert (peringatan otomatis). EBITDA margin (marjin EBITDA), operating profit as a percent of revenue. It dropped to 9.2% against a 15% target. - HIghlight "the agent did not wait to be asked." Part 2. CFO first challenge - What happens: The CFO does not trust it yet. He asks if this is the final close or a guess. - Terms: Month-end close (tutup buku bulanan), the finalized accounts for the month. Estimate vs actual (estimasi vs aktual). - HIghlight: Shows the agent uses real posted data, not a guess.
A3: #VALUE! | C3: Part 3. AI shows the EBITDA bridge - What happens: The AI answers with a chart that walks from budget profit to actual profit. - Terms: Variance bridge (jembatan varians), a step chart of causes. Budget vs actual (anggaran vs aktual). - HIghlight: Point to the chart and say "here is exactly why, in one picture." Part 4. CFO challenges the mix - What happens: The CFO says prove the mix effect is not the cost counted twice, and break it by product. - Terms: Mix effect (efek mix produk). Blended margin (margin gabungan), one average across products, which can hide problems. - Highlight : A sharp CFO hates averages. This challenge makes demo feel real.
A5: #VALUE! | C5: Part 5. AI breaks it down by product - What happens: The AI shows margin per product and explains mix is separate from cost. - Terms: Gross margin percent (margin kotor %) per product. Volume (volume), units sold. - Why it works: Mix holds price and cost fixed and only changes the blend. Cost holds the blend fixed and only changes unit cost. Different bases, so no double count. Part 6. CFO asks about currency - What happens: The CFO asks which exchange rate was used and how much material is in dollars. - Terms: FX, USD/IDR (nilai tukar). Imported material share of COGS (porsi bahan impor dalam HPP), here about 55%. - Highlights : This links to Treasury agent later >> "the cost driver is currency." Part 7. AI answers on the rate - What happens: The AI says the bridge used actual settled rates, and any forward view uses a rate the CFO controls. - Terms: Settled rate (kurs realisasi), the rate actually paid. Spot rate (kurs spot), today's rate, about 17,950. - Note: The AI marks the forward rate [Medium confidence] and says it needs verification to gain and builds trust from CFO
A7: #VALUE! | C7: Part 8. CFO asks for options - What happens: The CFO wants choices, but warns he will not blindly raise prices. - Highlight : This sets up the recommendation. It shows the CFO, not the AI, is in charge. Part 9. AI recommendation, three moves - What happens: The AI gives three fixes, each with a confidence level. - Terms: Price pass-through. Hedge (melindungi nilai). Product mix steering (mengarahkan mix penjualan). - HIghlight : Read the confidence badges out loud. It shows responsible AI. Part 10. AI simulation - What happens: The AI runs a what-if and shows which scenarios recover margin. - Terms: Simulation, what-if, scenario (simulasi, skenario). Target line (garis target) at 15%. - Key point: No single move reaches 15% alone >> "price helps, but it is not enough by itself."
A9: #VALUE! | C9: Part 11. CFO deep dive - What happens: The CFO asks for the bad case, a 3% volume loss, and a 6% price option. - Terms: Price elasticity (elastisitas harga), how much volume you lose when price rises. This is the weak spot. - Highlight : CFO always asks for the downside. Do not hide it. Part 12. AI deep-dive chart - What happens: The AI shows the downside scenarios against the target. - Note: Even losing 3% volume, a 4% price rise still beats today. [Medium confidence] Elasticity needs verification. Part 13. CFO asks to calculate first - What happens: Before approving, the CFO asks for the exact math with his own parameters. Price +4% on two lines only, 2% volume loss, hedge USD 2.0M. Numbers, not a chart. - Terms: Parameters , the exact inputs the CFO sets. On-demand calculation (perhitungan sesuai permintaan). - Why it matters: CFO confirms the precise figures before signing.
A11: #VALUE! | C11: Part 14. AI on-demand calculation - What happens: The AI returns a precise table, not a chart. EBITDA 4,300 to 5,393. Margin 9.2% to 11.4%. Plus the hedge cash cost. - Terms: Premium , the cost of the hedge, IDR 340 mn. Downside protected (kerugian yang dilindungi), about IDR 1,077 mn if the rupiah weakens 3%. - Note to explain: This 11.4% is below the earlier 12.7% on purpose. The chart raised price on all lines. Here only two lines get the rise, plus a 2% volume loss, so it lands lower. The agent says this itself, which shows it is precise. [High confidence on the arithmetic] - Highlight : "the agent recalculated with the CFO's exact numbers in seconds." That is a strong selling point. Part 15. CFO final approval - What happens: The CFO approves, now that the math is confirmed. He also asks what it touches downstream. - Terms: Human-in-the-loop, dual control (persetujuan manusia, kontrol ganda). - Highlight : This is your governance message. Nothing runs without a person.
A13: #VALUE! | C13: Part 16. AI action and cascade - What happens: The approval fans out to the Treasury agent (the hedge), D365 Finance (the price list), the Collections agent (notified), and the audit log. Each waits for its own approval. - Terms: ERP, here Dynamics 365. Sales price agreement. Audit trail. Cascade. - HIghlight : End here >> "one decision, safely connected across your agents and your ERP, with you in control."

Sheet 01 Assumptions
A1: Assumptions & Inputs - change here to run any scenario
A2: One place for the key inputs. BLUE = input. YELLOW = key assumption. Money is in IDR million. Quantity is in '000 units. Price and unit cost are in IDR '000 per unit.
A4: PERIOD & SCOPE
A5: Company (illustrative) | B5: PT Future Manufacturing Tbk
A6: Period | B6: August 2026
A7: Comparison | B7: Actual vs Budget
A9: KEY ASSUMPTIONS
A10: Target EBITDA margin (%) | B10: 0.15 | C10: The margin the CFO wants to protect. Illustrative benchmark.
A11: Imported material share of COGS (%) | B11: 0.55 | C11: Share of product cost bought in USD. Used by the what-if to model FX.
A13: NOTE ON PRICE ELASTICITY
A14: Elasticity is NOT auto-modelled | B14: use the volume lever | C14: How volume reacts to a price change is the weakest assumption in any what-if. This model does not guess it. On the simulator, move the volume lever yourself to test a price rise. This needs verification with real client data.

Sheet 02 P&L Actual vs Budget
A1: P&L - Actual vs Budget (August 2026)
A2: Sales and margin by product, then operating costs down to EBITDA. BLUE = input. Money in IDR mn. Qty in '000 units. Price and cost in IDR '000/unit. Revenue = Qty x Price.
A4: SALES & GROSS MARGIN BY PRODUCT
A5: Product | B5: BUDGET | H5: ACTUAL
B6: Qty | C6: Price | D6: Cost | E6: Revenue | F6: COGS | G6: Gross margin | H6: Qty | I6: Price | J6: Cost | K6: Revenue | L6: COGS | M6: Gross margin
A7: Industrial Components | B7: 120 | C7: 150 | D7: 105 | E7: =B7*C7 -> 18000 | F7: =B7*D7 -> 12600 | G7: =E7-F7 -> 5400 | H7: 130 | I7: 147 | J7: 112 | K7: =H7*I7 -> 19110 | L7: =H7*J7 -> 14560 | M7: =K7-L7 -> 4550
A8: Precision Assemblies | B8: 40 | C8: 400 | D8: 240 | E8: =B8*C8 -> 16000 | F8: =B8*D8 -> 9600 | G8: =E8-F8 -> 6400 | H8: 34 | I8: 400 | J8: 255 | K8: =H8*I8 -> 13600 | L8: =H8*J8 -> 8670 | M8: =K8-L8 -> 4930
A9: Standard Parts | B9: 200 | C9: 60 | D9: 48 | E9: =B9*C9 -> 12000 | F9: =B9*D9 -> 9600 | G9: =E9-F9 -> 2400 | H9: 230 | I9: 60 | J9: 50 | K9: =H9*I9 -> 13800 | L9: =H9*J9 -> 11500 | M9: =K9-L9 -> 2300
A10: TOTAL | B10: =SUM(B7:B9) -> 360 | E10: =SUM(E7:E9) -> 46000 | F10: =SUM(F7:F9) -> 31800 | G10: =SUM(G7:G9) -> 14200 | H10: =SUM(H7:H9) -> 394 | K10: =SUM(K7:K9) -> 46510 | L10: =SUM(L7:L9) -> 34730 | M10: =SUM(M7:M9) -> 11780
A12: OPERATING EXPENSES
A13: Cost line | B13: Budget | C13: Actual | D13: Var (Act-Bud)
A14: Payroll | B14: 3200 | C14: 3300 | D14: =C14-B14 -> 100
A15: Logistics & freight | B15: 1400 | C15: 1650 | D15: =C15-B15 -> 250
A16: Rent & utilities | B16: 900 | C16: 920 | D16: =C16-B16 -> 20
A17: Marketing & selling | B17: 800 | C17: 850 | D17: =C17-B17 -> 50
A18: Other opex | B18: 700 | C18: 760 | D18: =C18-B18 -> 60
A19: Total operating expenses | B19: =SUM(B14:B18) -> 7000 | C19: =SUM(C14:C18) -> 7480 | D19: =C19-B19 -> 480
A21: PROFIT SUMMARY (to EBITDA)
A22: Line | B22: Budget | C22: Actual | D22: Variance
A23: Revenue | B23: =E10 -> 46000 | C23: =K10 -> 46510 | D23: =C23-B23 -> 510
A24: COGS | B24: =F10 -> 31800 | C24: =L10 -> 34730 | D24: =C24-B24 -> 2930
A25: Gross margin | B25: =G10 -> 14200 | C25: =M10 -> 11780 | D25: =C25-B25 -> -2420
A26: Gross margin % | B26: =B25/B23 -> 0.30869565 | C26: =C25/C23 -> 0.25327886 | D26: =C26-B26 -> -0.055416787
A27: Operating expenses | B27: =B19 -> 7000 | C27: =C19 -> 7480 | D27: =C27-B27 -> 480
A28: EBITDA | B28: =B25-B27 -> 7200 | C28: =C25-C27 -> 4300 | D28: =C28-B28 -> -2900
A29: EBITDA % | B29: =B28/B23 -> 0.15652174 | C29: =C28/C23 -> 0.092453236 | D29: =C29-B29 -> -0.064068503
A31: Read it: revenue is basically on plan, but EBITDA fell hard. Sheet 03 explains exactly why. Qty in '000 units; price and cost in IDR '000/unit; all money columns in IDR mn.

Sheet 03 Variance Bridge
A1: Variance Bridge - why EBITDA moved
A2: It splits the change from Budget to Actual into four margin drivers plus operating cost. GREEN = pulled from sheet 02. Units: IDR mn. Positive helped profit, negative hurt it.
A4: THE FIVE DRIVERS (Budget to Actual)
A5: Driver | B5: IDR mn | C5: Helped / hurt | D5: What it means
A6: Volume | B6: =(SUM('02 P&L Actual vs Budget'!H7:H9)-SUM('02 P&L Actual vs Budget'!B7:B9))*('02 P&L Actual vs Budget'!G10/SUM('02 P&L Actual vs Budget'!B7:B9)) -> 1341.1111 | C6: =IF(B6>=0,"Helped","Hurt") -> Helped | D6: Sold more or fewer total units, valued at the average budget margin.
A7: Mix | B7: =SUMPRODUCT('02 P&L Actual vs Budget'!H7:H9-'02 P&L Actual vs Budget'!B7:B9,'02 P&L Actual vs Budget'!C7:C9-'02 P&L Actual vs Budget'!D7:D9)-B6 -> -1491.1111 | C7: =IF(B7>=0,"Helped","Hurt") -> Hurt | D7: Sold a different blend of products. More low-margin, less high-margin, hurts here.
A8: Price | B8: =SUMPRODUCT('02 P&L Actual vs Budget'!I7:I9-'02 P&L Actual vs Budget'!C7:C9,'02 P&L Actual vs Budget'!H7:H9) -> -390 | C8: =IF(B8>=0,"Helped","Hurt") -> Hurt | D8: Sold at higher or lower prices than budget.
A9: Cost (input) | B9: =SUMPRODUCT('02 P&L Actual vs Budget'!D7:D9-'02 P&L Actual vs Budget'!J7:J9,'02 P&L Actual vs Budget'!H7:H9) -> -1880 | C9: =IF(B9>=0,"Helped","Hurt") -> Hurt | D9: Unit costs rose or fell. FX on imported materials shows up here.
A10: Operating cost | B10: ='02 P&L Actual vs Budget'!B19-'02 P&L Actual vs Budget'!C19 -> -480 | C10: =IF(B10>=0,"Helped","Hurt") -> Hurt | D10: Spent more or less on payroll, freight, and other opex.
A12: EBITDA BRIDGE (ties out)
A13: Budget EBITDA | B13: ='02 P&L Actual vs Budget'!B28 -> 7200
A14: + Volume | B14: =B6 -> 1341.1111
A15: + Mix | B15: =B7 -> -1491.1111
A16: + Price | B16: =B8 -> -390
A17: + Cost (input) | B17: =B9 -> -1880
A18: + Operating cost | B18: =B10 -> -480
A19: Actual EBITDA (built up) | B19: =B13+B14+B15+B16+B17+B18 -> 4300
A20: Actual EBITDA (from sheet 02) | B20: ='02 P&L Actual vs Budget'!C28 -> 4300
A21: Check (should be 0) | B21: =B19-B20 -> 0

Sheet 04 KPIs & Ratios
A1: KPIs & Ratios
A2: The headline numbers a CFO scans. GREEN = pulled from sheet 02. Units: IDR mn and %.
A4: Metric | B4: Budget | C4: Actual | D4: Change | E4: Note
A5: Revenue (IDR mn) | B5: ='02 P&L Actual vs Budget'!B23 -> 46000 | C5: ='02 P&L Actual vs Budget'!C23 -> 46510 | D5: =C5-B5 -> 510 | E5: On plan or not.
A6: Revenue growth vs budget | B6: =0 -> 0 | C6: ='02 P&L Actual vs Budget'!C23/'02 P&L Actual vs Budget'!B23-1 -> 0.011086957 | D6: =C6-B6 -> 0.011086957 | E6: Small positive here.
A7: Gross margin (IDR mn) | B7: ='02 P&L Actual vs Budget'!B25 -> 14200 | C7: ='02 P&L Actual vs Budget'!C25 -> 11780 | D7: =C7-B7 -> -2420 | E7: Absolute margin.
A8: Gross margin % | B8: ='02 P&L Actual vs Budget'!B25/'02 P&L Actual vs Budget'!B23 -> 0.30869565 | C8: ='02 P&L Actual vs Budget'!C25/'02 P&L Actual vs Budget'!C23 -> 0.25327886 | D8: =C8-B8 -> -0.055416787 | E8: The margin rate. Watch the drop.
A9: EBITDA (IDR mn) | B9: ='02 P&L Actual vs Budget'!B28 -> 7200 | C9: ='02 P&L Actual vs Budget'!C28 -> 4300 | D9: =C9-B9 -> -2900 | E9: Operating cash profit proxy.
A10: EBITDA % | B10: ='02 P&L Actual vs Budget'!B28/'02 P&L Actual vs Budget'!B23 -> 0.15652174 | C10: ='02 P&L Actual vs Budget'!C28/'02 P&L Actual vs Budget'!C23 -> 0.092453236 | D10: =C10-B10 -> -0.064068503 | E10: The headline. Fell hard.
A11: Operating cost (IDR mn) | B11: ='02 P&L Actual vs Budget'!B19 -> 7000 | C11: ='02 P&L Actual vs Budget'!C19 -> 7480 | D11: =C11-B11 -> 480 | E11: Total opex.
A12: Opex to revenue % | B12: ='02 P&L Actual vs Budget'!B19/'02 P&L Actual vs Budget'!B23 -> 0.15217391 | C12: ='02 P&L Actual vs Budget'!C19/'02 P&L Actual vs Budget'!C23 -> 0.16082563 | D12: =C12-B12 -> 0.0086517159 | E12: Cost discipline. Slightly worse.
A13: Blended avg price (IDR '000) | B13: ='02 P&L Actual vs Budget'!B23/'02 P&L Actual vs Budget'!B10 -> 127.77778 | C13: ='02 P&L Actual vs Budget'!C23/'02 P&L Actual vs Budget'!H10 -> 118.04569 | D13: =C13-B13 -> -9.7320925 | E13: Revenue per unit.
A14: Blended avg unit cost (IDR '000) | B14: ='02 P&L Actual vs Budget'!B24/'02 P&L Actual vs Budget'!B10 -> 88.333333 | C14: ='02 P&L Actual vs Budget'!C24/'02 P&L Actual vs Budget'!H10 -> 88.147208 | D14: =C14-B14 -> -0.18612521 | E14: Cost per unit. Up on FX.
A16: GROSS MARGIN % BY PRODUCT (actual)
A17: Product | B17: Revenue | C17: Gross margin | D17: GM % | E17: Note
A18: ='02 P&L Actual vs Budget'!A7 -> Industrial Components | B18: ='02 P&L Actual vs Budget'!K7 -> 19110 | C18: ='02 P&L Actual vs Budget'!M7 -> 4550 | D18: ='02 P&L Actual vs Budget'!M7/'02 P&L Actual vs Budget'!K7 -> 0.23809524 | E18: High volume, thin margin after cost rise
A19: ='02 P&L Actual vs Budget'!A8 -> Precision Assemblies | B19: ='02 P&L Actual vs Budget'!K8 -> 13600 | C19: ='02 P&L Actual vs Budget'!M8 -> 4930 | D19: ='02 P&L Actual vs Budget'!M8/'02 P&L Actual vs Budget'!K8 -> 0.3625 | E19: Best margin, but volume fell
A20: ='02 P&L Actual vs Budget'!A9 -> Standard Parts | B20: ='02 P&L Actual vs Budget'!K9 -> 13800 | C20: ='02 P&L Actual vs Budget'!M9 -> 2300 | D20: ='02 P&L Actual vs Budget'!M9/'02 P&L Actual vs Budget'!K9 -> 0.16666667 | E20: Lowest margin, volume grew

Sheet 05 What-if Simulator
A1: What-if Simulator - test a fix before you commit
A2: Change the levers and watch EBITDA move. Starts from Actual. BLUE = input you change. GREEN = pulled from sheet 02. Units: IDR mn, % for levers.
A4: LEVERS (change these)
A5: Selling price change (%) | B5: 0.04 | C5: Applies to all product prices.
A6: Material / input cost change (%) | B6: 0 | C6: Direct change to unit costs.
A7: Sales volume change (%) | B7: 0 | C7: Applies to all volumes. Use this to test how a price rise might cost you volume.
A8: USD/IDR change (%) | B8: 0.03 | C8: Raises the imported part of unit cost (share on sheet 01).
A9: Operating cost change (%) | B9: 0 | C9: Applies to total opex.
A11: SCENARIO P&L BY PRODUCT
A12: Product | B12: New qty | C12: New price | D12: New cost | E12: New revenue | F12: New COGS | G12: New GM
A13: ='02 P&L Actual vs Budget'!A7 -> Industrial Components | B13: ='02 P&L Actual vs Budget'!H7*(1+$B$7) -> 130 | C13: ='02 P&L Actual vs Budget'!I7*(1+$B$5) -> 152.88 | D13: ='02 P&L Actual vs Budget'!J7*(1+$B$6+'01 Assumptions'!$B$11*$B$8) -> 113.848 | E13: =B13*C13 -> 19874.4 | F13: =B13*D13 -> 14800.24 | G13: =E13-F13 -> 5074.16
A14: ='02 P&L Actual vs Budget'!A8 -> Precision Assemblies | B14: ='02 P&L Actual vs Budget'!H8*(1+$B$7) -> 34 | C14: ='02 P&L Actual vs Budget'!I8*(1+$B$5) -> 416 | D14: ='02 P&L Actual vs Budget'!J8*(1+$B$6+'01 Assumptions'!$B$11*$B$8) -> 259.2075 | E14: =B14*C14 -> 14144 | F14: =B14*D14 -> 8813.055 | G14: =E14-F14 -> 5330.945
A15: ='02 P&L Actual vs Budget'!A9 -> Standard Parts | B15: ='02 P&L Actual vs Budget'!H9*(1+$B$7) -> 230 | C15: ='02 P&L Actual vs Budget'!I9*(1+$B$5) -> 62.4 | D15: ='02 P&L Actual vs Budget'!J9*(1+$B$6+'01 Assumptions'!$B$11*$B$8) -> 50.825 | E15: =B15*C15 -> 14352 | F15: =B15*D15 -> 11689.75 | G15: =E15-F15 -> 2662.25
A16: TOTAL | B16: =SUM(B13:B15) -> 394 | E16: =SUM(E13:E15) -> 48370.4 | F16: =SUM(F13:F15) -> 35303.045 | G16: =SUM(G13:G15) -> 13067.355
A18: RESULT
A19: Base EBITDA - Actual (IDR mn) | B19: ='02 P&L Actual vs Budget'!C28 -> 4300
A20: Scenario gross margin (IDR mn) | B20: =G16 -> 13067.355
A21: Scenario operating cost (IDR mn) | B21: ='02 P&L Actual vs Budget'!C19*(1+$B$9) -> 7480
A22: Scenario EBITDA (IDR mn) | B22: =B20-B21 -> 5587.355
A23: Change vs Actual (IDR mn) | B23: =B22-B19 -> 1287.355
A24: Scenario revenue (IDR mn) | B24: =E16 -> 48370.4
A25: Scenario EBITDA % | B25: =B22/B24 -> 0.11551186
A26: Target EBITDA % | B26: ='01 Assumptions'!$B$10 -> 0.15
A27: Status vs target | B27: =IF(B25>=B26,"On / above target","Below target") -> Below target
A29: Approx price rise to offset cost + FX (pp) | B29: =('01 Assumptions'!$B$11*$B$8+$B$6)*'02 P&L Actual vs Budget'!C24/'02 P&L Actual vs Budget'!C23 -> 0.012320899 | C29: Rough guide: how much price alone would cover the extra cost. Ignores lost volume.
A31: Try these: FX +3% alone (see margin fall). Price +4% and FX +3% (partial recovery). Then add volume -3% to test customer pushback. All illustrative.

Sheet 06 Recommendation
A1: Agent Recommendation & CFO Decision Card
A2: What the agent recommends, why, and the impact, pulled live from sheets 02 and 03. Figures are illustrative. Price actions depend on customer response.
A4: SITUATION
A5: Revenue vs budget | B5: ='02 P&L Actual vs Budget'!C23/'02 P&L Actual vs Budget'!B23-1 -> 0.011086957
A6: EBITDA margin: budget vs actual | B6: ='02 P&L Actual vs Budget'!B28/'02 P&L Actual vs Budget'!B23 -> 0.15652174 | C6: ='02 P&L Actual vs Budget'!C28/'02 P&L Actual vs Budget'!C23 -> 0.092453236
A7: EBITDA change (IDR mn) | B7: ='02 P&L Actual vs Budget'!C28-'02 P&L Actual vs Budget'!B28 -> -2900
A8: Biggest driver: input cost (IDR mn) | B8: ='03 Variance Bridge'!B9 -> -1880
A9: Second driver: mix (IDR mn) | B9: ='03 Variance Bridge'!B7 -> -1491.1111
A10: Offset: volume (IDR mn) | B10: ='03 Variance Bridge'!B6 -> 1341.1111
A12: RECOMMENDATION - three moves
A13: 1) PROTECT MARGIN (price)
A14: - Reverse the price erosion on Industrial Components | C14: Price was cut ~2%; input cost rose. Restore price where the market allows | E14: Recovers price variance
A15: - Pass through a targeted increase on the FX-exposed lines | C15: Cover the imported cost rise, not a blanket hike | E15: Rebuilds margin
A17: 2) FIX THE MIX (sell more of the good stuff)
A18: - Find why Precision Assemblies volume fell | C18: Best-margin line, volume down ~15%. Check demand, supply, or sales focus | E18: Mix is the 2nd driver
A19: - Steer sales incentives toward high-margin lines | C19: Reward margin, not just revenue | E19: Improves the blend
A21: 3) ATTACK COST (the biggest driver)
A22: - Hedge the USD exposure | C22: Imported material inflation is the top driver. Hand the FX piece to the Treasury agent | E22: Stabilises unit cost
A23: - Review supplier contracts and freight | C23: Logistics opex overspent. Renegotiate or reroute | E23: Cuts opex
A24: - Run the what-if before deciding | C24: Test the price rise and the volume it might cost | E24: Avoids a bad call
A26: EXPECTED IMPACT (illustrative, from the what-if)
A27: A 4% price rise with FX +3% lifts EBITDA margin from ~9% toward ~12%
A28: Closing the rest of the gap to the ~15% target needs mix and cost actions too
A30: CFO DECISION CARD
A31: Requested by: Financial Performance Agent | Approval: CFO + Commercial / Sales (dual control)
A32: [ Approve price actions ] [ Approve hedge ] [ Push mix ] [ Run what-if ] [ Ask why ] [ Reject ]
A34: Caution: the price actions assume customers accept the increase. If volume falls, the recovery shrinks. Test it on the what-if and validate elasticity with real data before committing.
