Workbook

Sheet 00 Read Me First
B1: COLLECTIONS & CREDIT INTELLIGENCE AGENT - DEMO DATA ENGINE | D1: Good pick. Collections and credit risk is the strongest cash story after your treasury demo, and it reuses the same company so your agents form one connected narrative. Let me confirm the build approach and then construct it. Same as before: a storyline sheet plus a linked Excel data engine, with the numbers tying out. First I will re-check the spreadsheet skill, then build. Skill confirmed. Building the Collections and Credit Intelligence Agent workbook now, same standards as your treasury demo (Arial, formulas not hardcoded, cross-sheet links in green, zero formula errors). Built. One reference to fix: the recommendation sheet points at the wrong worklist total row. Correcting it, then recalculating. The worklist used wrong row numbers. Fixing the mapping, the note cell, and the total reference, then rebuilding cleanly. Zero errors. Now verifying the numbers tie out before I hand it over. All numbers tie out. The risk scores, DSO, exposure, and recovery totals are internally consistent. Copying to outputs. Done. Here is the Collections and Credit Intelligence Agent demo, built to the same standard as your treasury one. *What is inside* - A storyline sheet (the 7-step agent loop, wow moments, verify list) plus a 6-sheet linked data engine. - Same company, PT Future Manufacturing. Customer A (PT Anugerah Prima) is the late key account in both demos, so the two agents tell one connected story. [High confidence] - Zero formula errors. Every number pulls from the assumptions sheet, so you can change an input and watch it re-flow. *The story in three numbers (all illustrative)* - IDR 38B is overdue, and the top 5 accounts hold about 70% of it. Focus wins. - DSO is 57 days vs a 47-day target. Closing that gap frees about IDR 19.9B in cash. This is the CFO's prize. - 1 customer (CV Berkah Jaya) is high-risk with an open dispute. The agent recommends a credit hold plus an illustrative provision of about IDR 2.5B. *How the risk score works* (so you can defend it in the room) - Each customer scores 0 to 100 from five things: how many days late they pay, how much of the balance is 61+ days overdue, how much of their credit limit is used, whether the trend is worsening, and whether there is a dispute. - Under 34 is Low, 34 to 66 is Medium, 67+ is High. All the weights sit on sheet 01, so you can tune the model live if a client challenges it. *What is illustrative vs what to verify* (on the Read Me and storyline sheets) - Target DSO (47) and the recovery percentages are illustrative. Use the client's own benchmarks if you have them. - The provision figure is illustrative. Real expected credit loss needs a PSAK 71 or IFRS 9 model and Controller sign-off. Do not present it as final. - Confirm the D365 F&O Credit and Collections module and Copilot licensing on the client's release. Do not quote agent pricing without checking Microsoft's current terms. This needs verification. *One honest caution.* This demo leans on the same "cash" emotion as your treasury demo. That is good for a follow-on with the same CFO, since it deepens the story. If you are presenting to a brand-new audience, lead with whichever pain they feel most, then bring the second agent as the encore. Your stated bottleneck is English storytelling, not the data. The strongest next step is a spoken demo script in English for this agent: a word-for-word narration you can practice, tied to each sheet, with simple transitions and a few lines to handle CFO pushback. Want me to write that script next?
B2: A complete, linked receivables model that sits behind the storyline. Same illustrative company as your cash flow demo, so the two agents form one Future Finance AI story.
B4: WHAT THIS WORKBOOK IS
B5: It answers one CFO question: how much cash is stuck in receivables, who is risky, and what should we do this week.
B6: The 'STORYLINE COLLECTIONS 01' sheet is the demo script. The numbered sheets are the working model behind it.
B8: SHEET MAP
B9: 01 Assumptions - all inputs (BLUE). Sales, target DSO, the risk-score weights, recovery %.
B10: 02 Customer Credit & Aging - the receivables book: terms, behaviour, and aging buckets per customer.
B11: 03 Risk Scoring - scores each customer 0-100 and sets a Low/Medium/High tier.
B12: 04 DSO & Cash Impact - DSO, trapped cash, cash freed at target, and exposure by risk tier.
B13: 05 Collections Worklist - who to chase first, ranked, with expected recovery.
B14: 06 Recommendation - the three moves, the impact, the decision card, and an illustrative journal.
B16: THE STORY IN THREE NUMBERS
... B36: BLUE = input you can change. GREEN = pulled from another sheet. BLACK = calculated. YELLOW = key assumption.

Sheet STORYLINE COLLECTIONS
B1: COLLECTIONS & CREDIT INTELLIGENCE AGENT
B2: Demo storyline for a CFO / Finance audience. Company: PT Future Manufacturing Tbk (illustrative). Same company as the cash flow demo, so your agents tell one connected story.
B4: THE BUSINESS PROBLEM
B5: Setup | C5: PT Future Manufacturing sells on credit to distributors, retailers, and export buyers. About IDR 110B is tied up in receivables and IDR 38B is overdue. DSO is ~57 days, above the 47-day target. Cash is trapped, a few customers are sliding toward default, and the AR team chases invoices reactively in spreadsheets, so the riskiest accounts are not always chased first.
B7: THE AGENT LOOP (7 STEPS)
B8: 1. TRIGGER | C8: Runs every morning, and on events: an invoice becomes overdue, a customer crosses its credit limit, or payment behaviour worsens. Send aletr notifications
B9: 2. PERCEIVE | C9: Reads from D365 Finance: open AR invoices and aging, the customer master and credit limits, payment history, dispute cases, and cash application. Can add external credit signals.
B10: 3. REASON | C10: Builds the aging picture, scores each customer's risk (lateness, overdue severity, credit use, trend, disputes), computes DSO and trapped cash, and predicts which invoices will slip. Finds the 20% of accounts holding most of the overdue cash.
B11: 4. RECOMMEND | C11: Produces a ranked collections worklist (who to call first, expected recovery), risk actions (holds and provisions on high-risk, tighter limits on worsening accounts), and prevention (automated dunning for low-risk). Every item is quantified.
B12: 5. APPROVE | C12: Human in the loop. The CFO or Credit Manager reviews and approves the worklist, the credit holds, and the provision. Dual control. This is the trust and governance step, not a black box.
B13: 6. EXECUTE | C13: Sends dunning reminders, creates collection tasks and calls for the team, updates credit holds in D365, and logs every action for audit.
B14: 7. LEARN | C14: Tracks which actions recovered cash, updates the risk scores and predicted pay dates, and improves the ranking over time.
B16: WOW MOMENTS (tie each to a sheet)
B17: Found the trapped cash | C17: IDR 38B overdue, and the top 5 accounts hold ~70% of it. Point to sheet 05.
B18: Caught a default early | C18: 1 customer sliding to default with an open dispute. Agent recommends a hold plus a provision. Point to sheet 03 and 04.
B19: Showed the prize | C19: Cutting DSO from ~57 to 47 days frees about IDR 19.9B in cash. Point to sheet 04.
B20: Governance, not a black box | C20: Human approval plus a full audit trail. Point to the decision card on sheet 06.

Sheet 00 Mock Up
A1: #VALUE! | C1: Part 1. The alert, connected from Treasury - What happens: Collections opens by picking up Treasury's request to pull IDR 5.0B early from the top customer, then adds its own picture: 38B overdue, DSO about 57, one high-risk account. - Terms: Handover between agents. Overdue. - Highlight >> "the baton passed from Treasury to here." It shows the agents work as one chain. Part 2. CFO challenge, discount vs margin and relationship - What happens: The CFO warns that chasing the top customer or offering a discount risks the relationship and margin, and asks for the cost of the discount versus the cash. - Terms: Early-pay discount, a small price cut to get paid sooner. Margin, the profit given up.
A3: #VALUE! | C3: Part 3. AI shows the book and the discount trade - What happens: Two charts, AR aging and risk by tier, then the exact discount trade for Customer A. - Terms: AR aging, how old each unpaid balance is. Risk tier . - Numbers: 38B overdue, top 5 hold about 70%. The trade: a 1% discount to pull 5,000 costs about 50 million. So 50 million of margin frees 5,000 million of cash. [Medium confidence, the customer must accept] Part 4. CFO challenge, prove the DSO - What happens: The CFO says DSO is easy to game and asks for the exact definition and period. - Term: DSO, Days Sales Outstanding, the average days to collect cash. - Why it matters: A weak DSO method can hide a problem. The CFO is right to check. Part 5. AI defends the DSO method - What happens: The agent gives the standard formula. Total receivables divided by annual credit sales, times 365. 110B over 700B is 57 days, annualized, not a favourable short window. [High confidence on the method] - HIghlight "match it to your own convention before a board number." Part 6. CFO challenge, prove the risk - What happens: The CFO says one late payment is not a default, and asks for evidence, not a score. - CFO does not accept a black-box score. This is the strongest challenge in the demo. Part 7. AI gives the evidence - What happens: Five signals, not one. 35 days beyond terms, a 90+ overdue balance, 100% credit-limit use, worsening trend, and an open dispute. The combination drives the high risk. [Medium confidence on default risk] - Term: Credit limit, the most you let a customer owe. - This shows the AI can explain itself. That is a selling point.
A5: #VALUE! | C5: Part 8. CFO asks for options and simulation - What happens: The CFO wants each option in cash and in DSO, then wants to test his own mix. Part 9. AI recommendation and fixed simulation - What happens: Three options with a chart. A, Customer A only, frees 5,000, DSO to 54.8. B, top 5, frees about 21,300, DSO to 46.2, roughly hits the 47 target. C, all overdue, frees about 32,163, DSO to 40.6. - The lesson is that chasing the top 5 gets you to target. You do not need to chase everyone. Part 10 and 11. The live "trial and error" simulator - What happens: The CFO says "let me try combinations." The agent gives sliders. In the app, dragging them re-runs the result live. - The levers: how much to pull from Customer A, the discount percent, and how much to chase from others. - What updates: cash freed, discount cost, new DSO, and a "Week 5 covered" status. - The lesson built in: more discount frees the same cash but costs more margin. A bigger chase lowers DSO but needs customers to actually pay. And if the CFO pulls less than 5,000 from Customer A, the status flips to "Week 5 gap," which would break Treasury's fix. - Terms: Lever, an input you adjust. DSO in days. - HIighligt >> "CFO are testing your own plan, not trusting mine."
A7: #VALUE! | C7: Part 12 and 13. CFO deep dive on Customer A - What happens: The CFO asks the Customer A trade alone, and how much they still owe after. - Result: 5,000 cash freed for a 50 discount cost, a strong trade. Customer A still owes 5,000 after, so the relationship is not strained. [Medium confidence] Part 14 and 15. CFO challenge, the recovery rates - What happens: The CFO asks where the recovery rates come from and warns against invented percentages. - What the AI does: It admits the rates are illustrative placeholders, 95% low, 85% medium, 40% high, not measured from real data, and says they must be calibrated on the client's history. [Low confidence on the rates] This needs verification. - This is important. It shows the AI does not fake numbers, which matches CFO own rule.
A9: #VALUE! | C9: Part 16 and 17. Calculate-first, exact numbers - What happens: Before approving, the CFO asks for exact figures, and asks the agent to confirm the 5 billion lands in Week 5. - Result: cash 5,000, discount cost 50, Customer A overdue 10,000 to 5,000, total AR 110,000 to 105,000, DSO 57.4 to 54.8, Week 5 covered. - Point out that this confirms Treasury's fix holds.
A11: #VALUE! | C11: Part 18 and 19. Final approval and cascade, loop closed - What happens: The CFO approves. The action fans out. D365 puts Berkah on hold, raises the provision, and sends dunning. Treasury is told the 5.0B will land in Week 5. The account manager calls Customer A. The audit log records it. - Terms: Credit hold, stop new orders to a risky customer. Provision (pencadangan), money set aside for likely bad debt. Dunning (surat penagihan), reminder letters. - The close: Performance set price and hedge, Treasury fixed cash and FX, Collections freed the cash and confirmed it back to Week 5. One decision, four agents, one ERP.

Sheet 01 Assumptions
A1: Assumptions & Inputs - change here to run any scenario
A2: One place for every input. BLUE cells are inputs you can change. YELLOW = key assumptions the model depends on. Units: IDR million unless it says USD or days.
A4: SALES & DSO TARGET
A5: Annual credit sales (IDR mn) | B5: 700000 | C5: Sales made on credit over 12 months. Drives the DSO calculation.
A6: Days in year | B6: 365 | C6: Used to convert AR into days of sales.
A7: Target DSO (days) | B7: 47 | C7: The goal. Illustrative benchmark. Confirm with the client's peer data.
A8: Spot USD / IDR (for export customers) | B8: 17950 | C8: Export balances shown in IDR are converted at this rate.
A10: RISK SCORING MODEL (points, max 100)
A11: DBT weight (days beyond terms) | B11: 30 | C11: More days late = more points.
A12: Overdue severity weight (61+ days share) | B12: 25 | C12: Share of balance that is 61+ days overdue.
A13: Credit utilization weight (balance / limit) | B13: 20 | C13: How much of the credit line is used.
A14: Trend points: Worsening | B14: 15 | C14: Payment behaviour getting worse.
A15: Trend points: Stable | B15: 5 | C15: No clear change.
A16: Trend points: Improving | B16: 0 | C16: Getting better.
A17: Dispute points (Yes) | B17: 10 | C17: Open dispute raises risk.
A18: DBT days for maximum points | B18: 60 | C18: DBT at or above this scores full DBT points.
A19: Tier threshold: Medium (min score) | B19: 34 | C19: Score at or above this = Medium.
A20: Tier threshold: High (min score) | B20: 67 | C20: Score at or above this = High.
A22: RECOVERY & PROVISION (illustrative placeholders)
A23: Low-risk recovery of overdue (%) | B23: 0.95 | C23: Assumed share of overdue cash we collect.
A24: Medium-risk recovery of overdue (%) | B24: 0.85 | C24: Illustrative.
A25: High-risk recovery of overdue (%) | B25: 0.4 | C25: Illustrative. High risk = harder to collect.
A26: High-risk loss rate (ECL proxy, %) | B26: 0.5 | C26: Illustrative provision rate. Real ECL needs PSAK 71 / IFRS 9.

Sheet 02 Customer Credit & Aging
A1: Customer Credit & AR Aging
A2: The receivables book: credit terms, payment behaviour, and how old each balance is. BLUE = input. Aging buckets are in IDR mn. Export balances are USD-origin, converted at the spot rate on sheet 01.
A4: ID | B4: Customer | C4: Segment | D4: Terms | E4: Curr | F4: Credit limit | G4: DBT (days) | H4: Trend | I4: Dispute | J4: On-time % | K4: Current | L4: 1-30 od | M4: 31-60 od | N4: 61-90 od | O4: 90+ od | P4: Total AR | Q4: Overdue | R4: % overdue | S4: Utilisation
A5: C001 | B5: PT Anugerah Prima (Customer A) | C5: Key account | D5: Net 45 | E5: IDR | F5: 30000 | G5: 18 | H5: Worsening | I5: No | J5: 0.7 | K5: 8000 | L5: 6000 | M5: 4000 | N5: 0 | O5: 0 | P5: =SUM(K5:O5) -> 18000 | Q5: =SUM(L5:O5) -> 10000 | R5: =IF(P5=0,0,Q5/P5) -> 0.55555556 | S5: =IF(F5=0,0,P5/F5) -> 0.6
A6: C002 | B6: PT Distribusi Jaya | C6: Distributor | D6: Net 30 | E6: IDR | F6: 20000 | G6: 8 | H6: Stable | I6: No | J6: 0.88 | K6: 9000 | L6: 3000 | M6: 0 | N6: 0 | O6: 0 | P6: =SUM(K6:O6) -> 12000 | Q6: =SUM(L6:O6) -> 3000 | R6: =IF(P6=0,0,Q6/P6) -> 0.25 | S6: =IF(F6=0,0,P6/F6) -> 0.6
A7: C003 | B7: PT Ritel Nusantara | C7: Domestic retail | D7: Net 30 | E7: IDR | F7: 18000 | G7: 12 | H7: Stable | I7: No | J7: 0.82 | K7: 8000 | L7: 2500 | M7: 1000 | N7: 0 | O7: 0 | P7: =SUM(K7:O7) -> 11500 | Q7: =SUM(L7:O7) -> 3500 | R7: =IF(P7=0,0,Q7/P7) -> 0.30434783 | S7: =IF(F7=0,0,P7/F7) -> 0.63888889
A8: C004 | B8: CV Mitra Dagang | C8: Distributor | D8: Net 30 | E8: IDR | F8: 12000 | G8: 5 | H8: Improving | I8: No | J8: 0.92 | K8: 6000 | L8: 2000 | M8: 0 | N8: 0 | O8: 0 | P8: =SUM(K8:O8) -> 8000 | Q8: =SUM(L8:O8) -> 2000 | R8: =IF(P8=0,0,Q8/P8) -> 0.25 | S8: =IF(F8=0,0,P8/F8) -> 0.66666667
A9: C005 | B9: CV Toko Sejahtera | C9: SME | D9: Net 30 | E9: IDR | F9: 6000 | G9: 22 | H9: Worsening | I9: No | J9: 0.65 | K9: 2000 | L9: 1500 | M9: 1000 | N9: 500 | O9: 0 | P9: =SUM(K9:O9) -> 5000 | Q9: =SUM(L9:O9) -> 3000 | R9: =IF(P9=0,0,Q9/P9) -> 0.6 | S9: =IF(F9=0,0,P9/F9) -> 0.83333333
A10: C006 | B10: PT Karya Abadi | C10: Distributor | D10: Net 30 | E10: IDR | F10: 15000 | G10: 14 | H10: Stable | I10: No | J10: 0.8 | K10: 7000 | L10: 2000 | M10: 1500 | N10: 0 | O10: 0 | P10: =SUM(K10:O10) -> 10500 | Q10: =SUM(L10:O10) -> 3500 | R10: =IF(P10=0,0,Q10/P10) -> 0.33333333 | S10: =IF(F10=0,0,P10/F10) -> 0.7
A11: C007 | B11: PT Sumber Makmur | C11: Wholesale | D11: Net 60 | E11: IDR | F11: 25000 | G11: 20 | H11: Worsening | I11: No | J11: 0.72 | K11: 10000 | L11: 3000 | M11: 2000 | N11: 1500 | O11: 0 | P11: =SUM(K11:O11) -> 16500 | Q11: =SUM(L11:O11) -> 6500 | R11: =IF(P11=0,0,Q11/P11) -> 0.39393939 | S11: =IF(F11=0,0,P11/F11) -> 0.66
A12: C008 | B12: Lion City Trading Pte | C12: Export (USD) | D12: Net 30 | E12: USD | F12: 10000 | G12: 0 | H12: Stable | I12: No | J12: 0.98 | K12: 7180 | L12: 0 | M12: 0 | N12: 0 | O12: 0 | P12: =SUM(K12:O12) -> 7180 | Q12: =SUM(L12:O12) -> 0 | R12: =IF(P12=0,0,Q12/P12) -> 0 | S12: =IF(F12=0,0,P12/F12) -> 0.718
A13: C009 | B13: Peninsula Export Sdn | C13: Export (USD) | D13: Net 30 | E13: USD | F13: 8000 | G13: 0 | H13: Stable | I13: No | J13: 0.97 | K13: 5385 | L13: 0 | M13: 0 | N13: 0 | O13: 0 | P13: =SUM(K13:O13) -> 5385 | Q13: =SUM(L13:O13) -> 0 | R13: =IF(P13=0,0,Q13/P13) -> 0 | S13: =IF(F13=0,0,P13/F13) -> 0.673125
A14: C010 | B14: PT Maju Bersama | C14: Domestic retail | D14: Net 30 | E14: IDR | F14: 10000 | G14: 6 | H14: Stable | I14: No | J14: 0.9 | K14: 5000 | L14: 1500 | M14: 0 | N14: 0 | O14: 0 | P14: =SUM(K14:O14) -> 6500 | Q14: =SUM(L14:O14) -> 1500 | R14: =IF(P14=0,0,Q14/P14) -> 0.23076923 | S14: =IF(F14=0,0,P14/F14) -> 0.65
A15: C011 | B15: CV Berkah Jaya | C15: SME | D15: Net 30 | E15: IDR | F15: 5000 | G15: 35 | H15: Worsening | I15: Yes | J15: 0.55 | K15: 1500 | L15: 1000 | M15: 800 | N15: 700 | O15: 1000 | P15: =SUM(K15:O15) -> 5000 | Q15: =SUM(L15:O15) -> 3500 | R15: =IF(P15=0,0,Q15/P15) -> 0.7 | S15: =IF(F15=0,0,P15/F15) -> 1
A16: C012 | B16: PT Cahaya Sentosa | C16: Distributor | D16: Net 30 | E16: IDR | F16: 8000 | G16: 7 | H16: Stable | I16: No | J16: 0.89 | K16: 3000 | L16: 1435 | M16: 0 | N16: 0 | O16: 0 | P16: =SUM(K16:O16) -> 4435 | Q16: =SUM(L16:O16) -> 1435 | R16: =IF(P16=0,0,Q16/P16) -> 0.32356257 | S16: =IF(F16=0,0,P16/F16) -> 0.554375
B18: TOTAL | K18: =SUM(K5:K16) -> 72065 | L18: =SUM(L5:L16) -> 23935 | M18: =SUM(M5:M16) -> 10300 | N18: =SUM(N5:N16) -> 2700 | O18: =SUM(O5:O16) -> 1000 | P18: =SUM(P5:P16) -> 110000 | Q18: =SUM(Q5:Q16) -> 37935 | R18: =Q18/P18 -> 0.34486364
A20: DBT = Days Beyond Terms (average days a customer pays late). 'od' = overdue. Rows shaded amber = worsening trend; red = open dispute.

Sheet 03 Risk Scoring
A1: Customer Risk Scoring
A2: The agent scores each customer 0-100 from lateness, overdue severity, credit use, trend, and disputes. GREEN = pulled from sheet 02. Weights are on sheet 01. Higher score = higher risk.
A4: ID | B4: Customer | C4: Balance | D4: Util % | E4: 61+ od | F4: Severity % | G4: DBT | H4: Trend | I4: Disp | J4: DBT pts | K4: Sev pts | L4: Util pts | M4: Trend pts | N4: Disp pts | O4: Risk score | P4: Tier | Q4: Rank
A5: ='02 Customer Credit & Aging'!A5 -> C001 | B5: ='02 Customer Credit & Aging'!B5 -> PT Anugerah Prima (Customer A) | C5: ='02 Customer Credit & Aging'!P5 -> 18000 | D5: ='02 Customer Credit & Aging'!S5 -> 0.6 | E5: ='02 Customer Credit & Aging'!N5+'02 Customer Credit & Aging'!O5 -> 0 | F5: =IF(C5=0,0,E5/C5) -> 0 | G5: ='02 Customer Credit & Aging'!G5 -> 18 | H5: ='02 Customer Credit & Aging'!H5 -> Worsening | I5: ='02 Customer Credit & Aging'!I5 -> No | J5: =MIN(G5/'01 Assumptions'!$B$18,1)*'01 Assumptions'!$B$11 -> 9 | K5: =F5*'01 Assumptions'!$B$12 -> 0 | L5: =MIN(D5,1)*'01 Assumptions'!$B$13 -> 12 | M5: =IF(H5="Worsening",'01 Assumptions'!$B$14,IF(H5="Stable",'01 Assumptions'!$B$15,'01 Assumptions'!$B$16)) -> 15 | N5: =IF(I5="Yes",'01 Assumptions'!$B$17,0) -> 0 | O5: =J5+K5+L5+M5+N5 -> 36 | P5: =IF(O5>='01 Assumptions'!$B$20,"High",IF(O5>='01 Assumptions'!$B$19,"Medium","Low")) -> Medium | Q5: =RANK(O5,$O$5:$O$16) -> 4
A6: ='02 Customer Credit & Aging'!A6 -> C002 | B6: ='02 Customer Credit & Aging'!B6 -> PT Distribusi Jaya | C6: ='02 Customer Credit & Aging'!P6 -> 12000 | D6: ='02 Customer Credit & Aging'!S6 -> 0.6 | E6: ='02 Customer Credit & Aging'!N6+'02 Customer Credit & Aging'!O6 -> 0 | F6: =IF(C6=0,0,E6/C6) -> 0 | G6: ='02 Customer Credit & Aging'!G6 -> 8 | H6: ='02 Customer Credit & Aging'!H6 -> Stable | I6: ='02 Customer Credit & Aging'!I6 -> No | J6: =MIN(G6/'01 Assumptions'!$B$18,1)*'01 Assumptions'!$B$11 -> 4 | K6: =F6*'01 Assumptions'!$B$12 -> 0 | L6: =MIN(D6,1)*'01 Assumptions'!$B$13 -> 12 | M6: =IF(H6="Worsening",'01 Assumptions'!$B$14,IF(H6="Stable",'01 Assumptions'!$B$15,'01 Assumptions'!$B$16)) -> 5 | N6: =IF(I6="Yes",'01 Assumptions'!$B$17,0) -> 0 | O6: =J6+K6+L6+M6+N6 -> 21 | P6: =IF(O6>='01 Assumptions'!$B$20,"High",IF(O6>='01 Assumptions'!$B$19,"Medium","Low")) -> Low | Q6: =RANK(O6,$O$5:$O$16) -> 7
A7: ='02 Customer Credit & Aging'!A7 -> C003 | B7: ='02 Customer Credit & Aging'!B7 -> PT Ritel Nusantara | C7: ='02 Customer Credit & Aging'!P7 -> 11500 | D7: ='02 Customer Credit & Aging'!S7 -> 0.63888889 | E7: ='02 Customer Credit & Aging'!N7+'02 Customer Credit & Aging'!O7 -> 0 | F7: =IF(C7=0,0,E7/C7) -> 0 | G7: ='02 Customer Credit & Aging'!G7 -> 12 | H7: ='02 Customer Credit & Aging'!H7 -> Stable | I7: ='02 Customer Credit & Aging'!I7 -> No | J7: =MIN(G7/'01 Assumptions'!$B$18,1)*'01 Assumptions'!$B$11 -> 6 | K7: =F7*'01 Assumptions'!$B$12 -> 0 | L7: =MIN(D7,1)*'01 Assumptions'!$B$13 -> 12.777778 | M7: =IF(H7="Worsening",'01 Assumptions'!$B$14,IF(H7="Stable",'01 Assumptions'!$B$15,'01 Assumptions'!$B$16)) -> 5 | N7: =IF(I7="Yes",'01 Assumptions'!$B$17,0) -> 0 | O7: =J7+K7+L7+M7+N7 -> 23.777778 | P7: =IF(O7>='01 Assumptions'!$B$20,"High",IF(O7>='01 Assumptions'!$B$19,"Medium","Low")) -> Low | Q7: =RANK(O7,$O$5:$O$16) -> 6
A8: ='02 Customer Credit & Aging'!A8 -> C004 | B8: ='02 Customer Credit & Aging'!B8 -> CV Mitra Dagang | C8: ='02 Customer Credit & Aging'!P8 -> 8000 | D8: ='02 Customer Credit & Aging'!S8 -> 0.66666667 | E8: ='02 Customer Credit & Aging'!N8+'02 Customer Credit & Aging'!O8 -> 0 | F8: =IF(C8=0,0,E8/C8) -> 0 | G8: ='02 Customer Credit & Aging'!G8 -> 5 | H8: ='02 Customer Credit & Aging'!H8 -> Improving | I8: ='02 Customer Credit & Aging'!I8 -> No | J8: =MIN(G8/'01 Assumptions'!$B$18,1)*'01 Assumptions'!$B$11 -> 2.5 | K8: =F8*'01 Assumptions'!$B$12 -> 0 | L8: =MIN(D8,1)*'01 Assumptions'!$B$13 -> 13.333333 | M8: =IF(H8="Worsening",'01 Assumptions'!$B$14,IF(H8="Stable",'01 Assumptions'!$B$15,'01 Assumptions'!$B$16)) -> 0 | N8: =IF(I8="Yes",'01 Assumptions'!$B$17,0) -> 0 | O8: =J8+K8+L8+M8+N8 -> 15.833333 | P8: =IF(O8>='01 Assumptions'!$B$20,"High",IF(O8>='01 Assumptions'!$B$19,"Medium","Low")) -> Low | Q8: =RANK(O8,$O$5:$O$16) -> 12
A9: ='02 Customer Credit & Aging'!A9 -> C005 | B9: ='02 Customer Credit & Aging'!B9 -> CV Toko Sejahtera | C9: ='02 Customer Credit & Aging'!P9 -> 5000 | D9: ='02 Customer Credit & Aging'!S9 -> 0.83333333 | E9: ='02 Customer Credit & Aging'!N9+'02 Customer Credit & Aging'!O9 -> 500 | F9: =IF(C9=0,0,E9/C9) -> 0.1 | G9: ='02 Customer Credit & Aging'!G9 -> 22 | H9: ='02 Customer Credit & Aging'!H9 -> Worsening | I9: ='02 Customer Credit & Aging'!I9 -> No | J9: =MIN(G9/'01 Assumptions'!$B$18,1)*'01 Assumptions'!$B$11 -> 11 | K9: =F9*'01 Assumptions'!$B$12 -> 2.5 | L9: =MIN(D9,1)*'01 Assumptions'!$B$13 -> 16.666667 | M9: =IF(H9="Worsening",'01 Assumptions'!$B$14,IF(H9="Stable",'01 Assumptions'!$B$15,'01 Assumptions'!$B$16)) -> 15 | N9: =IF(I9="Yes",'01 Assumptions'!$B$17,0) -> 0 | O9: =J9+K9+L9+M9+N9 -> 45.166667 | P9: =IF(O9>='01 Assumptions'!$B$20,"High",IF(O9>='01 Assumptions'!$B$19,"Medium","Low")) -> Medium | Q9: =RANK(O9,$O$5:$O$16) -> 2
A10: ='02 Customer Credit & Aging'!A10 -> C006 | B10: ='02 Customer Credit & Aging'!B10 -> PT Karya Abadi | C10: ='02 Customer Credit & Aging'!P10 -> 10500 | D10: ='02 Customer Credit & Aging'!S10 -> 0.7 | E10: ='02 Customer Credit & Aging'!N10+'02 Customer Credit & Aging'!O10 -> 0 | F10: =IF(C10=0,0,E10/C10) -> 0 | G10: ='02 Customer Credit & Aging'!G10 -> 14 | H10: ='02 Customer Credit & Aging'!H10 -> Stable | I10: ='02 Customer Credit & Aging'!I10 -> No | J10: =MIN(G10/'01 Assumptions'!$B$18,1)*'01 Assumptions'!$B$11 -> 7 | K10: =F10*'01 Assumptions'!$B$12 -> 0 | L10: =MIN(D10,1)*'01 Assumptions'!$B$13 -> 14 | M10: =IF(H10="Worsening",'01 Assumptions'!$B$14,IF(H10="Stable",'01 Assumptions'!$B$15,'01 Assumptions'!$B$16)) -> 5 | N10: =IF(I10="Yes",'01 Assumptions'!$B$17,0) -> 0 | O10: =J10+K10+L10+M10+N10 -> 26 | P10: =IF(O10>='01 Assumptions'!$B$20,"High",IF(O10>='01 Assumptions'!$B$19,"Medium","Low")) -> Low | Q10: =RANK(O10,$O$5:$O$16) -> 5
A11: ='02 Customer Credit & Aging'!A11 -> C007 | B11: ='02 Customer Credit & Aging'!B11 -> PT Sumber Makmur | C11: ='02 Customer Credit & Aging'!P11 -> 16500 | D11: ='02 Customer Credit & Aging'!S11 -> 0.66 | E11: ='02 Customer Credit & Aging'!N11+'02 Customer Credit & Aging'!O11 -> 1500 | F11: =IF(C11=0,0,E11/C11) -> 0.090909091 | G11: ='02 Customer Credit & Aging'!G11 -> 20 | H11: ='02 Customer Credit & Aging'!H11 -> Worsening | I11: ='02 Customer Credit & Aging'!I11 -> No | J11: =MIN(G11/'01 Assumptions'!$B$18,1)*'01 Assumptions'!$B$11 -> 10 | K11: =F11*'01 Assumptions'!$B$12 -> 2.2727273 | L11: =MIN(D11,1)*'01 Assumptions'!$B$13 -> 13.2 | M11: =IF(H11="Worsening",'01 Assumptions'!$B$14,IF(H11="Stable",'01 Assumptions'!$B$15,'01 Assumptions'!$B$16)) -> 15 | N11: =IF(I11="Yes",'01 Assumptions'!$B$17,0) -> 0 | O11: =J11+K11+L11+M11+N11 -> 40.472727 | P11: =IF(O11>='01 Assumptions'!$B$20,"High",IF(O11>='01 Assumptions'!$B$19,"Medium","Low")) -> Medium | Q11: =RANK(O11,$O$5:$O$16) -> 3
A12: ='02 Customer Credit & Aging'!A12 -> C008 | B12: ='02 Customer Credit & Aging'!B12 -> Lion City Trading Pte | C12: ='02 Customer Credit & Aging'!P12 -> 7180 | D12: ='02 Customer Credit & Aging'!S12 -> 0.718 | E12: ='02 Customer Credit & Aging'!N12+'02 Customer Credit & Aging'!O12 -> 0 | F12: =IF(C12=0,0,E12/C12) -> 0 | G12: ='02 Customer Credit & Aging'!G12 -> 0 | H12: ='02 Customer Credit & Aging'!H12 -> Stable | I12: ='02 Customer Credit & Aging'!I12 -> No | J12: =MIN(G12/'01 Assumptions'!$B$18,1)*'01 Assumptions'!$B$11 -> 0 | K12: =F12*'01 Assumptions'!$B$12 -> 0 | L12: =MIN(D12,1)*'01 Assumptions'!$B$13 -> 14.36 | M12: =IF(H12="Worsening",'01 Assumptions'!$B$14,IF(H12="Stable",'01 Assumptions'!$B$15,'01 Assumptions'!$B$16)) -> 5 | N12: =IF(I12="Yes",'01 Assumptions'!$B$17,0) -> 0 | O12: =J12+K12+L12+M12+N12 -> 19.36 | P12: =IF(O12>='01 Assumptions'!$B$20,"High",IF(O12>='01 Assumptions'!$B$19,"Medium","Low")) -> Low | Q12: =RANK(O12,$O$5:$O$16) -> 10
A13: ='02 Customer Credit & Aging'!A13 -> C009 | B13: ='02 Customer Credit & Aging'!B13 -> Peninsula Export Sdn | C13: ='02 Customer Credit & Aging'!P13 -> 5385 | D13: ='02 Customer Credit & Aging'!S13 -> 0.673125 | E13: ='02 Customer Credit & Aging'!N13+'02 Customer Credit & Aging'!O13 -> 0 | F13: =IF(C13=0,0,E13/C13) -> 0 | G13: ='02 Customer Credit & Aging'!G13 -> 0 | H13: ='02 Customer Credit & Aging'!H13 -> Stable | I13: ='02 Customer Credit & Aging'!I13 -> No | J13: =MIN(G13/'01 Assumptions'!$B$18,1)*'01 Assumptions'!$B$11 -> 0 | K13: =F13*'01 Assumptions'!$B$12 -> 0 | L13: =MIN(D13,1)*'01 Assumptions'!$B$13 -> 13.4625 | M13: =IF(H13="Worsening",'01 Assumptions'!$B$14,IF(H13="Stable",'01 Assumptions'!$B$15,'01 Assumptions'!$B$16)) -> 5 | N13: =IF(I13="Yes",'01 Assumptions'!$B$17,0) -> 0 | O13: =J13+K13+L13+M13+N13 -> 18.4625 | P13: =IF(O13>='01 Assumptions'!$B$20,"High",IF(O13>='01 Assumptions'!$B$19,"Medium","Low")) -> Low | Q13: =RANK(O13,$O$5:$O$16) -> 11
A14: ='02 Customer Credit & Aging'!A14 -> C010 | B14: ='02 Customer Credit & Aging'!B14 -> PT Maju Bersama | C14: ='02 Customer Credit & Aging'!P14 -> 6500 | D14: ='02 Customer Credit & Aging'!S14 -> 0.65 | E14: ='02 Customer Credit & Aging'!N14+'02 Customer Credit & Aging'!O14 -> 0 | F14: =IF(C14=0,0,E14/C14) -> 0 | G14: ='02 Customer Credit & Aging'!G14 -> 6 | H14: ='02 Customer Credit & Aging'!H14 -> Stable | I14: ='02 Customer Credit & Aging'!I14 -> No | J14: =MIN(G14/'01 Assumptions'!$B$18,1)*'01 Assumptions'!$B$11 -> 3 | K14: =F14*'01 Assumptions'!$B$12 -> 0 | L14: =MIN(D14,1)*'01 Assumptions'!$B$13 -> 13 | M14: =IF(H14="Worsening",'01 Assumptions'!$B$14,IF(H14="Stable",'01 Assumptions'!$B$15,'01 Assumptions'!$B$16)) -> 5 | N14: =IF(I14="Yes",'01 Assumptions'!$B$17,0) -> 0 | O14: =J14+K14+L14+M14+N14 -> 21 | P14: =IF(O14>='01 Assumptions'!$B$20,"High",IF(O14>='01 Assumptions'!$B$19,"Medium","Low")) -> Low | Q14: =RANK(O14,$O$5:$O$16) -> 7
A15: ='02 Customer Credit & Aging'!A15 -> C011 | B15: ='02 Customer Credit & Aging'!B15 -> CV Berkah Jaya | C15: ='02 Customer Credit & Aging'!P15 -> 5000 | D15: ='02 Customer Credit & Aging'!S15 -> 1 | E15: ='02 Customer Credit & Aging'!N15+'02 Customer Credit & Aging'!O15 -> 1700 | F15: =IF(C15=0,0,E15/C15) -> 0.34 | G15: ='02 Customer Credit & Aging'!G15 -> 35 | H15: ='02 Customer Credit & Aging'!H15 -> Worsening | I15: ='02 Customer Credit & Aging'!I15 -> Yes | J15: =MIN(G15/'01 Assumptions'!$B$18,1)*'01 Assumptions'!$B$11 -> 17.5 | K15: =F15*'01 Assumptions'!$B$12 -> 8.5 | L15: =MIN(D15,1)*'01 Assumptions'!$B$13 -> 20 | M15: =IF(H15="Worsening",'01 Assumptions'!$B$14,IF(H15="Stable",'01 Assumptions'!$B$15,'01 Assumptions'!$B$16)) -> 15 | N15: =IF(I15="Yes",'01 Assumptions'!$B$17,0) -> 10 | O15: =J15+K15+L15+M15+N15 -> 71 | P15: =IF(O15>='01 Assumptions'!$B$20,"High",IF(O15>='01 Assumptions'!$B$19,"Medium","Low")) -> High | Q15: =RANK(O15,$O$5:$O$16) -> 1
A16: ='02 Customer Credit & Aging'!A16 -> C012 | B16: ='02 Customer Credit & Aging'!B16 -> PT Cahaya Sentosa | C16: ='02 Customer Credit & Aging'!P16 -> 4435 | D16: ='02 Customer Credit & Aging'!S16 -> 0.554375 | E16: ='02 Customer Credit & Aging'!N16+'02 Customer Credit & Aging'!O16 -> 0 | F16: =IF(C16=0,0,E16/C16) -> 0 | G16: ='02 Customer Credit & Aging'!G16 -> 7 | H16: ='02 Customer Credit & Aging'!H16 -> Stable | I16: ='02 Customer Credit & Aging'!I16 -> No | J16: =MIN(G16/'01 Assumptions'!$B$18,1)*'01 Assumptions'!$B$11 -> 3.5 | K16: =F16*'01 Assumptions'!$B$12 -> 0 | L16: =MIN(D16,1)*'01 Assumptions'!$B$13 -> 11.0875 | M16: =IF(H16="Worsening",'01 Assumptions'!$B$14,IF(H16="Stable",'01 Assumptions'!$B$15,'01 Assumptions'!$B$16)) -> 5 | N16: =IF(I16="Yes",'01 Assumptions'!$B$17,0) -> 0 | O16: =J16+K16+L16+M16+N16 -> 19.5875 | P16: =IF(O16>='01 Assumptions'!$B$20,"High",IF(O16>='01 Assumptions'!$B$19,"Medium","Low")) -> Low | Q16: =RANK(O16,$O$5:$O$16) -> 9
A18: Risk score = DBT points + severity points + utilisation points + trend points + dispute points. Tiers: Low under 34, Medium 34-66, High 67+.

Sheet 04 DSO & Cash Impact
A1: DSO & Trapped-Cash Impact
A2: How much cash is tied up in receivables, and how much a lower DSO would free. GREEN = pulled from other sheets. Units: IDR mn and days.
A4: RECEIVABLES POSITION
A5: Total AR outstanding (IDR mn) | B5: ='02 Customer Credit & Aging'!P18 -> 110000
A6: Not yet due (current) | B6: ='02 Customer Credit & Aging'!K18 -> 72065
A7: Overdue (past due) | B7: ='02 Customer Credit & Aging'!Q18 -> 37935
A8: Overdue as % of AR | B8: =B7/B5 -> 0.34486364
A10: DSO & CASH FREED
A11: Annual credit sales (IDR mn) | B11: ='01 Assumptions'!$B$5 -> 700000
A12: Daily credit sales (IDR mn) | B12: ='01 Assumptions'!$B$5/'01 Assumptions'!$B$6 -> 1917.8082
A13: Current DSO (days) | B13: =B5/'01 Assumptions'!$B$5*'01 Assumptions'!$B$6 -> 57.357143
A14: Target DSO (days) | B14: ='01 Assumptions'!$B$7 -> 47
A15: DSO gap (days) | B15: =B13-B14 -> 10.357143
A16: Cash freed if target met (IDR mn) | B16: =B15*B12 -> 19863.014 | C16: Equals DSO gap x daily sales. The prize for the CFO.
A18: RISK EXPOSURE BY TIER
A19: Tier | B19: Customers | C19: Exposure (IDR mn) | D19: % of AR | E19: Note
A20: High | B20: =COUNTIF('03 Risk Scoring'!$P$5:$P$16,"High") -> 1 | C20: =SUMIF('03 Risk Scoring'!$P$5:$P$16,"High",'03 Risk Scoring'!$C$5:$C$16) -> 5000 | D20: =C20/$B$5 -> 0.045454545 | E20: Likely bad-debt candidates. Act now.
A21: Medium | B21: =COUNTIF('03 Risk Scoring'!$P$5:$P$16,"Medium") -> 3 | C21: =SUMIF('03 Risk Scoring'!$P$5:$P$16,"Medium",'03 Risk Scoring'!$C$5:$C$16) -> 39500 | D21: =C21/$B$5 -> 0.35909091 | E21: Watch list. Call before they slip further.
A22: Low | B22: =COUNTIF('03 Risk Scoring'!$P$5:$P$16,"Low") -> 8 | C22: =SUMIF('03 Risk Scoring'!$P$5:$P$16,"Low",'03 Risk Scoring'!$C$5:$C$16) -> 65500 | D22: =C22/$B$5 -> 0.59545455 | E22: Standard automated reminders.
A23: Total | B23: =SUM(B20:B22) -> 12 | C23: =SUM(C20:C22) -> 110000 | D23: =C23/B5 -> 1
A25: Illustrative provision on high-risk (ECL proxy, IDR mn) | B25: =C20*'01 Assumptions'!$B$26 -> 2500 | C25: Illustrative only. Real ECL needs PSAK 71 / IFRS 9 and Controller sign-off.

Sheet 05 Collections Worklist
A1: Agent Collections Worklist - who to chase first
A2: Accounts with overdue cash, ranked by amount and risk. GREEN = pulled from sheets 02/03. Recovery % is by risk tier (sheet 01). Focus the top of this list to collect most of the cash.
A4: Rank | B4: Customer | C4: Segment | D4: Overdue (IDR mn) | E4: Oldest bucket | F4: Tier | G4: Score | H4: Recommended action | I4: Recovery % | J4: Expected recovery
A5: 1 | B5: ='02 Customer Credit & Aging'!B5 -> PT Anugerah Prima (Customer A) | C5: ='02 Customer Credit & Aging'!C5 -> Key account | D5: ='02 Customer Credit & Aging'!Q5 -> 10000 | E5: =IF('02 Customer Credit & Aging'!O5>0,"90+ days",IF('02 Customer Credit & Aging'!N5>0,"61-90 days",IF('02 Customer Credit & Aging'!M5>0,"31-60 days",IF('02 Customer Credit & Aging'!L5>0,"1-30 days","Current")))) -> 31-60 days | F5: ='03 Risk Scoring'!P5 -> Medium | G5: ='03 Risk Scoring'!O5 -> 36 | H5: Priority call today. Offer a 1% early-pay discount for immediate settlement. Agree a plan on the 31-60 balance. | I5: =IF(F5="High",'01 Assumptions'!$B$25,IF(F5="Medium",'01 Assumptions'!$B$24,'01 Assumptions'!$B$23)) -> 0.85 | J5: =D5*I5 -> 8500
A6: 2 | B6: ='02 Customer Credit & Aging'!B11 -> PT Sumber Makmur | C6: ='02 Customer Credit & Aging'!C11 -> Wholesale | D6: ='02 Customer Credit & Aging'!Q11 -> 6500 | E6: =IF('02 Customer Credit & Aging'!O11>0,"90+ days",IF('02 Customer Credit & Aging'!N11>0,"61-90 days",IF('02 Customer Credit & Aging'!M11>0,"31-60 days",IF('02 Customer Credit & Aging'!L11>0,"1-30 days","Current")))) -> 61-90 days | F6: ='03 Risk Scoring'!P11 -> Medium | G6: ='03 Risk Scoring'!O11 -> 40.472727 | H6: Call before further slippage. Confirm a firm pay date. Review the IDR 25,000 mn credit limit. | I6: =IF(F6="High",'01 Assumptions'!$B$25,IF(F6="Medium",'01 Assumptions'!$B$24,'01 Assumptions'!$B$23)) -> 0.85 | J6: =D6*I6 -> 5525
A7: 3 | B7: ='02 Customer Credit & Aging'!B15 -> CV Berkah Jaya | C7: ='02 Customer Credit & Aging'!C15 -> SME | D7: ='02 Customer Credit & Aging'!Q15 -> 3500 | E7: =IF('02 Customer Credit & Aging'!O15>0,"90+ days",IF('02 Customer Credit & Aging'!N15>0,"61-90 days",IF('02 Customer Credit & Aging'!M15>0,"31-60 days",IF('02 Customer Credit & Aging'!L15>0,"1-30 days","Current")))) -> 90+ days | F7: ='03 Risk Scoring'!P15 -> High | G7: ='03 Risk Scoring'!O15 -> 71 | H7: HOLD new shipments. Resolve the dispute. Escalate to the credit committee. Provision the 90+ balance. | I7: =IF(F7="High",'01 Assumptions'!$B$25,IF(F7="Medium",'01 Assumptions'!$B$24,'01 Assumptions'!$B$23)) -> 0.4 | J7: =D7*I7 -> 1400
A8: 4 | B8: ='02 Customer Credit & Aging'!B10 -> PT Karya Abadi | C8: ='02 Customer Credit & Aging'!C10 -> Distributor | D8: ='02 Customer Credit & Aging'!Q10 -> 3500 | E8: =IF('02 Customer Credit & Aging'!O10>0,"90+ days",IF('02 Customer Credit & Aging'!N10>0,"61-90 days",IF('02 Customer Credit & Aging'!M10>0,"31-60 days",IF('02 Customer Credit & Aging'!L10>0,"1-30 days","Current")))) -> 31-60 days | F8: ='03 Risk Scoring'!P10 -> Low | G8: ='03 Risk Scoring'!O10 -> 26 | H8: Send a reminder and confirm the 31-60 invoice pay date. | I8: =IF(F8="High",'01 Assumptions'!$B$25,IF(F8="Medium",'01 Assumptions'!$B$24,'01 Assumptions'!$B$23)) -> 0.95 | J8: =D8*I8 -> 3325
A9: 5 | B9: ='02 Customer Credit & Aging'!B9 -> CV Toko Sejahtera | C9: ='02 Customer Credit & Aging'!C9 -> SME | D9: ='02 Customer Credit & Aging'!Q9 -> 3000 | E9: =IF('02 Customer Credit & Aging'!O9>0,"90+ days",IF('02 Customer Credit & Aging'!N9>0,"61-90 days",IF('02 Customer Credit & Aging'!M9>0,"31-60 days",IF('02 Customer Credit & Aging'!L9>0,"1-30 days","Current")))) -> 61-90 days | F9: ='03 Risk Scoring'!P9 -> Medium | G9: ='03 Risk Scoring'!O9 -> 45.166667 | H9: Call. Worsening SME. Confirm a pay date, tighten the limit, and watch the 61-90 balance. | I9: =IF(F9="High",'01 Assumptions'!$B$25,IF(F9="Medium",'01 Assumptions'!$B$24,'01 Assumptions'!$B$23)) -> 0.85 | J9: =D9*I9 -> 2550
A10: 6 | B10: ='02 Customer Credit & Aging'!B7 -> PT Ritel Nusantara | C10: ='02 Customer Credit & Aging'!C7 -> Domestic retail | D10: ='02 Customer Credit & Aging'!Q7 -> 3500 | E10: =IF('02 Customer Credit & Aging'!O7>0,"90+ days",IF('02 Customer Credit & Aging'!N7>0,"61-90 days",IF('02 Customer Credit & Aging'!M7>0,"31-60 days",IF('02 Customer Credit & Aging'!L7>0,"1-30 days","Current")))) -> 31-60 days | F10: ='03 Risk Scoring'!P7 -> Low | G10: ='03 Risk Scoring'!O7 -> 23.777778 | H10: Reminder. Confirm the 31-60 balance pay date. | I10: =IF(F10="High",'01 Assumptions'!$B$25,IF(F10="Medium",'01 Assumptions'!$B$24,'01 Assumptions'!$B$23)) -> 0.95 | J10: =D10*I10 -> 3325
A11: 7 | B11: ='02 Customer Credit & Aging'!B6 -> PT Distribusi Jaya | C11: ='02 Customer Credit & Aging'!C6 -> Distributor | D11: ='02 Customer Credit & Aging'!Q6 -> 3000 | E11: =IF('02 Customer Credit & Aging'!O6>0,"90+ days",IF('02 Customer Credit & Aging'!N6>0,"61-90 days",IF('02 Customer Credit & Aging'!M6>0,"31-60 days",IF('02 Customer Credit & Aging'!L6>0,"1-30 days","Current")))) -> 1-30 days | F11: ='03 Risk Scoring'!P6 -> Low | G11: ='03 Risk Scoring'!O6 -> 21 | H11: Automated reminder. Low risk, standard dunning. | I11: =IF(F11="High",'01 Assumptions'!$B$25,IF(F11="Medium",'01 Assumptions'!$B$24,'01 Assumptions'!$B$23)) -> 0.95 | J11: =D11*I11 -> 2850
A12: 8 | B12: ='02 Customer Credit & Aging'!B8 -> CV Mitra Dagang | C12: ='02 Customer Credit & Aging'!C8 -> Distributor | D12: ='02 Customer Credit & Aging'!Q8 -> 2000 | E12: =IF('02 Customer Credit & Aging'!O8>0,"90+ days",IF('02 Customer Credit & Aging'!N8>0,"61-90 days",IF('02 Customer Credit & Aging'!M8>0,"31-60 days",IF('02 Customer Credit & Aging'!L8>0,"1-30 days","Current")))) -> 1-30 days | F12: ='03 Risk Scoring'!P8 -> Low | G12: ='03 Risk Scoring'!O8 -> 15.833333 | H12: Automated reminder. Improving, no action needed. | I12: =IF(F12="High",'01 Assumptions'!$B$25,IF(F12="Medium",'01 Assumptions'!$B$24,'01 Assumptions'!$B$23)) -> 0.95 | J12: =D12*I12 -> 1900
A13: 9 | B13: ='02 Customer Credit & Aging'!B14 -> PT Maju Bersama | C13: ='02 Customer Credit & Aging'!C14 -> Domestic retail | D13: ='02 Customer Credit & Aging'!Q14 -> 1500 | E13: =IF('02 Customer Credit & Aging'!O14>0,"90+ days",IF('02 Customer Credit & Aging'!N14>0,"61-90 days",IF('02 Customer Credit & Aging'!M14>0,"31-60 days",IF('02 Customer Credit & Aging'!L14>0,"1-30 days","Current")))) -> 1-30 days | F13: ='03 Risk Scoring'!P14 -> Low | G13: ='03 Risk Scoring'!O14 -> 21 | H13: Automated reminder. Low risk. | I13: =IF(F13="High",'01 Assumptions'!$B$25,IF(F13="Medium",'01 Assumptions'!$B$24,'01 Assumptions'!$B$23)) -> 0.95 | J13: =D13*I13 -> 1425
A14: 10 | B14: ='02 Customer Credit & Aging'!B16 -> PT Cahaya Sentosa | C14: ='02 Customer Credit & Aging'!C16 -> Distributor | D14: ='02 Customer Credit & Aging'!Q16 -> 1435 | E14: =IF('02 Customer Credit & Aging'!O16>0,"90+ days",IF('02 Customer Credit & Aging'!N16>0,"61-90 days",IF('02 Customer Credit & Aging'!M16>0,"31-60 days",IF('02 Customer Credit & Aging'!L16>0,"1-30 days","Current")))) -> 1-30 days | F14: ='03 Risk Scoring'!P16 -> Low | G14: ='03 Risk Scoring'!O16 -> 19.5875 | H14: Automated reminder. Low risk. | I14: =IF(F14="High",'01 Assumptions'!$B$25,IF(F14="Medium",'01 Assumptions'!$B$24,'01 Assumptions'!$B$23)) -> 0.95 | J14: =D14*I14 -> 1363.25
B15: TOTAL (accounts with overdue) | D15: =SUM(D5:D14) -> 37935 | J15: =SUM(J5:J14) -> 32163.25
A17: The two export customers (Lion City, Peninsula) are current, so they are not on the worklist. Recovery % are illustrative and set by tier on sheet 01.

Sheet 06 Recommendation
A1: Agent Recommendation & CFO Decision Card
A2: What the agent recommends, why, and the impact, pulled live from sheets 04 and 05. The provision journal is illustrative and needs Controller sign-off.
A4: SITUATION (from the receivables book)
A5: Total AR outstanding (IDR mn) | B5: ='04 DSO & Cash Impact'!B5 -> 110000
A6: Overdue (IDR mn) | B6: ='04 DSO & Cash Impact'!B7 -> 37935
A7: Current DSO (days) | B7: ='04 DSO & Cash Impact'!B13 -> 57.357143
A8: Target DSO (days) | B8: ='04 DSO & Cash Impact'!B14 -> 47
A9: Cash freed if target met (IDR mn) | B9: ='04 DSO & Cash Impact'!B16 -> 19863.014
A10: High-risk exposure (IDR mn) | B10: ='04 DSO & Cash Impact'!C20 -> 5000
A12: RECOMMENDATION - three moves
A13: 1) ACCELERATE (pull cash in, lower DSO)
A14: - Work the ranked worklist top-down | C14: The top 5 accounts hold ~70% of the overdue cash | E14: Fastest DSO reduction
A15: - Offer a small early-pay discount to the key account | C15: 1% to Customer A to settle the 31-60 balance now | E15: Frees cash this month
A16: - Confirm firm pay dates on all Medium accounts | C16: Get commitments before month-end | E16: Prevents slippage
A18: 2) CONTAIN (stop the bleed on risky accounts)
A19: - Put CV Berkah Jaya on credit hold | C19: High risk, dispute, 90+ balance | E19: Caps further exposure
A20: - Raise an illustrative provision on high-risk | C20: Book an ECL estimate, confirm with Controller | E20: Protects the P&L
A21: - Tighten limits on worsening Medium accounts | C21: Toko Sejahtera, Sumber Makmur | E21: Reduces future risk
A23: 3) PREVENT (make it stick)
A24: - Automate dunning for Low-risk accounts | C24: Reminders sent without staff time | E24: Frees the AR team
A25: - Run the agent weekly | C25: Re-score, re-rank, re-predict | E25: Keeps DSO down
A26: - Review credit-limit policy quarterly | C26: Feed behaviour back into limits | E26: Fewer surprises
A28: EXPECTED IMPACT (calculated)
A29: Expected cash recovery from the worklist (IDR mn) | B29: ='05 Collections Worklist'!J15 -> 32163.25 | C29: Sum of overdue x recovery % across the worklist.
A30: Cash freed by hitting the DSO target (IDR mn) | B30: ='04 DSO & Cash Impact'!B16 -> 19863.014
A31: Illustrative provision on high-risk (IDR mn) | B31: ='04 DSO & Cash Impact'!B25 -> 2500
A33: CFO DECISION CARD
A34: Requested by: Collections & Credit Agent | Approval: CFO + Credit / Finance Manager (dual control)
A35: [ Approve worklist ] [ Approve credit holds ] [ Approve provision ] [ Modify ] [ Ask why ] [ Reject ]
A37: ILLUSTRATIVE PROVISION JOURNAL - NEEDS CONTROLLER SIGN-OFF
A38: To raise the bad-debt provision (simplified, illustrative only):
A39: Dr | B39: Impairment loss on receivables (P&L) | E39: ECL estimate
A40: Cr | B40: Allowance for doubtful accounts (contra-AR) | E40: same amount
A41: Expected credit loss under PSAK 71 / IFRS 9 needs a proper model and Controller sign-off. Do not present the provision figure as final.
