Workbook

Sheet 00 Read Me First
B1: PAYMENT LEAKAGE & FRAUD AGENT - DEMO DATA ENGINE
B2: A working AP-integrity model behind the storyline. Same illustrative company as your other agents, so the whole suite tells one Future Finance AI story.
B4: WHAT THIS WORKBOOK IS
B5: It answers one CFO question: how much cash are we losing to duplicate payments, overbilling, missed discounts, and fraud, and how do we stop it.
B6: The 'STORYLINE LEAKAGE 01' sheet is the demo script. The numbered sheets are the working model behind it.
B8: SHEET MAP
B9: 01 Assumptions - inputs (BLUE): approval threshold, split band, recovery rates.
B10: 02 AP Transactions - a sample of the payment feed the agent scans.
B11: 03 Anomaly Detection - the agent's flags per transaction, with amount at risk.
B12: 04 Leakage & Fraud Summary - the found-money number, by category and by action.
B13: 05 Action Worklist - what to do, in order, with an owner.
B14: 06 Recommendation - the three moves, the impact, the decision card, an illustrative journal.
... B36: BLUE = input you can change. GREEN = pulled from another sheet. BLACK = calculated. YELLOW = key assumption.

Sheet STORYLINE LEAKAGE
B1: PAYMENT LEAKAGE & FRAUD AGENT
B2: Demo storyline for a CFO / Finance audience. Company: PT Future Manufacturing Tbk (illustrative). Same company as the other agents, so they tell one connected story.
B4: THE BUSINESS PROBLEM
B5: Setup | C5: PT Future Manufacturing pays hundreds of vendor invoices each cycle, across USD imports and domestic suppliers. Money leaks out through duplicate payments, overbilling above the purchase order, missed early-payment discounts, and the occasional fraud attempt such as a changed bank account. The AP team checks by hand and cannot catch everything before the payment run.
B7: THE AGENT LOOP (7 STEPS)
B8: 1. TRIGGER | C8: Runs on every payment proposal and invoice batch, and continuously on the AP feed. Also runs when a vendor master record or bank account changes.
B9: 2. PERCEIVE | C9: Reads open and paid AP invoices, purchase orders and goods receipts (for 3-way match), payment terms, the vendor master and bank details, and the approval log.
B10: 3. REASON | C10: Detects duplicates, 3-way match breaks, missed discounts, split invoices, and suspicious bank changes. Scores severity, quantifies the amount at risk, and separates 'already paid, recover' from 'about to pay, block'.
B11: 4. RECOMMEND | C11: Produces a ranked action list. Block or hold the risky payments now, recover the ones already paid, and fix the root causes so it does not happen again.
B12: 5. APPROVE | C12: Human in the loop. The AP manager or CFO approves the holds, the recoveries, and the control changes. Dual control. This is the trust and governance step.
B13: 6. EXECUTE | C13: Places payment holds in D365, raises vendor debit notes for recovery, sends verification callbacks, merges duplicate vendor records, and logs every action for audit.
B14: 7. LEARN | C14: Tracks which flags were true, tunes the thresholds to cut false alarms, and gets more accurate over time.
B16: WOW MOMENTS (tie each to a sheet)
B17: Stopped a fraud | C17: It blocked a IDR 3.8B payment where the vendor bank account changed 2 days before the run. That is a classic fraud pattern. Point to sheet 03 and 05.
B18: Found money already gone | C18: IDR 3.05B in duplicate payments already made, ready to claw back. Point to sheet 04.
B19: One clear number | C19: IDR 7.8B of leakage and fraud risk caught this cycle, most of it before it left the building. Point to sheet 04.
B20: Governance, not a black box | C20: Human approval plus a full audit trail. Point to the decision card on sheet 06.

Sheet 00 Mock Up
A1: #VALUE! | C1: Part 1. The alert, feeding two agents - What happens: The agent runs its weekly scan, 1,850 invoices, 10 flagged. Two items need the CFO: a held IDR 3.8B suspected fraud, and IDR 3.0B in duplicate payments to claw back. Total risk IDR 7.8B. - The connection: what it protects feeds Treasury (cash) and Performance (cost, which lifts EBITDA margin). - Terms: Payment integrity. Duplicate payment. Claw back (menarik kembali dana). - Highlights "this agent guards the back door." It rounds out the suite. Part 2. CFO challenge, is it really fraud - What happens: The CFO asks how the agent knows it is fraud, not a real bank change, and what the exposure is if wrong. - Term: Exposure (eksposur / risiko kerugian), the money at risk. - CFO worries about blocking a real vendor. Part 3. AI answer plus the breakdown chart - What happens: The agent says it is high risk, not confirmed fraud, and it holds for a callback, not a permanent block. The pattern is the classic business email compromise signature. Then a chart of the categories. - Terms: Business email compromise, BEC (penipuan pengalihan rekening), a fraud where a criminal changes the bank details. Callback verification. - The key line: if legitimate you lose one day, if fraud you lose 3.8 billion. [Medium confidence on fraud, High on the callback being correct]
A3: #VALUE! | C3: Part 4. CFO challenge, prove the duplicates and the false-positive rate - What happens: The CFO asks the agent to prove they are true duplicates, not two real invoices, and asks the false-positive rate. - Term: False-positive rate, how often the agent flags something that is fine. - This is the trust question for any detection tool. Part 5. AI gives the evidence - What happens: One duplicate is the same invoice number paid twice. The other is the same invoice number under a duplicate vendor record. The agent flags by invoice number and by vendor-plus-amount, so a repeated invoice number is strong evidence, not just a matching amount. [Medium confidence on a precise false-positive rate] This needs verification. Part 6. CFO cross-agent challenge, the smartest one - What happens: The CFO says missed early-payment discounts assume we had cash, and warns not to pay early if it breaks the Week 5 cash gap Treasury flagged. - Why it matters: This shows the CFO thinking across agents. A real risk is two agents fighting over the same cash.
A5: #VALUE! | C5: Part 7. AI answer, connects to Treasury - What happens: The agent agrees, says it checked the cash position, is not recommending early payment in tight weeks like Week 5, and flagged it to Treasury so the agents do not clash. [Medium confidence] - This is a strong moment. It proves the agents coordinate, not collide. Part 8 and 9. Options and the fixed simulation - What happens: The CFO wants what he actually keeps, not the gross. The agent shows total protected under three recovery rates: 60% keeps 6,370, 85% keeps 7,233, 100% keeps 7,750, against the 7,845 at risk. - The point: blocked money never leaves, so it holds in every case. Only the recoverable part depends on the vendor.
A7: #VALUE! | C7: Part 10 and 11. The live trial-and-error simulator - What happens: The CFO says "let me try it." The agent gives sliders. In the app, dragging them re-runs live. - The levers: how much of the suspect payment to hold, the duplicate recovery rate, and the overbilling recovery rate. - What updates: blocked, recovered, total protected, and lost. - The lesson built in: release the hold and the fraud protection drops to zero, gambling 3.8 billion. Lower recovery rates shrink what you keep. - Terms: Recovery rate, the share of clawed-back money you actually get. Part 12 and 13. Deep dive, the fraud decision alone - What happens: The CFO asks the hold decision on its own. A chart shows 3,800 protected if fraud versus about 40 cost if legitimate. - The point: 3,800 protected for a 40 downside is a clear call. Hold and verify.
A9: #VALUE! | C9: Part 14 and 15. CFO challenge, net recoverable after disputes - What happens: The CFO asks the real recoverable after vendor disputes, not the gross 3 billion. - What the AI does: It gives net figures at different rates and says the calculation uses the rate the CFO sets, so he sees net, not gross. [Medium confidence] This needs verification Part 16 and 17. Calculate-first, exact numbers - What happens: The CFO asks for exact figures with his parameters. Hold 3.8B, 85% duplicate recovery, 90% overbilling. - Result: blocked 4,300, recovered 2,953, lost 95, total protected 7,253. It also shows what feeds Treasury (7,253 cash) and Performance (3,048 cost). - Terms: Debit note (nota debit), a document to reclaim money from a vendor.
A11: #VALUE! | C11: Part 18 and 19. Final approval and cascade - What happens: The CFO approves. D365 keeps the hold, raises debit notes, and blocks the duplicate vendor record. The bank runs the callback. Treasury and Performance get the cash and cost impact. The audit log records it. - The close: this agent stops money leaving, which strengthens the same cash and profit story the other three build.
A13: #VALUE!

Sheet 01 Assumptions
A1: Assumptions & Inputs - change here to run any scenario
A2: One place for every input. BLUE cells are inputs you can change. YELLOW = key assumptions the model depends on. Amounts are in IDR million (USD import bills shown as IDR-equivalent).
A4: SCAN & CONTROL SETTINGS
A5: Invoices scanned this cycle (illustrative) | B5: 1850 | C5: Illustrative count for the flag-rate story. The transaction sheet shows a small sample.
A6: Approval threshold (IDR mn) | B6: 1000 | C6: Invoices above this need extra approval. Used to spot split invoices.
A7: Split 'just under' band (% of threshold) | B7: 0.9 | C7: Flag invoices priced between this % and 100% of the threshold when a same-day sibling exists.
A8: Duplicate test | B8: by invoice no + vendor/amount | C8: A repeat invoice number, or the same vendor and amount, is flagged as a possible duplicate.
A10: RECOVERY ASSUMPTIONS (illustrative)
A11: Duplicate payment recovery rate (%) | B11: 0.95 | C11: Share of duplicate cash we expect to claw back. Illustrative.
A12: Overbilling recovery rate (%) | B12: 0.9 | C12: Share of overbilled cash we expect to recover. Illustrative.
A13: Weeks in year | B13: 52 | C13: Used to annualise the discount leakage (illustrative).
A14: Sample period (weeks) | B14: 2 | C14: The sample below covers about 2 weeks of invoices.

Sheet 02 AP Transactions
A1: AP Transactions (sample of the payment feed)
A2: Vendor invoices and payments the agent scans. This is a small, illustrative sample. BLUE = input. Amounts in IDR mn. The agent does the flagging on sheet 03, so this sheet is the raw feed.
A4: Txn | B4: Vendor | C4: Vendor ID | D4: Invoice no | E4: Inv date | F4: Amount | G4: PO amt | H4: GR amt | I4: Terms | J4: Disc % | K4: Disc days | L4: Days to pay | M4: Bank changed? | N4: Approver | O4: Status
A5: T01 | B5: Shenzhen Micro Ltd | C5: V-SM | D5: INV-8790 | E5: 46239 | F5: 2200 | G5: 2200 | H5: 2200 | I5: Net 30 | L5: 28 | M5: No | N5: Andi | O5: Paid
A6: T02 | B6: Taipei Semicon Co | C6: V-TS | D6: INV-TS-540 | E6: 46240 | F6: 1600 | G6: 1600 | H6: 1600 | I6: Net 30 | L6: 30 | M6: No | N6: Andi | O6: Paid
A7: T03 | B7: PT Bahan Baku Lokal | C7: V-BBL | D7: INV-BBL-210 | E7: 46241 | F7: 900 | G7: 900 | H7: 900 | I7: Net 30 | L7: 25 | M7: No | N7: Budi | O7: Paid
A8: T04 | B8: PT Logistik Andalan | C8: V-LA | D8: INV-LA-105 | E8: 46241 | F8: 700 | I8: Net 30 | L8: 20 | M8: No | N8: Budi | O8: Paid
A9: T05 | B9: PT Energi Pratama | C9: V-EP | D9: INV-EP-133 | E9: 46242 | F9: 1300 | I9: Net 30 | L9: 22 | M9: No | N9: Citra | O9: Paid
A10: T06 | B10: Shenzhen Micro Ltd | C10: V-SM | D10: INV-8801 | E10: 46243 | F10: 1850 | G10: 1850 | H10: 1850 | I10: Net 30 | L10: 12 | M10: No | N10: Andi | O10: Paid
A11: T07 | B11: Shenzhen Micro Ltd | C11: V-SM | D11: INV-8801 | E11: 46246 | F11: 1850 | G11: 1850 | H11: 1850 | I11: Net 30 | L11: 9 | M11: No | N11: Andi | O11: Paid
A12: T08 | B12: Taipei Semicon Co | C12: V-TS | D12: INV-TS-551 | E12: 46244 | F12: 3200 | G12: 2800 | H12: 2800 | I12: Net 30 | L12: 20 | M12: No | N12: Andi | O12: Paid
A13: T09 | B13: Osaka Precision KK | C13: V-OP | D13: INV-OP-330 | E13: 46245 | F13: 4500 | G13: 4500 | H13: 4000 | I13: Net 30 | M13: No | N13: Dewi | O13: Pending
A14: T10 | B14: PT Logistik Andalan | C14: V-LA | D14: INV-LA-110 | E14: 46242 | F14: 2000 | I14: 2/10 Net 30 | J14: 0.02 | K14: 10 | L14: 25 | M14: No | N14: Budi | O14: Paid
A15: T11 | B15: PT Energi Pratama | C15: V-EP | D15: INV-EP-140 | E15: 46243 | F15: 1500 | I15: 2/10 Net 30 | J15: 0.02 | K15: 10 | L15: 18 | M15: No | N15: Citra | O15: Paid
A16: T12 | B16: PT Bahan Baku Lokal | C16: V-BBL | D16: INV-BBL-260 | E16: 46244 | F16: 2500 | G16: 2500 | H16: 2500 | I16: 1/10 Net 30 | J16: 0.01 | K16: 10 | L16: 20 | M16: No | N16: Budi | O16: Paid
A17: T13 | B17: Osaka Precision KK | C17: V-OP | D17: INV-OP-345 | E17: 46247 | F17: 3800 | G17: 3800 | H17: 3800 | I17: Net 30 | M17: Yes | N17: Dewi | O17: Pending
A18: T14 | B18: PT Bahan Baku Lokal | C18: V-BBL | D18: INV-BBL-220 | E18: 46245 | F18: 1200 | G18: 1200 | H18: 1200 | I18: Net 30 | L18: 24 | M18: No | N18: Budi | O18: Paid
A19: T15 | B19: PT Bahan Baku Lokal (cabang) | C19: V-BBL2 | D19: INV-BBL-220 | E19: 46249 | F19: 1200 | G19: 1200 | H19: 1200 | I19: Net 30 | L19: 20 | M19: No | N19: Eka | O19: Paid
A20: T16 | B20: PT Kemasan Prima | C20: V-KP | D20: INV-KP-501 | E20: 46246 | F20: 980 | I20: Net 30 | L20: 25 | M20: No | N20: Fajar | O20: Paid
A21: T17 | B21: PT Kemasan Prima | C21: V-KP | D21: INV-KP-502 | E21: 46246 | F21: 970 | I21: Net 30 | L21: 25 | M21: No | N21: Fajar | O21: Paid
A22: T18 | B22: Taipei Semicon Co | C22: V-TS | D22: INV-TS-560 | E22: 46248 | F22: 2100 | G22: 2100 | H22: 2100 | I22: Net 30 | L22: 29 | M22: No | N22: Andi | O22: Paid
A23: T19 | B23: PT Logistik Andalan | C23: V-LA | D23: INV-LA-120 | E23: 46249 | F23: 850 | I23: Net 30 | L23: 21 | M23: No | N23: Budi | O23: Paid
A24: T20 | B24: Shenzhen Micro Ltd | C24: V-SM | D24: INV-8815 | E24: 46250 | F24: 2600 | G24: 2600 | H24: 2600 | I24: Net 30 | L24: 27 | M24: No | N24: Andi | O24: Paid
A25: T21 | B25: PT Bahan Baku Lokal | C25: V-BBL | D25: INV-BBL-275 | E25: 46251 | F25: 1400 | G25: 1400 | H25: 1400 | I25: Net 30 | L25: 26 | M25: No | N25: Budi | O25: Paid
A26: T22 | B26: PT Energi Pratama | C26: V-EP | D26: INV-EP-155 | E26: 46252 | F26: 1250 | I26: Net 30 | L26: 23 | M26: No | N26: Citra | O26: Paid
A28: PO amt = purchase order value. GR amt = goods received value. A blank PO/GR means a service invoice (no goods). 'Days to pay' is blank for pending invoices.

Sheet 03 Anomaly Detection
A1: Anomaly Detection - what the agent flags
A2: The agent scores each transaction for leakage and fraud. GREEN = pulled from sheet 02. Logic and thresholds are on sheet 01. Amount at risk is in IDR mn.
A4: Txn | B4: Vendor | C4: Invoice no | D4: Amount | E4: Dup count | F4: Dup copy | G4: 3-way gap | H4: Disc lost | I4: Bank | J4: Split | K4: Anomaly type | L4: Severity | M4: Amount at risk | N4: Recommended action | O4: Status | P4: Flag
A5: ='02 AP Transactions'!A5 -> T01 | B5: ='02 AP Transactions'!B5 -> Shenzhen Micro Ltd | C5: ='02 AP Transactions'!D5 -> INV-8790 | D5: ='02 AP Transactions'!F5 -> 2200 | E5: =COUNTIF('02 AP Transactions'!$D$5:$D$26,'02 AP Transactions'!D5) -> 1 | F5: =IF(COUNTIF('02 AP Transactions'!$D$5:$D5,'02 AP Transactions'!D5)>1,1,0) -> 0 | G5: =IF(AND('02 AP Transactions'!G5>0,'02 AP Transactions'!H5>0),MAX(0,'02 AP Transactions'!F5-MIN('02 AP Transactions'!G5,'02 AP Transactions'!H5)),0) -> 0 | H5: =IF(AND('02 AP Transactions'!J5>0,'02 AP Transactions'!L5>'02 AP Transactions'!K5,'02 AP Transactions'!O5="Paid"),'02 AP Transactions'!J5*'02 AP Transactions'!F5,0) -> 0 | I5: =IF('02 AP Transactions'!M5="Yes",1,0) -> 0 | J5: =IF(AND('02 AP Transactions'!F5>='01 Assumptions'!$B$6*'01 Assumptions'!$B$7,'02 AP Transactions'!F5<'01 Assumptions'!$B$6,COUNTIFS('02 AP Transactions'!$B$5:$B$26,'02 AP Transactions'!B5,'02 AP Transactions'!$E$5:$E$26,'02 AP Transactions'!E5)>1),1,0) -> 0 | K5: =IF(I5=1,"Bank-change fraud",IF(F5=1,"Duplicate payment",IF(G5>0,"Overbilling (3-way)",IF(J5=1,"Split / threshold",IF(H5>0,"Lost discount","-"))))) -> - | L5: =IF(I5=1,"High",IF(F5=1,"High",IF(G5>0,"Medium",IF(J5=1,"Medium",IF(H5>0,"Low","-"))))) -> - | M5: =IF(I5=1,D5,IF(F5=1,D5,IF(G5>0,G5,IF(J5=1,0,IF(H5>0,H5,0))))) -> 0 | N5: =IF(I5=1,"Hold & verify (callback)",IF(F5=1,IF('02 AP Transactions'!O5="Pending","Block payment","Recover / claw back"),IF(G5>0,IF('02 AP Transactions'!O5="Pending","Short-pay to PO/GR","Recover overbilled"),IF(J5=1,"Investigate approval",IF(H5>0,"Fix discount process","-"))))) -> - | O5: ='02 AP Transactions'!O5 -> Paid | P5: =IF(K5="-","","FLAG")
A6: ='02 AP Transactions'!A6 -> T02 | B6: ='02 AP Transactions'!B6 -> Taipei Semicon Co | C6: ='02 AP Transactions'!D6 -> INV-TS-540 | D6: ='02 AP Transactions'!F6 -> 1600 | E6: =COUNTIF('02 AP Transactions'!$D$5:$D$26,'02 AP Transactions'!D6) -> 1 | F6: =IF(COUNTIF('02 AP Transactions'!$D$5:$D6,'02 AP Transactions'!D6)>1,1,0) -> 0 | G6: =IF(AND('02 AP Transactions'!G6>0,'02 AP Transactions'!H6>0),MAX(0,'02 AP Transactions'!F6-MIN('02 AP Transactions'!G6,'02 AP Transactions'!H6)),0) -> 0 | H6: =IF(AND('02 AP Transactions'!J6>0,'02 AP Transactions'!L6>'02 AP Transactions'!K6,'02 AP Transactions'!O6="Paid"),'02 AP Transactions'!J6*'02 AP Transactions'!F6,0) -> 0 | I6: =IF('02 AP Transactions'!M6="Yes",1,0) -> 0 | J6: =IF(AND('02 AP Transactions'!F6>='01 Assumptions'!$B$6*'01 Assumptions'!$B$7,'02 AP Transactions'!F6<'01 Assumptions'!$B$6,COUNTIFS('02 AP Transactions'!$B$5:$B$26,'02 AP Transactions'!B6,'02 AP Transactions'!$E$5:$E$26,'02 AP Transactions'!E6)>1),1,0) -> 0 | K6: =IF(I6=1,"Bank-change fraud",IF(F6=1,"Duplicate payment",IF(G6>0,"Overbilling (3-way)",IF(J6=1,"Split / threshold",IF(H6>0,"Lost discount","-"))))) -> - | L6: =IF(I6=1,"High",IF(F6=1,"High",IF(G6>0,"Medium",IF(J6=1,"Medium",IF(H6>0,"Low","-"))))) -> - | M6: =IF(I6=1,D6,IF(F6=1,D6,IF(G6>0,G6,IF(J6=1,0,IF(H6>0,H6,0))))) -> 0 | N6: =IF(I6=1,"Hold & verify (callback)",IF(F6=1,IF('02 AP Transactions'!O6="Pending","Block payment","Recover / claw back"),IF(G6>0,IF('02 AP Transactions'!O6="Pending","Short-pay to PO/GR","Recover overbilled"),IF(J6=1,"Investigate approval",IF(H6>0,"Fix discount process","-"))))) -> - | O6: ='02 AP Transactions'!O6 -> Paid | P6: =IF(K6="-","","FLAG")
A7: ='02 AP Transactions'!A7 -> T03 | B7: ='02 AP Transactions'!B7 -> PT Bahan Baku Lokal | C7: ='02 AP Transactions'!D7 -> INV-BBL-210 | D7: ='02 AP Transactions'!F7 -> 900 | E7: =COUNTIF('02 AP Transactions'!$D$5:$D$26,'02 AP Transactions'!D7) -> 1 | F7: =IF(COUNTIF('02 AP Transactions'!$D$5:$D7,'02 AP Transactions'!D7)>1,1,0) -> 0 | G7: =IF(AND('02 AP Transactions'!G7>0,'02 AP Transactions'!H7>0),MAX(0,'02 AP Transactions'!F7-MIN('02 AP Transactions'!G7,'02 AP Transactions'!H7)),0) -> 0 | H7: =IF(AND('02 AP Transactions'!J7>0,'02 AP Transactions'!L7>'02 AP Transactions'!K7,'02 AP Transactions'!O7="Paid"),'02 AP Transactions'!J7*'02 AP Transactions'!F7,0) -> 0 | I7: =IF('02 AP Transactions'!M7="Yes",1,0) -> 0 | J7: =IF(AND('02 AP Transactions'!F7>='01 Assumptions'!$B$6*'01 Assumptions'!$B$7,'02 AP Transactions'!F7<'01 Assumptions'!$B$6,COUNTIFS('02 AP Transactions'!$B$5:$B$26,'02 AP Transactions'!B7,'02 AP Transactions'!$E$5:$E$26,'02 AP Transactions'!E7)>1),1,0) -> 0 | K7: =IF(I7=1,"Bank-change fraud",IF(F7=1,"Duplicate payment",IF(G7>0,"Overbilling (3-way)",IF(J7=1,"Split / threshold",IF(H7>0,"Lost discount","-"))))) -> - | L7: =IF(I7=1,"High",IF(F7=1,"High",IF(G7>0,"Medium",IF(J7=1,"Medium",IF(H7>0,"Low","-"))))) -> - | M7: =IF(I7=1,D7,IF(F7=1,D7,IF(G7>0,G7,IF(J7=1,0,IF(H7>0,H7,0))))) -> 0 | N7: =IF(I7=1,"Hold & verify (callback)",IF(F7=1,IF('02 AP Transactions'!O7="Pending","Block payment","Recover / claw back"),IF(G7>0,IF('02 AP Transactions'!O7="Pending","Short-pay to PO/GR","Recover overbilled"),IF(J7=1,"Investigate approval",IF(H7>0,"Fix discount process","-"))))) -> - | O7: ='02 AP Transactions'!O7 -> Paid | P7: =IF(K7="-","","FLAG")
A8: ='02 AP Transactions'!A8 -> T04 | B8: ='02 AP Transactions'!B8 -> PT Logistik Andalan | C8: ='02 AP Transactions'!D8 -> INV-LA-105 | D8: ='02 AP Transactions'!F8 -> 700 | E8: =COUNTIF('02 AP Transactions'!$D$5:$D$26,'02 AP Transactions'!D8) -> 1 | F8: =IF(COUNTIF('02 AP Transactions'!$D$5:$D8,'02 AP Transactions'!D8)>1,1,0) -> 0 | G8: =IF(AND('02 AP Transactions'!G8>0,'02 AP Transactions'!H8>0),MAX(0,'02 AP Transactions'!F8-MIN('02 AP Transactions'!G8,'02 AP Transactions'!H8)),0) -> 0 | H8: =IF(AND('02 AP Transactions'!J8>0,'02 AP Transactions'!L8>'02 AP Transactions'!K8,'02 AP Transactions'!O8="Paid"),'02 AP Transactions'!J8*'02 AP Transactions'!F8,0) -> 0 | I8: =IF('02 AP Transactions'!M8="Yes",1,0) -> 0 | J8: =IF(AND('02 AP Transactions'!F8>='01 Assumptions'!$B$6*'01 Assumptions'!$B$7,'02 AP Transactions'!F8<'01 Assumptions'!$B$6,COUNTIFS('02 AP Transactions'!$B$5:$B$26,'02 AP Transactions'!B8,'02 AP Transactions'!$E$5:$E$26,'02 AP Transactions'!E8)>1),1,0) -> 0 | K8: =IF(I8=1,"Bank-change fraud",IF(F8=1,"Duplicate payment",IF(G8>0,"Overbilling (3-way)",IF(J8=1,"Split / threshold",IF(H8>0,"Lost discount","-"))))) -> - | L8: =IF(I8=1,"High",IF(F8=1,"High",IF(G8>0,"Medium",IF(J8=1,"Medium",IF(H8>0,"Low","-"))))) -> - | M8: =IF(I8=1,D8,IF(F8=1,D8,IF(G8>0,G8,IF(J8=1,0,IF(H8>0,H8,0))))) -> 0 | N8: =IF(I8=1,"Hold & verify (callback)",IF(F8=1,IF('02 AP Transactions'!O8="Pending","Block payment","Recover / claw back"),IF(G8>0,IF('02 AP Transactions'!O8="Pending","Short-pay to PO/GR","Recover overbilled"),IF(J8=1,"Investigate approval",IF(H8>0,"Fix discount process","-"))))) -> - | O8: ='02 AP Transactions'!O8 -> Paid | P8: =IF(K8="-","","FLAG")
A9: ='02 AP Transactions'!A9 -> T05 | B9: ='02 AP Transactions'!B9 -> PT Energi Pratama | C9: ='02 AP Transactions'!D9 -> INV-EP-133 | D9: ='02 AP Transactions'!F9 -> 1300 | E9: =COUNTIF('02 AP Transactions'!$D$5:$D$26,'02 AP Transactions'!D9) -> 1 | F9: =IF(COUNTIF('02 AP Transactions'!$D$5:$D9,'02 AP Transactions'!D9)>1,1,0) -> 0 | G9: =IF(AND('02 AP Transactions'!G9>0,'02 AP Transactions'!H9>0),MAX(0,'02 AP Transactions'!F9-MIN('02 AP Transactions'!G9,'02 AP Transactions'!H9)),0) -> 0 | H9: =IF(AND('02 AP Transactions'!J9>0,'02 AP Transactions'!L9>'02 AP Transactions'!K9,'02 AP Transactions'!O9="Paid"),'02 AP Transactions'!J9*'02 AP Transactions'!F9,0) -> 0 | I9: =IF('02 AP Transactions'!M9="Yes",1,0) -> 0 | J9: =IF(AND('02 AP Transactions'!F9>='01 Assumptions'!$B$6*'01 Assumptions'!$B$7,'02 AP Transactions'!F9<'01 Assumptions'!$B$6,COUNTIFS('02 AP Transactions'!$B$5:$B$26,'02 AP Transactions'!B9,'02 AP Transactions'!$E$5:$E$26,'02 AP Transactions'!E9)>1),1,0) -> 0 | K9: =IF(I9=1,"Bank-change fraud",IF(F9=1,"Duplicate payment",IF(G9>0,"Overbilling (3-way)",IF(J9=1,"Split / threshold",IF(H9>0,"Lost discount","-"))))) -> - | L9: =IF(I9=1,"High",IF(F9=1,"High",IF(G9>0,"Medium",IF(J9=1,"Medium",IF(H9>0,"Low","-"))))) -> - | M9: =IF(I9=1,D9,IF(F9=1,D9,IF(G9>0,G9,IF(J9=1,0,IF(H9>0,H9,0))))) -> 0 | N9: =IF(I9=1,"Hold & verify (callback)",IF(F9=1,IF('02 AP Transactions'!O9="Pending","Block payment","Recover / claw back"),IF(G9>0,IF('02 AP Transactions'!O9="Pending","Short-pay to PO/GR","Recover overbilled"),IF(J9=1,"Investigate approval",IF(H9>0,"Fix discount process","-"))))) -> - | O9: ='02 AP Transactions'!O9 -> Paid | P9: =IF(K9="-","","FLAG")
A10: ='02 AP Transactions'!A10 -> T06 | B10: ='02 AP Transactions'!B10 -> Shenzhen Micro Ltd | C10: ='02 AP Transactions'!D10 -> INV-8801 | D10: ='02 AP Transactions'!F10 -> 1850 | E10: =COUNTIF('02 AP Transactions'!$D$5:$D$26,'02 AP Transactions'!D10) -> 2 | F10: =IF(COUNTIF('02 AP Transactions'!$D$5:$D10,'02 AP Transactions'!D10)>1,1,0) -> 0 | G10: =IF(AND('02 AP Transactions'!G10>0,'02 AP Transactions'!H10>0),MAX(0,'02 AP Transactions'!F10-MIN('02 AP Transactions'!G10,'02 AP Transactions'!H10)),0) -> 0 | H10: =IF(AND('02 AP Transactions'!J10>0,'02 AP Transactions'!L10>'02 AP Transactions'!K10,'02 AP Transactions'!O10="Paid"),'02 AP Transactions'!J10*'02 AP Transactions'!F10,0) -> 0 | I10: =IF('02 AP Transactions'!M10="Yes",1,0) -> 0 | J10: =IF(AND('02 AP Transactions'!F10>='01 Assumptions'!$B$6*'01 Assumptions'!$B$7,'02 AP Transactions'!F10<'01 Assumptions'!$B$6,COUNTIFS('02 AP Transactions'!$B$5:$B$26,'02 AP Transactions'!B10,'02 AP Transactions'!$E$5:$E$26,'02 AP Transactions'!E10)>1),1,0) -> 0 | K10: =IF(I10=1,"Bank-change fraud",IF(F10=1,"Duplicate payment",IF(G10>0,"Overbilling (3-way)",IF(J10=1,"Split / threshold",IF(H10>0,"Lost discount","-"))))) -> - | L10: =IF(I10=1,"High",IF(F10=1,"High",IF(G10>0,"Medium",IF(J10=1,"Medium",IF(H10>0,"Low","-"))))) -> - | M10: =IF(I10=1,D10,IF(F10=1,D10,IF(G10>0,G10,IF(J10=1,0,IF(H10>0,H10,0))))) -> 0 | N10: =IF(I10=1,"Hold & verify (callback)",IF(F10=1,IF('02 AP Transactions'!O10="Pending","Block payment","Recover / claw back"),IF(G10>0,IF('02 AP Transactions'!O10="Pending","Short-pay to PO/GR","Recover overbilled"),IF(J10=1,"Investigate approval",IF(H10>0,"Fix discount process","-"))))) -> - | O10: ='02 AP Transactions'!O10 -> Paid | P10: =IF(K10="-","","FLAG")
A11: ='02 AP Transactions'!A11 -> T07 | B11: ='02 AP Transactions'!B11 -> Shenzhen Micro Ltd | C11: ='02 AP Transactions'!D11 -> INV-8801 | D11: ='02 AP Transactions'!F11 -> 1850 | E11: =COUNTIF('02 AP Transactions'!$D$5:$D$26,'02 AP Transactions'!D11) -> 2 | F11: =IF(COUNTIF('02 AP Transactions'!$D$5:$D11,'02 AP Transactions'!D11)>1,1,0) -> 1 | G11: =IF(AND('02 AP Transactions'!G11>0,'02 AP Transactions'!H11>0),MAX(0,'02 AP Transactions'!F11-MIN('02 AP Transactions'!G11,'02 AP Transactions'!H11)),0) -> 0 | H11: =IF(AND('02 AP Transactions'!J11>0,'02 AP Transactions'!L11>'02 AP Transactions'!K11,'02 AP Transactions'!O11="Paid"),'02 AP Transactions'!J11*'02 AP Transactions'!F11,0) -> 0 | I11: =IF('02 AP Transactions'!M11="Yes",1,0) -> 0 | J11: =IF(AND('02 AP Transactions'!F11>='01 Assumptions'!$B$6*'01 Assumptions'!$B$7,'02 AP Transactions'!F11<'01 Assumptions'!$B$6,COUNTIFS('02 AP Transactions'!$B$5:$B$26,'02 AP Transactions'!B11,'02 AP Transactions'!$E$5:$E$26,'02 AP Transactions'!E11)>1),1,0) -> 0 | K11: =IF(I11=1,"Bank-change fraud",IF(F11=1,"Duplicate payment",IF(G11>0,"Overbilling (3-way)",IF(J11=1,"Split / threshold",IF(H11>0,"Lost discount","-"))))) -> Duplicate payment | L11: =IF(I11=1,"High",IF(F11=1,"High",IF(G11>0,"Medium",IF(J11=1,"Medium",IF(H11>0,"Low","-"))))) -> High | M11: =IF(I11=1,D11,IF(F11=1,D11,IF(G11>0,G11,IF(J11=1,0,IF(H11>0,H11,0))))) -> 1850 | N11: =IF(I11=1,"Hold & verify (callback)",IF(F11=1,IF('02 AP Transactions'!O11="Pending","Block payment","Recover / claw back"),IF(G11>0,IF('02 AP Transactions'!O11="Pending","Short-pay to PO/GR","Recover overbilled"),IF(J11=1,"Investigate approval",IF(H11>0,"Fix discount process","-"))))) -> Recover / claw back | O11: ='02 AP Transactions'!O11 -> Paid | P11: =IF(K11="-","","FLAG") -> FLAG
A12: ='02 AP Transactions'!A12 -> T08 | B12: ='02 AP Transactions'!B12 -> Taipei Semicon Co | C12: ='02 AP Transactions'!D12 -> INV-TS-551 | D12: ='02 AP Transactions'!F12 -> 3200 | E12: =COUNTIF('02 AP Transactions'!$D$5:$D$26,'02 AP Transactions'!D12) -> 1 | F12: =IF(COUNTIF('02 AP Transactions'!$D$5:$D12,'02 AP Transactions'!D12)>1,1,0) -> 0 | G12: =IF(AND('02 AP Transactions'!G12>0,'02 AP Transactions'!H12>0),MAX(0,'02 AP Transactions'!F12-MIN('02 AP Transactions'!G12,'02 AP Transactions'!H12)),0) -> 400 | H12: =IF(AND('02 AP Transactions'!J12>0,'02 AP Transactions'!L12>'02 AP Transactions'!K12,'02 AP Transactions'!O12="Paid"),'02 AP Transactions'!J12*'02 AP Transactions'!F12,0) -> 0 | I12: =IF('02 AP Transactions'!M12="Yes",1,0) -> 0 | J12: =IF(AND('02 AP Transactions'!F12>='01 Assumptions'!$B$6*'01 Assumptions'!$B$7,'02 AP Transactions'!F12<'01 Assumptions'!$B$6,COUNTIFS('02 AP Transactions'!$B$5:$B$26,'02 AP Transactions'!B12,'02 AP Transactions'!$E$5:$E$26,'02 AP Transactions'!E12)>1),1,0) -> 0 | K12: =IF(I12=1,"Bank-change fraud",IF(F12=1,"Duplicate payment",IF(G12>0,"Overbilling (3-way)",IF(J12=1,"Split / threshold",IF(H12>0,"Lost discount","-"))))) -> Overbilling (3-way) | L12: =IF(I12=1,"High",IF(F12=1,"High",IF(G12>0,"Medium",IF(J12=1,"Medium",IF(H12>0,"Low","-"))))) -> Medium | M12: =IF(I12=1,D12,IF(F12=1,D12,IF(G12>0,G12,IF(J12=1,0,IF(H12>0,H12,0))))) -> 400 | N12: =IF(I12=1,"Hold & verify (callback)",IF(F12=1,IF('02 AP Transactions'!O12="Pending","Block payment","Recover / claw back"),IF(G12>0,IF('02 AP Transactions'!O12="Pending","Short-pay to PO/GR","Recover overbilled"),IF(J12=1,"Investigate approval",IF(H12>0,"Fix discount process","-"))))) -> Recover overbilled | O12: ='02 AP Transactions'!O12 -> Paid | P12: =IF(K12="-","","FLAG") -> FLAG
A13: ='02 AP Transactions'!A13 -> T09 | B13: ='02 AP Transactions'!B13 -> Osaka Precision KK | C13: ='02 AP Transactions'!D13 -> INV-OP-330 | D13: ='02 AP Transactions'!F13 -> 4500 | E13: =COUNTIF('02 AP Transactions'!$D$5:$D$26,'02 AP Transactions'!D13) -> 1 | F13: =IF(COUNTIF('02 AP Transactions'!$D$5:$D13,'02 AP Transactions'!D13)>1,1,0) -> 0 | G13: =IF(AND('02 AP Transactions'!G13>0,'02 AP Transactions'!H13>0),MAX(0,'02 AP Transactions'!F13-MIN('02 AP Transactions'!G13,'02 AP Transactions'!H13)),0) -> 500 | H13: =IF(AND('02 AP Transactions'!J13>0,'02 AP Transactions'!L13>'02 AP Transactions'!K13,'02 AP Transactions'!O13="Paid"),'02 AP Transactions'!J13*'02 AP Transactions'!F13,0) -> 0 | I13: =IF('02 AP Transactions'!M13="Yes",1,0) -> 0 | J13: =IF(AND('02 AP Transactions'!F13>='01 Assumptions'!$B$6*'01 Assumptions'!$B$7,'02 AP Transactions'!F13<'01 Assumptions'!$B$6,COUNTIFS('02 AP Transactions'!$B$5:$B$26,'02 AP Transactions'!B13,'02 AP Transactions'!$E$5:$E$26,'02 AP Transactions'!E13)>1),1,0) -> 0 | K13: =IF(I13=1,"Bank-change fraud",IF(F13=1,"Duplicate payment",IF(G13>0,"Overbilling (3-way)",IF(J13=1,"Split / threshold",IF(H13>0,"Lost discount","-"))))) -> Overbilling (3-way) | L13: =IF(I13=1,"High",IF(F13=1,"High",IF(G13>0,"Medium",IF(J13=1,"Medium",IF(H13>0,"Low","-"))))) -> Medium | M13: =IF(I13=1,D13,IF(F13=1,D13,IF(G13>0,G13,IF(J13=1,0,IF(H13>0,H13,0))))) -> 500 | N13: =IF(I13=1,"Hold & verify (callback)",IF(F13=1,IF('02 AP Transactions'!O13="Pending","Block payment","Recover / claw back"),IF(G13>0,IF('02 AP Transactions'!O13="Pending","Short-pay to PO/GR","Recover overbilled"),IF(J13=1,"Investigate approval",IF(H13>0,"Fix discount process","-"))))) -> Short-pay to PO/GR | O13: ='02 AP Transactions'!O13 -> Pending | P13: =IF(K13="-","","FLAG") -> FLAG
A14: ='02 AP Transactions'!A14 -> T10 | B14: ='02 AP Transactions'!B14 -> PT Logistik Andalan | C14: ='02 AP Transactions'!D14 -> INV-LA-110 | D14: ='02 AP Transactions'!F14 -> 2000 | E14: =COUNTIF('02 AP Transactions'!$D$5:$D$26,'02 AP Transactions'!D14) -> 1 | F14: =IF(COUNTIF('02 AP Transactions'!$D$5:$D14,'02 AP Transactions'!D14)>1,1,0) -> 0 | G14: =IF(AND('02 AP Transactions'!G14>0,'02 AP Transactions'!H14>0),MAX(0,'02 AP Transactions'!F14-MIN('02 AP Transactions'!G14,'02 AP Transactions'!H14)),0) -> 0 | H14: =IF(AND('02 AP Transactions'!J14>0,'02 AP Transactions'!L14>'02 AP Transactions'!K14,'02 AP Transactions'!O14="Paid"),'02 AP Transactions'!J14*'02 AP Transactions'!F14,0) -> 40 | I14: =IF('02 AP Transactions'!M14="Yes",1,0) -> 0 | J14: =IF(AND('02 AP Transactions'!F14>='01 Assumptions'!$B$6*'01 Assumptions'!$B$7,'02 AP Transactions'!F14<'01 Assumptions'!$B$6,COUNTIFS('02 AP Transactions'!$B$5:$B$26,'02 AP Transactions'!B14,'02 AP Transactions'!$E$5:$E$26,'02 AP Transactions'!E14)>1),1,0) -> 0 | K14: =IF(I14=1,"Bank-change fraud",IF(F14=1,"Duplicate payment",IF(G14>0,"Overbilling (3-way)",IF(J14=1,"Split / threshold",IF(H14>0,"Lost discount","-"))))) -> Lost discount | L14: =IF(I14=1,"High",IF(F14=1,"High",IF(G14>0,"Medium",IF(J14=1,"Medium",IF(H14>0,"Low","-"))))) -> Low | M14: =IF(I14=1,D14,IF(F14=1,D14,IF(G14>0,G14,IF(J14=1,0,IF(H14>0,H14,0))))) -> 40 | N14: =IF(I14=1,"Hold & verify (callback)",IF(F14=1,IF('02 AP Transactions'!O14="Pending","Block payment","Recover / claw back"),IF(G14>0,IF('02 AP Transactions'!O14="Pending","Short-pay to PO/GR","Recover overbilled"),IF(J14=1,"Investigate approval",IF(H14>0,"Fix discount process","-"))))) -> Fix discount process | O14: ='02 AP Transactions'!O14 -> Paid | P14: =IF(K14="-","","FLAG") -> FLAG
A15: ='02 AP Transactions'!A15 -> T11 | B15: ='02 AP Transactions'!B15 -> PT Energi Pratama | C15: ='02 AP Transactions'!D15 -> INV-EP-140 | D15: ='02 AP Transactions'!F15 -> 1500 | E15: =COUNTIF('02 AP Transactions'!$D$5:$D$26,'02 AP Transactions'!D15) -> 1 | F15: =IF(COUNTIF('02 AP Transactions'!$D$5:$D15,'02 AP Transactions'!D15)>1,1,0) -> 0 | G15: =IF(AND('02 AP Transactions'!G15>0,'02 AP Transactions'!H15>0),MAX(0,'02 AP Transactions'!F15-MIN('02 AP Transactions'!G15,'02 AP Transactions'!H15)),0) -> 0 | H15: =IF(AND('02 AP Transactions'!J15>0,'02 AP Transactions'!L15>'02 AP Transactions'!K15,'02 AP Transactions'!O15="Paid"),'02 AP Transactions'!J15*'02 AP Transactions'!F15,0) -> 30 | I15: =IF('02 AP Transactions'!M15="Yes",1,0) -> 0 | J15: =IF(AND('02 AP Transactions'!F15>='01 Assumptions'!$B$6*'01 Assumptions'!$B$7,'02 AP Transactions'!F15<'01 Assumptions'!$B$6,COUNTIFS('02 AP Transactions'!$B$5:$B$26,'02 AP Transactions'!B15,'02 AP Transactions'!$E$5:$E$26,'02 AP Transactions'!E15)>1),1,0) -> 0 | K15: =IF(I15=1,"Bank-change fraud",IF(F15=1,"Duplicate payment",IF(G15>0,"Overbilling (3-way)",IF(J15=1,"Split / threshold",IF(H15>0,"Lost discount","-"))))) -> Lost discount | L15: =IF(I15=1,"High",IF(F15=1,"High",IF(G15>0,"Medium",IF(J15=1,"Medium",IF(H15>0,"Low","-"))))) -> Low | M15: =IF(I15=1,D15,IF(F15=1,D15,IF(G15>0,G15,IF(J15=1,0,IF(H15>0,H15,0))))) -> 30 | N15: =IF(I15=1,"Hold & verify (callback)",IF(F15=1,IF('02 AP Transactions'!O15="Pending","Block payment","Recover / claw back"),IF(G15>0,IF('02 AP Transactions'!O15="Pending","Short-pay to PO/GR","Recover overbilled"),IF(J15=1,"Investigate approval",IF(H15>0,"Fix discount process","-"))))) -> Fix discount process | O15: ='02 AP Transactions'!O15 -> Paid | P15: =IF(K15="-","","FLAG") -> FLAG
A16: ='02 AP Transactions'!A16 -> T12 | B16: ='02 AP Transactions'!B16 -> PT Bahan Baku Lokal | C16: ='02 AP Transactions'!D16 -> INV-BBL-260 | D16: ='02 AP Transactions'!F16 -> 2500 | E16: =COUNTIF('02 AP Transactions'!$D$5:$D$26,'02 AP Transactions'!D16) -> 1 | F16: =IF(COUNTIF('02 AP Transactions'!$D$5:$D16,'02 AP Transactions'!D16)>1,1,0) -> 0 | G16: =IF(AND('02 AP Transactions'!G16>0,'02 AP Transactions'!H16>0),MAX(0,'02 AP Transactions'!F16-MIN('02 AP Transactions'!G16,'02 AP Transactions'!H16)),0) -> 0 | H16: =IF(AND('02 AP Transactions'!J16>0,'02 AP Transactions'!L16>'02 AP Transactions'!K16,'02 AP Transactions'!O16="Paid"),'02 AP Transactions'!J16*'02 AP Transactions'!F16,0) -> 25 | I16: =IF('02 AP Transactions'!M16="Yes",1,0) -> 0 | J16: =IF(AND('02 AP Transactions'!F16>='01 Assumptions'!$B$6*'01 Assumptions'!$B$7,'02 AP Transactions'!F16<'01 Assumptions'!$B$6,COUNTIFS('02 AP Transactions'!$B$5:$B$26,'02 AP Transactions'!B16,'02 AP Transactions'!$E$5:$E$26,'02 AP Transactions'!E16)>1),1,0) -> 0 | K16: =IF(I16=1,"Bank-change fraud",IF(F16=1,"Duplicate payment",IF(G16>0,"Overbilling (3-way)",IF(J16=1,"Split / threshold",IF(H16>0,"Lost discount","-"))))) -> Lost discount | L16: =IF(I16=1,"High",IF(F16=1,"High",IF(G16>0,"Medium",IF(J16=1,"Medium",IF(H16>0,"Low","-"))))) -> Low | M16: =IF(I16=1,D16,IF(F16=1,D16,IF(G16>0,G16,IF(J16=1,0,IF(H16>0,H16,0))))) -> 25 | N16: =IF(I16=1,"Hold & verify (callback)",IF(F16=1,IF('02 AP Transactions'!O16="Pending","Block payment","Recover / claw back"),IF(G16>0,IF('02 AP Transactions'!O16="Pending","Short-pay to PO/GR","Recover overbilled"),IF(J16=1,"Investigate approval",IF(H16>0,"Fix discount process","-"))))) -> Fix discount process | O16: ='02 AP Transactions'!O16 -> Paid | P16: =IF(K16="-","","FLAG") -> FLAG
... A26: ='02 AP Transactions'!A26 -> T22 | B26: ='02 AP Transactions'!B26 -> PT Energi Pratama | C26: ='02 AP Transactions'!D26 -> INV-EP-155 | D26: ='02 AP Transactions'!F26 -> 1250 | E26: =COUNTIF('02 AP Transactions'!$D$5:$D$26,'02 AP Transactions'!D26) -> 1 | F26: =IF(COUNTIF('02 AP Transactions'!$D$5:$D26,'02 AP Transactions'!D26)>1,1,0) -> 0 | G26: =IF(AND('02 AP Transactions'!G26>0,'02 AP Transactions'!H26>0),MAX(0,'02 AP Transactions'!F26-MIN('02 AP Transactions'!G26,'02 AP Transactions'!H26)),0) -> 0 | H26: =IF(AND('02 AP Transactions'!J26>0,'02 AP Transactions'!L26>'02 AP Transactions'!K26,'02 AP Transactions'!O26="Paid"),'02 AP Transactions'!J26*'02 AP Transactions'!F26,0) -> 0 | I26: =IF('02 AP Transactions'!M26="Yes",1,0) -> 0 | J26: =IF(AND('02 AP Transactions'!F26>='01 Assumptions'!$B$6*'01 Assumptions'!$B$7,'02 AP Transactions'!F26<'01 Assumptions'!$B$6,COUNTIFS('02 AP Transactions'!$B$5:$B$26,'02 AP Transactions'!B26,'02 AP Transactions'!$E$5:$E$26,'02 AP Transactions'!E26)>1),1,0) -> 0 | K26: =IF(I26=1,"Bank-change fraud",IF(F26=1,"Duplicate payment",IF(G26>0,"Overbilling (3-way)",IF(J26=1,"Split / threshold",IF(H26>0,"Lost discount","-"))))) -> - | L26: =IF(I26=1,"High",IF(F26=1,"High",IF(G26>0,"Medium",IF(J26=1,"Medium",IF(H26>0,"Low","-"))))) -> - | M26: =IF(I26=1,D26,IF(F26=1,D26,IF(G26>0,G26,IF(J26=1,0,IF(H26>0,H26,0))))) -> 0 | N26: =IF(I26=1,"Hold & verify (callback)",IF(F26=1,IF('02 AP Transactions'!O26="Pending","Block payment","Recover / claw back"),IF(G26>0,IF('02 AP Transactions'!O26="Pending","Short-pay to PO/GR","Recover overbilled"),IF(J26=1,"Investigate approval",IF(H26>0,"Fix discount process","-"))))) -> - | O26: ='02 AP Transactions'!O26 -> Paid | P26: =IF(K26="-","","FLAG")
A28: How to read it: Dup copy = 1 means a repeat invoice number (the recoverable copy). 3-way gap = billed minus the lower of PO or goods received. Disc lost = discount thrown away by paying late. Bank = 1 means the vendor bank account changed. Split = 1 means an invoice sits just under the approval limit with a same-day sibling.

Sheet 04 Leakage & Fraud Summary
A1: Leakage & Fraud Summary - the found-money number
A2: What the agent found this cycle, and what it means for cash. GREEN = pulled from sheet 03. Units: IDR mn.
A4: HEADLINE
A5: Invoices scanned this cycle | B5: ='01 Assumptions'!$B$5 -> 1850
A6: Items flagged | B6: =COUNTIF('03 Anomaly Detection'!$P$5:$P$26,"FLAG") -> 10
A7: Flag rate | B7: =B6/B5 -> 0.0054054054
A8: Total amount at risk found (IDR mn) | B8: =SUM('03 Anomaly Detection'!$M$5:$M$26) -> 7845
A10: WHERE THE MONEY IS
A11: Category | B11: Count | C11: Amount at risk (IDR mn) | D11: Action | E11: Note
A12: Bank-change fraud | B12: =COUNTIF('03 Anomaly Detection'!$K$5:$K$26,A12) -> 1 | C12: =SUMIF('03 Anomaly Detection'!$K$5:$K$26,A12,'03 Anomaly Detection'!$M$5:$M$26) -> 3800 | D12: Hold & verify before paying | E12: Classic fraud pattern. Highest priority.
A13: Duplicate payment | B13: =COUNTIF('03 Anomaly Detection'!$K$5:$K$26,A13) -> 2 | C13: =SUMIF('03 Anomaly Detection'!$K$5:$K$26,A13,'03 Anomaly Detection'!$M$5:$M$26) -> 3050 | D13: Recover / block | E13: Cash paid twice, or about to be.
A14: Overbilling (3-way) | B14: =COUNTIF('03 Anomaly Detection'!$K$5:$K$26,A14) -> 2 | C14: =SUMIF('03 Anomaly Detection'!$K$5:$K$26,A14,'03 Anomaly Detection'!$M$5:$M$26) -> 900 | D14: Recover / short-pay | E14: Billed above PO or goods received.
A15: Lost discount | B15: =COUNTIF('03 Anomaly Detection'!$K$5:$K$26,A15) -> 3 | C15: =SUMIF('03 Anomaly Detection'!$K$5:$K$26,A15,'03 Anomaly Detection'!$M$5:$M$26) -> 95 | D15: Fix the process | E15: Small each time, adds up over a year.
A16: Split / threshold | B16: =COUNTIF('03 Anomaly Detection'!$K$5:$K$26,A16) -> 2 | C16: =SUMIF('03 Anomaly Detection'!$K$5:$K$26,A16,'03 Anomaly Detection'!$D$5:$D$26) -> 1950 | D16: Investigate approval | E16: Control weakness, not a direct loss.
A17: (Split value shown is invoice value under review, not a direct loss, so it is not in the totals below.)
A19: WHAT IT MEANS FOR CASH
A20: Blocked before payment (preventable) | B20: =SUMIF('03 Anomaly Detection'!$O$5:$O$26,"Pending",'03 Anomaly Detection'!$M$5:$M$26) -> 4300 | C20: Held or short-paid before cash left the building.
A21: Recoverable (already paid) | B21: =SUMIFS('03 Anomaly Detection'!$M$5:$M$26,'03 Anomaly Detection'!$K$5:$K$26,"Duplicate payment",'03 Anomaly Detection'!$O$5:$O$26,"Paid")+SUMIFS('03 Anomaly Detection'!$M$5:$M$26,'03 Anomaly Detection'!$K$5:$K$26,"Overbilling (3-way)",'03 Anomaly Detection'!$O$5:$O$26,"Paid") -> 3450 | C21: Claw back via vendor debit note or credit.
A22: Expected recovered (after recovery rates) | B22: =SUMIFS('03 Anomaly Detection'!$M$5:$M$26,'03 Anomaly Detection'!$K$5:$K$26,"Duplicate payment",'03 Anomaly Detection'!$O$5:$O$26,"Paid")*'01 Assumptions'!$B$11+SUMIFS('03 Anomaly Detection'!$M$5:$M$26,'03 Anomaly Detection'!$K$5:$K$26,"Overbilling (3-way)",'03 Anomaly Detection'!$O$5:$O$26,"Paid")*'01 Assumptions'!$B$12 -> 3257.5 | C22: Recovery is not 100%. Rates are on sheet 01 (illustrative).
A23: Lost this cycle (discounts, not recoverable) | B23: =SUMIF('03 Anomaly Detection'!$K$5:$K$26,"Lost discount",'03 Anomaly Detection'!$M$5:$M$26) -> 95
A24: Total cash protected (blocked + expected recovered) | B24: =B20+B22 -> 7557.5
A26: FORWARD VIEW (illustrative)
A27: Annualised discount leakage if unfixed (IDR mn) | B27: =B23/'01 Assumptions'!$B$14*'01 Assumptions'!$B$13 -> 2470 | C27: Assumes the sample rate holds all year. Weak assumption. Use to size the prevention prize, not as a promise.

Sheet 05 Action Worklist
A1: Agent Action Worklist - what to do, in order
A2: Flagged items ranked by amount at risk and severity. GREEN = pulled from sheet 03. Work the top of the list first: block the fraud, recover the duplicates, then fix the rest.
A4: Rank | B4: Txn | C4: Vendor | D4: Invoice no | E4: Anomaly type | F4: Severity | G4: Amount at risk | H4: Status | I4: Recommended action | J4: Owner
A5: 1 | B5: ='03 Anomaly Detection'!A17 -> T13 | C5: ='03 Anomaly Detection'!B17 -> Osaka Precision KK | D5: ='03 Anomaly Detection'!C17 -> INV-OP-345 | E5: ='03 Anomaly Detection'!K17 -> Bank-change fraud | F5: ='03 Anomaly Detection'!L17 -> High | G5: ='03 Anomaly Detection'!M17 -> 3800 | H5: ='03 Anomaly Detection'!O17 -> Pending | I5: ='03 Anomaly Detection'!N17 -> Hold & verify (callback) | J5: Treasury + CFO
A6: 2 | B6: ='03 Anomaly Detection'!A11 -> T07 | C6: ='03 Anomaly Detection'!B11 -> Shenzhen Micro Ltd | D6: ='03 Anomaly Detection'!C11 -> INV-8801 | E6: ='03 Anomaly Detection'!K11 -> Duplicate payment | F6: ='03 Anomaly Detection'!L11 -> High | G6: ='03 Anomaly Detection'!M11 -> 1850 | H6: ='03 Anomaly Detection'!O11 -> Paid | I6: ='03 Anomaly Detection'!N11 -> Recover / claw back | J6: AP + Controller
A7: 3 | B7: ='03 Anomaly Detection'!A19 -> T15 | C7: ='03 Anomaly Detection'!B19 -> PT Bahan Baku Lokal (cabang) | D7: ='03 Anomaly Detection'!C19 -> INV-BBL-220 | E7: ='03 Anomaly Detection'!K19 -> Duplicate payment | F7: ='03 Anomaly Detection'!L19 -> High | G7: ='03 Anomaly Detection'!M19 -> 1200 | H7: ='03 Anomaly Detection'!O19 -> Paid | I7: ='03 Anomaly Detection'!N19 -> Recover / claw back | J7: AP + Controller
A8: 4 | B8: ='03 Anomaly Detection'!A13 -> T09 | C8: ='03 Anomaly Detection'!B13 -> Osaka Precision KK | D8: ='03 Anomaly Detection'!C13 -> INV-OP-330 | E8: ='03 Anomaly Detection'!K13 -> Overbilling (3-way) | F8: ='03 Anomaly Detection'!L13 -> Medium | G8: ='03 Anomaly Detection'!M13 -> 500 | H8: ='03 Anomaly Detection'!O13 -> Pending | I8: ='03 Anomaly Detection'!N13 -> Short-pay to PO/GR | J8: AP + Controller
A9: 5 | B9: ='03 Anomaly Detection'!A12 -> T08 | C9: ='03 Anomaly Detection'!B12 -> Taipei Semicon Co | D9: ='03 Anomaly Detection'!C12 -> INV-TS-551 | E9: ='03 Anomaly Detection'!K12 -> Overbilling (3-way) | F9: ='03 Anomaly Detection'!L12 -> Medium | G9: ='03 Anomaly Detection'!M12 -> 400 | H9: ='03 Anomaly Detection'!O12 -> Paid | I9: ='03 Anomaly Detection'!N12 -> Recover overbilled | J9: AP + Controller
A10: 6 | B10: ='03 Anomaly Detection'!A14 -> T10 | C10: ='03 Anomaly Detection'!B14 -> PT Logistik Andalan | D10: ='03 Anomaly Detection'!C14 -> INV-LA-110 | E10: ='03 Anomaly Detection'!K14 -> Lost discount | F10: ='03 Anomaly Detection'!L14 -> Low | G10: ='03 Anomaly Detection'!M14 -> 40 | H10: ='03 Anomaly Detection'!O14 -> Paid | I10: ='03 Anomaly Detection'!N14 -> Fix discount process | J10: AP process
A11: 7 | B11: ='03 Anomaly Detection'!A15 -> T11 | C11: ='03 Anomaly Detection'!B15 -> PT Energi Pratama | D11: ='03 Anomaly Detection'!C15 -> INV-EP-140 | E11: ='03 Anomaly Detection'!K15 -> Lost discount | F11: ='03 Anomaly Detection'!L15 -> Low | G11: ='03 Anomaly Detection'!M15 -> 30 | H11: ='03 Anomaly Detection'!O15 -> Paid | I11: ='03 Anomaly Detection'!N15 -> Fix discount process | J11: AP process
A12: 8 | B12: ='03 Anomaly Detection'!A16 -> T12 | C12: ='03 Anomaly Detection'!B16 -> PT Bahan Baku Lokal | D12: ='03 Anomaly Detection'!C16 -> INV-BBL-260 | E12: ='03 Anomaly Detection'!K16 -> Lost discount | F12: ='03 Anomaly Detection'!L16 -> Low | G12: ='03 Anomaly Detection'!M16 -> 25 | H12: ='03 Anomaly Detection'!O16 -> Paid | I12: ='03 Anomaly Detection'!N16 -> Fix discount process | J12: AP process
A13: 9 | B13: ='03 Anomaly Detection'!A20 -> T16 | C13: ='03 Anomaly Detection'!B20 -> PT Kemasan Prima | D13: ='03 Anomaly Detection'!C20 -> INV-KP-501 | E13: ='03 Anomaly Detection'!K20 -> Split / threshold | F13: ='03 Anomaly Detection'!L20 -> Medium | G13: ='03 Anomaly Detection'!M20 -> 0 | H13: ='03 Anomaly Detection'!O20 -> Paid | I13: ='03 Anomaly Detection'!N20 -> Investigate approval | J13: Internal audit
A14: 10 | B14: ='03 Anomaly Detection'!A21 -> T17 | C14: ='03 Anomaly Detection'!B21 -> PT Kemasan Prima | D14: ='03 Anomaly Detection'!C21 -> INV-KP-502 | E14: ='03 Anomaly Detection'!K21 -> Split / threshold | F14: ='03 Anomaly Detection'!L21 -> Medium | G14: ='03 Anomaly Detection'!M21 -> 0 | H14: ='03 Anomaly Detection'!O21 -> Paid | I14: ='03 Anomaly Detection'!N21 -> Investigate approval | J14: Internal audit
C15: TOTAL amount at risk (flagged) | G15: =SUM(G5:G14) -> 7845
A17: Split-invoice items show 0 amount at risk because they are a control flag, not a direct loss. They still need an approval review.

Sheet 06 Recommendation
A1: Agent Recommendation & CFO Decision Card
A2: What the agent recommends, why, and the impact, pulled live from sheet 04. Recovery journals are illustrative and need Controller sign-off.
A4: SITUATION (this scan cycle)
A5: Total amount at risk found (IDR mn) | B5: ='04 Leakage & Fraud Summary'!B8 -> 7845
A6: Suspected fraud held (IDR mn) | B6: =SUMIF('03 Anomaly Detection'!$K$5:$K$26,"Bank-change fraud",'03 Anomaly Detection'!$M$5:$M$26) -> 3800
A7: Duplicate payments found (IDR mn) | B7: =SUMIF('03 Anomaly Detection'!$K$5:$K$26,"Duplicate payment",'03 Anomaly Detection'!$M$5:$M$26) -> 3050
A8: Blocked before payment (IDR mn) | B8: ='04 Leakage & Fraud Summary'!B20 -> 4300
A9: Total cash protected (IDR mn) | B9: ='04 Leakage & Fraud Summary'!B24 -> 7557.5
A11: RECOMMENDATION - three moves
A12: 1) STOP (before cash leaves)
A13: - Hold the Osaka Precision payment where the bank account changed | C13: IDR 3,800 mn, pending. Verify by phone callback to a known number | E13: Blocks a likely fraud
A14: - Short-pay the overbilled pending invoice to PO / goods received | C14: Osaka INV-OP-330, pay 4,000 not 4,500 | E14: Saves 500 mn now
A16: 2) RECOVER (already paid)
A17: - Claw back the two duplicate payments | C17: Shenzhen INV-8801 paid twice; the BBL invoice paid on a duplicate vendor record | E17: Recovers ~3,050 mn
A18: - Recover the overbilled paid invoice | C18: Taipei INV-TS-551, billed 3,200 vs PO 2,800 | E18: Recovers 400 mn
A19: - Raise vendor debit notes for all recoveries | C19: Net against the next payment run | E19: Fast, low friction
A21: 3) PREVENT (fix the root cause)
A22: - Merge the duplicate vendor master record | C22: PT Bahan Baku Lokal set up twice enabled a duplicate | E22: Removes the loophole
A23: - Turn on duplicate-invoice and 3-way match blocks | C23: Stop the payment before it posts | E23: Prevents repeats
A24: - Require callback verification for any bank-account change | C24: No change is trusted without a callback | E24: Stops BEC fraud
A25: - Fix the discount-capture process | C25: Pay within the discount window | E25: Saves ~see sheet 04 annualised
A27: EXPECTED IMPACT (calculated)
A28: Cash blocked before payment (IDR mn) | B28: ='04 Leakage & Fraud Summary'!B20 -> 4300
A29: Expected recovered from paid items (IDR mn) | B29: ='04 Leakage & Fraud Summary'!B22 -> 3257.5
A30: Total cash protected (IDR mn) | B30: ='04 Leakage & Fraud Summary'!B24 -> 7557.5
A32: CFO DECISION CARD
A33: Requested by: Payment Leakage & Fraud Agent | Approval: CFO + AP / Controller (dual control)
A34: [ Approve holds ] [ Approve recoveries ] [ Approve control changes ] [ Modify ] [ Ask why ] [ Reject ]
A36: ILLUSTRATIVE RECOVERY JOURNAL - NEEDS CONTROLLER SIGN-OFF
A37: To reverse a duplicate payment already made (simplified, illustrative only):
A38: Dr | B38: Bank / vendor receivable (recovery due) | E38: duplicate amount
A39: Cr | B39: Accounts payable / expense (reverse the double) | E39: same amount
A40: Recovery depends on vendor agreement. A suspected fraud may need bank and legal involvement. Confirm all entries with the Controller before acting.
